Workbook
Name DMB: #REF!

Sheet MPR Review
C2: Month | D2: 46023
C4: ="Current Month-Year " & ":" & TEXT(TODAY(),"YYYY-MM") -> Current Month-Year :2026-09
A5: Strategic Imperative | C5: Mandatory Outcome KPIs | D5: Meric Owner MT | E5: Definition | F5: Operators | G5: AOP 2025 | H5: Units | I5: Metric Nature | J5: Frequency | K5: Target Actual | L5: Jan | M5: Feb | N5: Q1 | O5: Apr | P5: May | Q5: Q2 | R5: Jul | S5: Aug | T5: Q3 | U5: Oct | V5: Nov | W5: Dec | X5: If reported Red then Cause and Actions | Y5: Consecutive Red more han 2 instance please submit PRIDE | Z5: Consecutive Red more than 2 instance and only for PS&Qmetrics share CAPA | AA5: Next Update/Closure timeline DD-MM
A7: 1. Patient Safety & Quality | C7: =IF('1.Quality'!A6<>"",'1.Quality'!A6,"") -> % CAPA Investigations Currently ≤ 90 days | D7: Neena S | E7: =IF('1.Quality'!B6<>"",'1.Quality'!B6,"") -> Timeliness of investigations | F7: =IF('1.Quality'!C6<>"",'1.Quality'!C6,"") -> >= | G7: =IF('1.Quality'!D6<>"",'1.Quality'!D6,"") -> 90 | H7: =IF('1.Quality'!E6<>"",'1.Quality'!E6,"") -> % | I7: =IF('1.Quality'!F6<>"",'1.Quality'!F6,"") -> Higher the better | J7: =IF('1.Quality'!G6<>"",'1.Quality'!G6,"") -> Monthly | K7: Target | L7: =IF('1.Quality'!I24<>"",'1.Quality'!I24,"") -> 0 | M7: =IF('1.Quality'!J24<>"",'1.Quality'!J24,"") -> 0 | N7: =IF('1.Quality'!K24<>"",'1.Quality'!K24,"") -> 0 | O7: =IF('1.Quality'!L24<>"",'1.Quality'!L24,"") -> 0 | P7: =IF('1.Quality'!M24<>"",'1.Quality'!M24,"") -> 0 | Q7: =IF('1.Quality'!N24<>"",'1.Quality'!N24,"") -> 0 | R7: =IF('1.Quality'!O24<>"",'1.Quality'!O24,"") -> 0 | S7: =IF('1.Quality'!P24<>"",'1.Quality'!P24,"") -> 0 | ... W7: =IF('1.Quality'!T24<>"",'1.Quality'!T24,"") -> 0
K8: Actual | L8: =IF('1.Quality'!I25<>"",'1.Quality'!I25,"") -> 0 | M8: =IF('1.Quality'!J25<>"",'1.Quality'!J25,"") -> 0 | N8: =IF('1.Quality'!K25<>"",'1.Quality'!K25,"") -> 0 | O8: =IF('1.Quality'!L25<>"",'1.Quality'!L25,"") -> 0 | P8: =IF('1.Quality'!M25<>"",'1.Quality'!M25,"") -> 0 | Q8: =IF('1.Quality'!N25<>"",'1.Quality'!N25,"") -> 0 | R8: =IF('1.Quality'!O25<>"",'1.Quality'!O25,"") -> 0 | S8: =IF('1.Quality'!P25<>"",'1.Quality'!P25,"") -> 0 | ... W8: =IF('1.Quality'!T25<>"",'1.Quality'!T25,"")
C9: =IF('1.Quality'!A8<>"",'1.Quality'!A8,"") -> % Complaints Open > 90 days | D9: Neena S | E9: =IF('1.Quality'!B8<>"",'1.Quality'!B8,"") -> Measures complaint closures | F9: =IF('1.Quality'!C8<>"",'1.Quality'!C8,"") -> <= | G9: =IF('1.Quality'!D8<>"",'1.Quality'!D8,"") -> Q1 (8%), Q2 (7%) Q3 (6%) Q4 (5%) | H9: =IF('1.Quality'!E8<>"",'1.Quality'!E8,"") -> % | I9: =IF('1.Quality'!F8<>"",'1.Quality'!F8,"") -> Lower the better | J9: =IF('1.Quality'!G8<>"",'1.Quality'!G8,"") -> Monthly | K9: Target | L9: =IF('1.Quality'!I6<>"",'1.Quality'!I6,"") -> 0.9 | M9: =IF('1.Quality'!J6<>"",'1.Quality'!J6,"") -> 0.9 | N9: =IF('1.Quality'!K6<>"",'1.Quality'!K6,"") -> 0.9 | O9: =IF('1.Quality'!L6<>"",'1.Quality'!L6,"") -> 0.9 | P9: =IF('1.Quality'!M6<>"",'1.Quality'!M6,"") -> 0.9 | Q9: =IF('1.Quality'!N6<>"",'1.Quality'!N6,"") -> 0.9 | R9: =IF('1.Quality'!O6<>"",'1.Quality'!O6,"") -> 0.9 | S9: =IF('1.Quality'!P6<>"",'1.Quality'!P6,"") -> 0.9 | ... W9: =IF('1.Quality'!T6<>"",'1.Quality'!T6,"") -> 0.9
K10: Actual | L10: =IF('1.Quality'!I7<>"",'1.Quality'!I7,"") -> 1 | M10: =IF('1.Quality'!J7<>"",'1.Quality'!J7,"") -> 0.75 | N10: =IF('1.Quality'!K7<>"",'1.Quality'!K7,"") -> 0.4 | O10: =IF('1.Quality'!L7<>"",'1.Quality'!L7,"") -> 0 | P10: =IF('1.Quality'!M7<>"",'1.Quality'!M7,"") -> 0 | Q10: =IF('1.Quality'!N7<>"",'1.Quality'!N7,"") -> 0 | R10: =IF('1.Quality'!O7<>"",'1.Quality'!O7,"") -> 1 | S10: =IF('1.Quality'!P7<>"",'1.Quality'!P7,"") -> 1 | ... W10: =IF('1.Quality'!T7<>"",'1.Quality'!T7,"")
C11: =IF('1.Quality'!A16<>"",'1.Quality'!A16,"") -> C&R > Global Due date | D11: Neena S | E11: =IF('1.Quality'!B16<>"",'1.Quality'!B16,"") -> # of C&Rs that are open beyond plan in market | F11: =IF('1.Quality'!C16<>"",'1.Quality'!C16,"") -> <= | G11: =IF('1.Quality'!D16<>"",'1.Quality'!D16,"") -> 3 | H11: =IF('1.Quality'!E16<>"",'1.Quality'!E16,"") -> No. | I11: =IF('1.Quality'!F16<>"",'1.Quality'!F16,"") -> Lower the better | J11: =IF('1.Quality'!G16<>"",'1.Quality'!G16,"") -> Monthly | K11: Target | L11: =IF('1.Quality'!I8<>"",'1.Quality'!I8,"") -> 0.08 | M11: =IF('1.Quality'!J8<>"",'1.Quality'!J8,"") -> 0.08 | N11: =IF('1.Quality'!K8<>"",'1.Quality'!K8,"") -> 0.08 | O11: =IF('1.Quality'!L8<>"",'1.Quality'!L8,"") -> 0.07 | P11: =IF('1.Quality'!M8<>"",'1.Quality'!M8,"") -> 0.07 | Q11: =IF('1.Quality'!N8<>"",'1.Quality'!N8,"") -> 0.07 | R11: =IF('1.Quality'!O8<>"",'1.Quality'!O8,"") -> 0.06 | S11: =IF('1.Quality'!P8<>"",'1.Quality'!P8,"") -> 0.06 | ... W11: =IF('1.Quality'!T8<>"",'1.Quality'!T8,"") -> 0.05
K12: Actual | L12: =IF('1.Quality'!I9<>"",'1.Quality'!I9,"") -> 0.038 | M12: =IF('1.Quality'!J9<>"",'1.Quality'!J9,"") -> 0.038 | N12: =IF('1.Quality'!K9<>"",'1.Quality'!K9,"") -> 0.028 | O12: =IF('1.Quality'!L9<>"",'1.Quality'!L9,"") -> 0.026 | P12: =IF('1.Quality'!M9<>"",'1.Quality'!M9,"") -> 0.026 | Q12: =IF('1.Quality'!N9<>"",'1.Quality'!N9,"") -> 0.03 | R12: =IF('1.Quality'!O9<>"",'1.Quality'!O9,"") -> 0.03 | S12: =IF('1.Quality'!P9<>"",'1.Quality'!P9,"") -> 0.035 | ... W12: =IF('1.Quality'!T9<>"",'1.Quality'!T9,"")
C13: =IF('2.Regulatory'!A6<>"",'2.Regulatory'!A6,"") -> Registrations & re-certifications on time | D13: Sumit K | E13: =IF('2.Regulatory'!B6<>"",'2.Regulatory'!B6,"") -> (Registration approvals and renewals completed on time) *100/ Total number of approvals planned for the month | F13: =IF('2.Regulatory'!C6<>"",'2.Regulatory'!C6,"") -> >= | G13: =IF('2.Regulatory'!D6<>"",'2.Regulatory'!D6,"") -> 0.97 | H13: =IF('2.Regulatory'!E6<>"",'2.Regulatory'!E6,"") -> % | I13: =IF('2.Regulatory'!F6<>"",'2.Regulatory'!F6,"") -> Higher the better | J13: =IF('2.Regulatory'!G6<>"",'2.Regulatory'!G6,"") -> Monthly | K13: Target | L13: =IF('2.Regulatory'!I6<>"",'2.Regulatory'!I6,"") -> 0.97 | M13: =IF('2.Regulatory'!J6<>"",'2.Regulatory'!J6,"") -> 0.97 | N13: =IF('2.Regulatory'!K6<>"",'2.Regulatory'!K6,"") -> 0.97 | O13: =IF('2.Regulatory'!L6<>"",'2.Regulatory'!L6,"") -> 0.97 | P13: =IF('2.Regulatory'!M6<>"",'2.Regulatory'!M6,"") -> 0.97 | Q13: =IF('2.Regulatory'!N6<>"",'2.Regulatory'!N6,"") -> 0.97 | R13: =IF('2.Regulatory'!O6<>"",'2.Regulatory'!O6,"") -> 0.97 | S13: =IF('2.Regulatory'!P6<>"",'2.Regulatory'!P6,"") -> 0.97 | ... W13: =IF('2.Regulatory'!T6<>"",'2.Regulatory'!T6,"") -> 0.97
K14: Actual | L14: =IF('2.Regulatory'!I7<>"",'2.Regulatory'!I7,"") -> 1 | M14: =IF('2.Regulatory'!J7<>"",'2.Regulatory'!J7,"") -> 1 | N14: =IF('2.Regulatory'!K7<>"",'2.Regulatory'!K7,"") -> 1 | O14: =IF('2.Regulatory'!L7<>"",'2.Regulatory'!L7,"") -> 0.66666667 | P14: =IF('2.Regulatory'!M7<>"",'2.Regulatory'!M7,"") -> 1 | Q14: =IF('2.Regulatory'!N7<>"",'2.Regulatory'!N7,"") -> 1 | R14: =IF('2.Regulatory'!O7<>"",'2.Regulatory'!O7,"") -> 1 | S14: =IF('2.Regulatory'!P7<>"",'2.Regulatory'!P7,"") -> 1 | ... W14: =IF('2.Regulatory'!T7<>"",'2.Regulatory'!T7,"")
C15: =IF('2.Regulatory'!A10<>"",'2.Regulatory'!A10,"") -> Submission on Time | D15: Sumit K | E15: =IF('2.Regulatory'!B10<>"",'2.Regulatory'!B10,"") -> (Regulatory submissions executed on time) *100/ Total number of submissions planned for the month | F15: =IF('2.Regulatory'!C10<>"",'2.Regulatory'!C10,"") -> >= | G15: =IF('2.Regulatory'!D10<>"",'2.Regulatory'!D10,"") -> 1 | H15: =IF('2.Regulatory'!E10<>"",'2.Regulatory'!E10,"") -> % | I15: =IF('2.Regulatory'!F10<>"",'2.Regulatory'!F10,"") -> Higher the better | J15: =IF('2.Regulatory'!G10<>"",'2.Regulatory'!G10,"") -> Monthly | K15: Target | L15: =IF('2.Regulatory'!I10<>"",'2.Regulatory'!I10,"") -> 1 | M15: =IF('2.Regulatory'!J10<>"",'2.Regulatory'!J10,"") -> 1 | N15: =IF('2.Regulatory'!K10<>"",'2.Regulatory'!K10,"") -> 1 | O15: =IF('2.Regulatory'!L10<>"",'2.Regulatory'!L10,"") -> 1 | P15: =IF('2.Regulatory'!M10<>"",'2.Regulatory'!M10,"") -> 1 | Q15: =IF('2.Regulatory'!N10<>"",'2.Regulatory'!N10,"") -> 1 | R15: =IF('2.Regulatory'!O10<>"",'2.Regulatory'!O10,"") -> 1 | S15: =IF('2.Regulatory'!P10<>"",'2.Regulatory'!P10,"") -> 1 | ... W15: =IF('2.Regulatory'!T10<>"",'2.Regulatory'!T10,"") -> 1
K16: Actual | L16: =IF('2.Regulatory'!I11<>"",'2.Regulatory'!I11,"") -> 1 | M16: =IF('2.Regulatory'!J11<>"",'2.Regulatory'!J11,"") -> 1 | N16: =IF('2.Regulatory'!K11<>"",'2.Regulatory'!K11,"") -> 1 | O16: =IF('2.Regulatory'!L11<>"",'2.Regulatory'!L11,"") -> 0.91666667 | P16: =IF('2.Regulatory'!M11<>"",'2.Regulatory'!M11,"") -> 1 | Q16: =IF('2.Regulatory'!N11<>"",'2.Regulatory'!N11,"") -> 1 | R16: =IF('2.Regulatory'!O11<>"",'2.Regulatory'!O11,"") -> 1 | S16: =IF('2.Regulatory'!P11<>"",'2.Regulatory'!P11,"") -> 1 | ... W16: =IF('2.Regulatory'!T11<>"",'2.Regulatory'!T11,"")
C17: =IF(#REF!<>"",#REF!,"") -> #REF! | D17: Vinayak P | E17: =IF(#REF!<>"",#REF!,"") -> #REF! | F17: =IF(#REF!<>"",#REF!,"") -> #REF! | G17: =IF(#REF!<>"",#REF!,"") -> #REF! | H17: =IF(#REF!<>"",#REF!,"") -> #REF! | I17: =IF(#REF!<>"",#REF!,"") -> #REF! | J17: =IF(#REF!<>"",#REF!,"") -> #REF! | K17: Target | L17: =IF(#REF!<>"",#REF!,"") -> #REF! | M17: =IF(#REF!<>"",#REF!,"") -> #REF! | N17: =IF(#REF!<>"",#REF!,"") -> #REF! | O17: =IF(#REF!<>"",#REF!,"") -> #REF! | P17: =IF(#REF!<>"",#REF!,"") -> #REF! | Q17: =IF(#REF!<>"",#REF!,"") -> #REF! | R17: =IF(#REF!<>"",#REF!,"") -> #REF! | S17: =IF(#REF!<>"",#REF!,"") -> #REF! | ... W17: =IF(#REF!<>"",#REF!,"") -> #REF!
K18: Actual | L18: =IF(#REF!<>"",#REF!,"") -> #REF! | M18: =IF(#REF!<>"",#REF!,"") -> #REF! | N18: =IF(#REF!<>"",#REF!,"") -> #REF! | O18: =IF(#REF!<>"",#REF!,"") -> #REF! | P18: =IF(#REF!<>"",#REF!,"") -> #REF! | Q18: =IF(#REF!<>"",#REF!,"") -> #REF! | R18: =IF(#REF!<>"",#REF!,"") -> #REF! | S18: =IF(#REF!<>"",#REF!,"") -> #REF! | ... W18: =IF(#REF!<>"",#REF!,"") -> #REF!
C19: =IF(#REF!<>"",#REF!,"") -> #REF! | D19: Vinayak P | E19: =IF(#REF!<>"",#REF!,"") -> #REF! | F19: =IF(#REF!<>"",#REF!,"") -> #REF! | G19: =IF(#REF!<>"",#REF!,"") -> #REF! | H19: =IF(#REF!<>"",#REF!,"") -> #REF! | I19: =IF(#REF!<>"",#REF!,"") -> #REF! | J19: =IF(#REF!<>"",#REF!,"") -> #REF! | K19: Target | L19: =IF(#REF!<>"",#REF!,"") -> #REF! | M19: =IF(#REF!<>"",#REF!,"") -> #REF! | N19: =IF(#REF!<>"",#REF!,"") -> #REF! | O19: =IF(#REF!<>"",#REF!,"") -> #REF! | P19: =IF(#REF!<>"",#REF!,"") -> #REF! | Q19: =IF(#REF!<>"",#REF!,"") -> #REF! | R19: =IF(#REF!<>"",#REF!,"") -> #REF! | S19: =IF(#REF!<>"",#REF!,"") -> #REF! | ... W19: =IF(#REF!<>"",#REF!,"") -> #REF!
K20: Actual | L20: =IF(#REF!<>"",#REF!,"") -> #REF! | M20: =IF(#REF!<>"",#REF!,"") -> #REF! | N20: =IF(#REF!<>"",#REF!,"") -> #REF! | O20: =IF(#REF!<>"",#REF!,"") -> #REF! | P20: =IF(#REF!<>"",#REF!,"") -> #REF! | Q20: =IF(#REF!<>"",#REF!,"") -> #REF! | R20: =IF(#REF!<>"",#REF!,"") -> #REF! | S20: =IF(#REF!<>"",#REF!,"") -> #REF! | ... W20: =IF(#REF!<>"",#REF!,"") -> #REF!
C21: =IF(#REF!<>"",#REF!,"") -> #REF! | D21: Vinayak P | E21: =IF(#REF!<>"",#REF!,"") -> #REF! | F21: =IF(#REF!<>"",#REF!,"") -> #REF! | G21: =IF(#REF!<>"",#REF!,"") -> #REF! | H21: =IF(#REF!<>"",#REF!,"") -> #REF! | I21: =IF(#REF!<>"",#REF!,"") -> #REF! | J21: =IF(#REF!<>"",#REF!,"") -> #REF! | K21: Target | L21: =IF(#REF!<>"",#REF!,"") -> #REF! | M21: =IF(#REF!<>"",#REF!,"") -> #REF! | N21: =IF(#REF!<>"",#REF!,"") -> #REF! | O21: =IF(#REF!<>"",#REF!,"") -> #REF! | P21: =IF(#REF!<>"",#REF!,"") -> #REF! | Q21: =IF(#REF!<>"",#REF!,"") -> #REF! | R21: =IF(#REF!<>"",#REF!,"") -> #REF! | S21: =IF(#REF!<>"",#REF!,"") -> #REF! | ... W21: =IF(#REF!<>"",#REF!,"") -> #REF!
K22: Actual | L22: =IF(#REF!<>"",#REF!,"") -> #REF! | M22: =IF(#REF!<>"",#REF!,"") -> #REF! | N22: =IF(#REF!<>"",#REF!,"") -> #REF! | O22: =IF(#REF!<>"",#REF!,"") -> #REF! | P22: =IF(#REF!<>"",#REF!,"") -> #REF! | Q22: =IF(#REF!<>"",#REF!,"") -> #REF! | R22: =IF(#REF!<>"",#REF!,"") -> #REF! | S22: =IF(#REF!<>"",#REF!,"") -> #REF! | ... W22: =IF(#REF!<>"",#REF!,"") -> #REF!
A23: 2. Commercial Excellence
C31: =IF('9.NAR '!A8<>"",'9.NAR '!A8,"") -> Order Intake | D31: Mark L | E31: =IF('9.NAR '!B8<>"",'9.NAR '!B8,"") -> Financial OIT vs AOP | F31: =IF('9.NAR '!C8<>"",'9.NAR '!C8,"") -> > | G31: =IF('9.NAR '!D8<>"",'9.NAR '!D8,"") -> €40 | H31: =IF('9.NAR '!E8<>"",'9.NAR '!E8,"") -> Mn | I31: =IF('9.NAR '!F8<>"",'9.NAR '!F8,"") -> Higher the better | J31: =IF('9.NAR '!G8<>"",'9.NAR '!G8,"") -> Monthly | K31: Target | L31: =IF('9.NAR '!I8<>"",'9.NAR '!I8,"") -> 2.4 | M31: =IF('9.NAR '!J8<>"",'9.NAR '!J8,"") -> 2.4 | N31: =IF('9.NAR '!K8<>"",'9.NAR '!K8,"") -> 3.2 | O31: =IF('9.NAR '!L8<>"",'9.NAR '!L8,"") -> 2.1 | P31: =IF('9.NAR '!M8<>"",'9.NAR '!M8,"") -> 2.1 | Q31: =IF('9.NAR '!N8<>"",'9.NAR '!N8,"") -> 4.8 | R31: =IF('9.NAR '!O8<>"",'9.NAR '!O8,"") -> 2.8 | S31: =IF('9.NAR '!P8<>"",'9.NAR '!P8,"") -> 2.8 | ... W31: =IF('9.NAR '!T8<>"",'9.NAR '!T8,"") -> 4.2
K32: Actual | L32: =IF('9.NAR '!I9<>"",'9.NAR '!I9,"") -> 2.1 | M32: =IF('9.NAR '!J9<>"",'9.NAR '!J9,"") -> 2.1 | N32: =IF('9.NAR '!K9<>"",'9.NAR '!K9,"") -> 3.1 | O32: =IF('9.NAR '!L9<>"",'9.NAR '!L9,"") -> 4.1 | P32: =IF('9.NAR '!M9<>"",'9.NAR '!M9,"") -> 2.6 | Q32: =IF('9.NAR '!N9<>"",'9.NAR '!N9,"") -> 3.2 | R32: =IF('9.NAR '!O9<>"",'9.NAR '!O9,"") -> 0.8 | S32: =IF('9.NAR '!P9<>"",'9.NAR '!P9,"") | ... W32: =IF('9.NAR '!T9<>"",'9.NAR '!T9,"")
C33: =IF('9.NAR '!A10<>"",'9.NAR '!A10,"") -> POS Attachment Rate | D33: Mark L | E33: =IF('9.NAR '!B10<>"",'9.NAR '!B10,"") -> PoS Attachement | F33: =IF('9.NAR '!C10<>"",'9.NAR '!C10,"") -> >= | G33: =IF('9.NAR '!D10<>"",'9.NAR '!D10,"") -> % | H33: =IF('9.NAR '!E10<>"",'9.NAR '!E10,"") -> % | I33: =IF('9.NAR '!F10<>"",'9.NAR '!F10,"") -> Higher the better | J33: =IF('9.NAR '!G10<>"",'9.NAR '!G10,"") -> Monthly | K33: Target | L33: =IF('9.NAR '!I10<>"",'9.NAR '!I10,"") -> 40 | M33: =IF('9.NAR '!J10<>"",'9.NAR '!J10,"") -> 40 | N33: =IF('9.NAR '!K10<>"",'9.NAR '!K10,"") -> 40 | O33: =IF('9.NAR '!L10<>"",'9.NAR '!L10,"") -> 40 | P33: =IF('9.NAR '!M10<>"",'9.NAR '!M10,"") -> 40 | Q33: =IF('9.NAR '!N10<>"",'9.NAR '!N10,"") -> 40 | R33: =IF('9.NAR '!O10<>"",'9.NAR '!O10,"") -> 40 | S33: =IF('9.NAR '!P10<>"",'9.NAR '!P10,"") -> 40 | ... W33: =IF('9.NAR '!T10<>"",'9.NAR '!T10,"") -> 40
K34: Actual | L34: =IF('9.NAR '!I11<>"",'9.NAR '!I11,"") -> 60 | M34: =IF('9.NAR '!J11<>"",'9.NAR '!J11,"") -> 20 | N34: =IF('9.NAR '!K11<>"",'9.NAR '!K11,"") -> 21 | O34: =IF('9.NAR '!L11<>"",'9.NAR '!L11,"") -> 68 | P34: =IF('9.NAR '!M11<>"",'9.NAR '!M11,"") -> 38 | Q34: =IF('9.NAR '!N11<>"",'9.NAR '!N11,"") | R34: =IF('9.NAR '!O11<>"",'9.NAR '!O11,"") | S34: =IF('9.NAR '!P11<>"",'9.NAR '!P11,"") | ... W34: =IF('9.NAR '!T11<>"",'9.NAR '!T11,"")
C35: =IF('10.EUROPE '!A6<>"",'10.EUROPE '!A6,"") -> Market Share % | D35: Silvia M | E35: =IF('10.EUROPE '!B6<>"",'10.EUROPE '!B6,"") -> Q4 '26 MAT Market Share % | F35: =IF('10.EUROPE '!C6<>"",'10.EUROPE '!C6,"") -> = | G35: =IF('10.EUROPE '!D6<>"",'10.EUROPE '!D6,"") -> 0.165 | H35: =IF('10.EUROPE '!E6<>"",'10.EUROPE '!E6,"") -> % | I35: =IF('10.EUROPE '!F6<>"",'10.EUROPE '!F6,"") -> Higher the better | J35: =IF('10.EUROPE '!G6<>"",'10.EUROPE '!G6,"") -> Quarterly | K35: Target | L35: =IF('10.EUROPE '!I6<>"",'10.EUROPE '!I6,"") | M35: =IF('10.EUROPE '!J6<>"",'10.EUROPE '!J6,"") | N35: =IF('10.EUROPE '!K6<>"",'10.EUROPE '!K6,"") | O35: =IF('10.EUROPE '!L6<>"",'10.EUROPE '!L6,"") | P35: =IF('10.EUROPE '!M6<>"",'10.EUROPE '!M6,"") | Q35: =IF('10.EUROPE '!N6<>"",'10.EUROPE '!N6,"") | R35: =IF('10.EUROPE '!O6<>"",'10.EUROPE '!O6,"") | S35: =IF('10.EUROPE '!P6<>"",'10.EUROPE '!P6,"") | ... W35: =IF('10.EUROPE '!T6<>"",'10.EUROPE '!T6,"") -> 0.165
K36: Actual | L36: =IF('10.EUROPE '!I7<>"",'10.EUROPE '!I7,"") | M36: =IF('10.EUROPE '!J7<>"",'10.EUROPE '!J7,"") | N36: =IF('10.EUROPE '!K7<>"",'10.EUROPE '!K7,"") -> 0.157 | O36: =IF('10.EUROPE '!L7<>"",'10.EUROPE '!L7,"") | P36: =IF('10.EUROPE '!M7<>"",'10.EUROPE '!M7,"") -> 0.145 | Q36: =IF('10.EUROPE '!N7<>"",'10.EUROPE '!N7,"") | R36: =IF('10.EUROPE '!O7<>"",'10.EUROPE '!O7,"") | S36: =IF('10.EUROPE '!P7<>"",'10.EUROPE '!P7,"") | ... W36: =IF('10.EUROPE '!T7<>"",'10.EUROPE '!T7,"")
C37: =IF('10.EUROPE '!A8<>"",'10.EUROPE '!A8,"") -> Order Intake EQ | D37: Silvia M | E37: =IF('10.EUROPE '!B8<>"",'10.EUROPE '!B8,"") -> 2026 FY Order Intake EQ | F37: =IF('10.EUROPE '!C8<>"",'10.EUROPE '!C8,"") -> = | G37: =IF('10.EUROPE '!D8<>"",'10.EUROPE '!D8,"") -> 42 | H37: =IF('10.EUROPE '!E8<>"",'10.EUROPE '!E8,"") -> Mn | I37: =IF('10.EUROPE '!F8<>"",'10.EUROPE '!F8,"") -> Higher the better | J37: =IF('10.EUROPE '!G8<>"",'10.EUROPE '!G8,"") -> Monthly | K37: Target | L37: =IF('10.EUROPE '!I8<>"",'10.EUROPE '!I8,"") -> 3 | M37: =IF('10.EUROPE '!J8<>"",'10.EUROPE '!J8,"") -> 1.6 | N37: =IF('10.EUROPE '!K8<>"",'10.EUROPE '!K8,"") -> 3.9 | O37: =IF('10.EUROPE '!L8<>"",'10.EUROPE '!L8,"") -> 3.1 | P37: =IF('10.EUROPE '!M8<>"",'10.EUROPE '!M8,"") -> 2.1 | Q37: =IF('10.EUROPE '!N8<>"",'10.EUROPE '!N8,"") -> 4.4 | R37: =IF('10.EUROPE '!O8<>"",'10.EUROPE '!O8,"") -> 2.9 | S37: =IF('10.EUROPE '!P8<>"",'10.EUROPE '!P8,"") -> 3 | ... W37: =IF('10.EUROPE '!T8<>"",'10.EUROPE '!T8,"") -> 7.1
K38: Actual | L38: =IF('10.EUROPE '!I9<>"",'10.EUROPE '!I9,"") -> 1 | M38: =IF('10.EUROPE '!J9<>"",'10.EUROPE '!J9,"") -> 2.9 | N38: =IF('10.EUROPE '!K9<>"",'10.EUROPE '!K9,"") -> 5.4 | O38: =IF('10.EUROPE '!L9<>"",'10.EUROPE '!L9,"") -> 1.9 | P38: =IF('10.EUROPE '!M9<>"",'10.EUROPE '!M9,"") -> 1.7 | Q38: =IF('10.EUROPE '!N9<>"",'10.EUROPE '!N9,"") -> 4.4 | R38: =IF('10.EUROPE '!O9<>"",'10.EUROPE '!O9,"") -> 1.5 | S38: =IF('10.EUROPE '!P9<>"",'10.EUROPE '!P9,"") -> 1.2 | ... W38: =IF('10.EUROPE '!T9<>"",'10.EUROPE '!T9,"")
C39: =IF('10.EUROPE '!A10<>"",'10.EUROPE '!A10,"") -> Order Intake CS | D39: Silvia M | E39: =IF('10.EUROPE '!B10<>"",'10.EUROPE '!B10,"") -> 2026 FY Order Intake CS | F39: =IF('10.EUROPE '!C10<>"",'10.EUROPE '!C10,"") -> = | G39: =IF('10.EUROPE '!D10<>"",'10.EUROPE '!D10,"") -> 26.9 | H39: =IF('10.EUROPE '!E10<>"",'10.EUROPE '!E10,"") -> Mn | I39: =IF('10.EUROPE '!F10<>"",'10.EUROPE '!F10,"") -> Higher the better | J39: =IF('10.EUROPE '!G10<>"",'10.EUROPE '!G10,"") -> Monthly | K39: Target | L39: =IF('10.EUROPE '!I10<>"",'10.EUROPE '!I10,"") -> 2 | M39: =IF('10.EUROPE '!J10<>"",'10.EUROPE '!J10,"") -> 2 | N39: =IF('10.EUROPE '!K10<>"",'10.EUROPE '!K10,"") -> 3.5 | O39: =IF('10.EUROPE '!L10<>"",'10.EUROPE '!L10,"") -> 1.8 | P39: =IF('10.EUROPE '!M10<>"",'10.EUROPE '!M10,"") -> 1.8 | Q39: =IF('10.EUROPE '!N10<>"",'10.EUROPE '!N10,"") -> 1.8 | R39: =IF('10.EUROPE '!O10<>"",'10.EUROPE '!O10,"") -> 1.7 | S39: =IF('10.EUROPE '!P10<>"",'10.EUROPE '!P10,"") -> 1.3 | ... W39: =IF('10.EUROPE '!T10<>"",'10.EUROPE '!T10,"") -> 3.7
K40: Actual | L40: =IF('10.EUROPE '!I11<>"",'10.EUROPE '!I11,"") -> 2.6 | M40: =IF('10.EUROPE '!J11<>"",'10.EUROPE '!J11,"") -> 1.9 | N40: =IF('10.EUROPE '!K11<>"",'10.EUROPE '!K11,"") -> 3.6 | O40: =IF('10.EUROPE '!L11<>"",'10.EUROPE '!L11,"") -> 2.9 | P40: =IF('10.EUROPE '!M11<>"",'10.EUROPE '!M11,"") -> 1.2 | Q40: =IF('10.EUROPE '!N11<>"",'10.EUROPE '!N11,"") -> 2 | R40: =IF('10.EUROPE '!O11<>"",'10.EUROPE '!O11,"") -> 1.2 | S40: =IF('10.EUROPE '!P11<>"",'10.EUROPE '!P11,"") -> 1.3 | ... W40: =IF('10.EUROPE '!T11<>"",'10.EUROPE '!T11,"")
C41: =IF('11.GROWTH '!A6<>"",'11.GROWTH '!A6,"") -> Market Share | D41: Mahmut B | E41: =IF('11.GROWTH '!B6<>"",'11.GROWTH '!B6,"") -> MAT MS(%) | F41: =IF('11.GROWTH '!C6<>"",'11.GROWTH '!C6,"") -> = | G41: =IF('11.GROWTH '!D6<>"",'11.GROWTH '!D6,"") -> 23 | H41: =IF('11.GROWTH '!E6<>"",'11.GROWTH '!E6,"") -> % | I41: =IF('11.GROWTH '!F6<>"",'11.GROWTH '!F6,"") -> Higher the better | J41: =IF('11.GROWTH '!G6<>"",'11.GROWTH '!G6,"") -> Quarterly | K41: Target | L41: =IF('11.GROWTH '!I6<>"",'11.GROWTH '!I6,"") | M41: =IF('11.GROWTH '!J6<>"",'11.GROWTH '!J6,"") | N41: =IF('11.GROWTH '!K6<>"",'11.GROWTH '!K6,"") -> 0.2 | O41: =IF('11.GROWTH '!L6<>"",'11.GROWTH '!L6,"") | P41: =IF('11.GROWTH '!M6<>"",'11.GROWTH '!M6,"") | Q41: =IF('11.GROWTH '!N6<>"",'11.GROWTH '!N6,"") -> 0.21 | R41: =IF('11.GROWTH '!O6<>"",'11.GROWTH '!O6,"") | S41: =IF('11.GROWTH '!P6<>"",'11.GROWTH '!P6,"") | ... W41: =IF('11.GROWTH '!T6<>"",'11.GROWTH '!T6,"") -> 0.23
K42: Actual | L42: =IF('11.GROWTH '!I7<>"",'11.GROWTH '!I7,"") | M42: =IF('11.GROWTH '!J7<>"",'11.GROWTH '!J7,"") | N42: =IF('11.GROWTH '!K7<>"",'11.GROWTH '!K7,"") | O42: =IF('11.GROWTH '!L7<>"",'11.GROWTH '!L7,"") | P42: =IF('11.GROWTH '!M7<>"",'11.GROWTH '!M7,"") | Q42: =IF('11.GROWTH '!N7<>"",'11.GROWTH '!N7,"") | R42: =IF('11.GROWTH '!O7<>"",'11.GROWTH '!O7,"") | S42: =IF('11.GROWTH '!P7<>"",'11.GROWTH '!P7,"") | ... W42: =IF('11.GROWTH '!T7<>"",'11.GROWTH '!T7,"")
C43: =IF('11.GROWTH '!A8<>"",'11.GROWTH '!A8,"") -> Order Intake EQ | D43: Mahmut B | E43: =IF('11.GROWTH '!B8<>"",'11.GROWTH '!B8,"") -> AOP OIT FY | F43: =IF('11.GROWTH '!C8<>"",'11.GROWTH '!C8,"") -> = | G43: =IF('11.GROWTH '!D8<>"",'11.GROWTH '!D8,"") -> 62.9 | H43: =IF('11.GROWTH '!E8<>"",'11.GROWTH '!E8,"") -> Mn | I43: =IF('11.GROWTH '!F8<>"",'11.GROWTH '!F8,"") -> Higher the better | J43: =IF('11.GROWTH '!G8<>"",'11.GROWTH '!G8,"") -> Monthly | K43: Target | L43: =IF('11.GROWTH '!I8<>"",'11.GROWTH '!I8,"") -> 1.5 | M43: =IF('11.GROWTH '!J8<>"",'11.GROWTH '!J8,"") -> 4.5 | N43: =IF('11.GROWTH '!K8<>"",'11.GROWTH '!K8,"") -> 5.5 | O43: =IF('11.GROWTH '!L8<>"",'11.GROWTH '!L8,"") -> 4.3 | P43: =IF('11.GROWTH '!M8<>"",'11.GROWTH '!M8,"") -> 6.5 | Q43: =IF('11.GROWTH '!N8<>"",'11.GROWTH '!N8,"") -> 6.4 | R43: =IF('11.GROWTH '!O8<>"",'11.GROWTH '!O8,"") -> 3.3 | S43: =IF('11.GROWTH '!P8<>"",'11.GROWTH '!P8,"") -> 6.1 | ... W43: =IF('11.GROWTH '!T8<>"",'11.GROWTH '!T8,"") -> 6.7
K44: Actual | L44: =IF('11.GROWTH '!I9<>"",'11.GROWTH '!I9,"") -> 2.1 | M44: =IF('11.GROWTH '!J9<>"",'11.GROWTH '!J9,"") -> 3.4 | N44: =IF('11.GROWTH '!K9<>"",'11.GROWTH '!K9,"") -> 8.8 | O44: =IF('11.GROWTH '!L9<>"",'11.GROWTH '!L9,"") -> 1.2 | P44: =IF('11.GROWTH '!M9<>"",'11.GROWTH '!M9,"") | Q44: =IF('11.GROWTH '!N9<>"",'11.GROWTH '!N9,"") | R44: =IF('11.GROWTH '!O9<>"",'11.GROWTH '!O9,"") | S44: =IF('11.GROWTH '!P9<>"",'11.GROWTH '!P9,"") | ... W44: =IF('11.GROWTH '!T9<>"",'11.GROWTH '!T9,"")
C45: =IF('11.GROWTH '!A10<>"",'11.GROWTH '!A10,"") -> Order Intake CS | D45: Mahmut B | E45: =IF('11.GROWTH '!B10<>"",'11.GROWTH '!B10,"") -> AOP OIT FY | F45: =IF('11.GROWTH '!C10<>"",'11.GROWTH '!C10,"") -> = | G45: =IF('11.GROWTH '!D10<>"",'11.GROWTH '!D10,"") -> 32.2 | H45: =IF('11.GROWTH '!E10<>"",'11.GROWTH '!E10,"") -> Mn | I45: =IF('11.GROWTH '!F10<>"",'11.GROWTH '!F10,"") -> Higher the better | J45: =IF('11.GROWTH '!G10<>"",'11.GROWTH '!G10,"") -> Monthly | K45: Target | L45: =IF('11.GROWTH '!I10<>"",'11.GROWTH '!I10,"") -> 2.697 | M45: =IF('11.GROWTH '!J10<>"",'11.GROWTH '!J10,"") -> 1.91 | N45: =IF('11.GROWTH '!K10<>"",'11.GROWTH '!K10,"") -> 2.475 | O45: =IF('11.GROWTH '!L10<>"",'11.GROWTH '!L10,"") -> 2.271 | P45: =IF('11.GROWTH '!M10<>"",'11.GROWTH '!M10,"") -> 2.709 | Q45: =IF('11.GROWTH '!N10<>"",'11.GROWTH '!N10,"") -> 3.862 | R45: =IF('11.GROWTH '!O10<>"",'11.GROWTH '!O10,"") -> 2.534 | S45: =IF('11.GROWTH '!P10<>"",'11.GROWTH '!P10,"") -> 2.27 | ... W45: =IF('11.GROWTH '!T10<>"",'11.GROWTH '!T10,"") -> 4.618
K46: Actual | L46: =IF('11.GROWTH '!I11<>"",'11.GROWTH '!I11,"") -> 2 | M46: =IF('11.GROWTH '!J11<>"",'11.GROWTH '!J11,"") -> 2.2 | N46: =IF('11.GROWTH '!K11<>"",'11.GROWTH '!K11,"") -> 2.5 | O46: =IF('11.GROWTH '!L11<>"",'11.GROWTH '!L11,"") -> 2.4 | P46: =IF('11.GROWTH '!M11<>"",'11.GROWTH '!M11,"") -> 3.1 | Q46: =IF('11.GROWTH '!N11<>"",'11.GROWTH '!N11,"") -> 3.8 | R46: =IF('11.GROWTH '!O11<>"",'11.GROWTH '!O11,"") -> 2.2 | S46: =IF('11.GROWTH '!P11<>"",'11.GROWTH '!P11,"") | ... W46: =IF('11.GROWTH '!T11<>"",'11.GROWTH '!T11,"")
A47: 3. Speed up Innovation | C47: =IF('5.R&D '!A6<>"",'5.R&D '!A6,"") -> NPI On-Time (%) | D47: Shailesh A | E47: =IF('5.R&D '!B6<>"",'5.R&D '!B6,"") -> % Dhruv NPI Milestone Readiness Index (%) | F47: =IF('5.R&D '!C6<>"",'5.R&D '!C6,"") -> >= | G47: =IF('5.R&D '!D6<>"",'5.R&D '!D6,"") -> 90 | H47: =IF('5.R&D '!E6<>"",'5.R&D '!E6,"") -> % | I47: =IF('5.R&D '!F6<>"",'5.R&D '!F6,"") -> Higher the better | J47: =IF('5.R&D '!G6<>"",'5.R&D '!G6,"") -> Monthly | K47: Target | L47: =IF('5.R&D '!I6<>"",'5.R&D '!I6,"") -> 90 | M47: =IF('5.R&D '!J6<>"",'5.R&D '!J6,"") -> 90 | N47: =IF('5.R&D '!K6<>"",'5.R&D '!K6,"") -> 90 | O47: =IF('5.R&D '!L6<>"",'5.R&D '!L6,"") -> 90 | P47: =IF('5.R&D '!M6<>"",'5.R&D '!M6,"") -> 90 | Q47: =IF('5.R&D '!N6<>"",'5.R&D '!N6,"") -> 90 | R47: =IF('5.R&D '!O6<>"",'5.R&D '!O6,"") -> 90 | S47: =IF('5.R&D '!P6<>"",'5.R&D '!P6,"") -> 90 | ... W47: =IF('5.R&D '!T6<>"",'5.R&D '!T6,"") -> 90
K48: Actual | L48: =IF('5.R&D '!I7<>"",'5.R&D '!I7,"") -> 60 | M48: =IF('5.R&D '!J7<>"",'5.R&D '!J7,"") -> 64 | N48: =IF('5.R&D '!K7<>"",'5.R&D '!K7,"") -> 67 | O48: =IF('5.R&D '!L7<>"",'5.R&D '!L7,"") -> 72 | P48: =IF('5.R&D '!M7<>"",'5.R&D '!M7,"") -> 77 | Q48: =IF('5.R&D '!N7<>"",'5.R&D '!N7,"") -> 91 | R48: =IF('5.R&D '!O7<>"",'5.R&D '!O7,"") -> 93 | S48: =IF('5.R&D '!P7<>"",'5.R&D '!P7,"") -> 94 | ... W48: =IF('5.R&D '!T7<>"",'5.R&D '!T7,"")
C49: =IF('5.R&D '!A8<>"",'5.R&D '!A8,"") -> LCM Ontime (%) | D49: Shailesh A | E49: =IF('5.R&D '!B8<>"",'5.R&D '!B8,"") -> % LCM Change Requests (CRs) implemented on or before the committed implementation date (within the reporting month.) | F49: =IF('5.R&D '!C8<>"",'5.R&D '!C8,"") -> >= | G49: =IF('5.R&D '!D8<>"",'5.R&D '!D8,"") -> 85 | H49: =IF('5.R&D '!E8<>"",'5.R&D '!E8,"") -> % | I49: =IF('5.R&D '!F8<>"",'5.R&D '!F8,"") -> Higher the better | J49: =IF('5.R&D '!G8<>"",'5.R&D '!G8,"") -> Monthly | K49: Target | L49: =IF('5.R&D '!I8<>"",'5.R&D '!I8,"") -> 85 | M49: =IF('5.R&D '!J8<>"",'5.R&D '!J8,"") -> 85 | N49: =IF('5.R&D '!K8<>"",'5.R&D '!K8,"") -> 85 | O49: =IF('5.R&D '!L8<>"",'5.R&D '!L8,"") -> 85 | P49: =IF('5.R&D '!M8<>"",'5.R&D '!M8,"") -> 85 | Q49: =IF('5.R&D '!N8<>"",'5.R&D '!N8,"") -> 85 | R49: =IF('5.R&D '!O8<>"",'5.R&D '!O8,"") -> 85 | S49: =IF('5.R&D '!P8<>"",'5.R&D '!P8,"") -> 85 | ... W49: =IF('5.R&D '!T8<>"",'5.R&D '!T8,"") -> 85
K50: Actual | L50: =IF('5.R&D '!I9<>"",'5.R&D '!I9,"") -> 80 | M50: =IF('5.R&D '!J9<>"",'5.R&D '!J9,"") -> 67 | N50: =IF('5.R&D '!K9<>"",'5.R&D '!K9,"") -> 133 | O50: =IF('5.R&D '!L9<>"",'5.R&D '!L9,"") -> 50 | P50: =IF('5.R&D '!M9<>"",'5.R&D '!M9,"") -> 91 | Q50: =IF('5.R&D '!N9<>"",'5.R&D '!N9,"") -> 80 | R50: =IF('5.R&D '!O9<>"",'5.R&D '!O9,"") -> 83.3 | S50: =IF('5.R&D '!P9<>"",'5.R&D '!P9,"") -> 88 | ... W50: =IF('5.R&D '!T9<>"",'5.R&D '!T9,"")
C51: =IF('5.R&D '!A10<>"",'5.R&D '!A10,"") -> I2M Value Creation | D51: Intekhab M | E51: =IF('5.R&D '!B10<>"",'5.R&D '!B10,"") -> Increase innovation value delivered | F51: =IF('5.R&D '!C10<>"",'5.R&D '!C10,"") -> >= | G51: =IF('5.R&D '!D10<>"",'5.R&D '!D10,"") -> 67 | H51: =IF('5.R&D '!E10<>"",'5.R&D '!E10,"") -> No. | I51: =IF('5.R&D '!F10<>"",'5.R&D '!F10,"") -> Higher the better | J51: =IF('5.R&D '!G10<>"",'5.R&D '!G10,"") -> Monthly | K51: Target | L51: =IF('5.R&D '!I10<>"",'5.R&D '!I10,"") -> 5.5 | M51: =IF('5.R&D '!J10<>"",'5.R&D '!J10,"") -> 11 | N51: =IF('5.R&D '!K10<>"",'5.R&D '!K10,"") -> 16.5 | O51: =IF('5.R&D '!L10<>"",'5.R&D '!L10,"") -> 22 | P51: =IF('5.R&D '!M10<>"",'5.R&D '!M10,"") -> 27.5 | Q51: =IF('5.R&D '!N10<>"",'5.R&D '!N10,"") -> 33 | R51: =IF('5.R&D '!O10<>"",'5.R&D '!O10,"") -> 38.5 | S51: =IF('5.R&D '!P10<>"",'5.R&D '!P10,"") -> 44 | ... W51: =IF('5.R&D '!T10<>"",'5.R&D '!T10,"") -> 67
K52: Actual | L52: =IF('5.R&D '!I11<>"",'5.R&D '!I11,"") -> 9 | M52: =IF('5.R&D '!J11<>"",'5.R&D '!J11,"") -> 17.3 | N52: =IF('5.R&D '!K11<>"",'5.R&D '!K11,"") -> 24.6 | O52: =IF('5.R&D '!L11<>"",'5.R&D '!L11,"") -> 26.3 | P52: =IF('5.R&D '!M11<>"",'5.R&D '!M11,"") -> 31 | Q52: =IF('5.R&D '!N11<>"",'5.R&D '!N11,"") -> 37.3 | R52: =IF('5.R&D '!O11<>"",'5.R&D '!O11,"") -> 49.7 | S52: =IF('5.R&D '!P11<>"",'5.R&D '!P11,"") -> 51.9 | ... W52: =IF('5.R&D '!T11<>"",'5.R&D '!T11,"")
C53: =IF(#REF!<>"",#REF!,"") -> #REF! | D53: Intekhab M | E53: =IF(#REF!<>"",#REF!,"") -> #REF! | F53: =IF(#REF!<>"",#REF!,"") -> #REF! | G53: =IF(#REF!<>"",#REF!,"") -> #REF! | H53: =IF(#REF!<>"",#REF!,"") -> #REF! | I53: =IF(#REF!<>"",#REF!,"") -> #REF! | J53: =IF(#REF!<>"",#REF!,"") -> #REF! | K53: Target | L53: =IF(#REF!<>"",#REF!,"") -> #REF! | M53: =IF(#REF!<>"",#REF!,"") -> #REF! | N53: =IF(#REF!<>"",#REF!,"") -> #REF! | O53: =IF(#REF!<>"",#REF!,"") -> #REF! | P53: =IF(#REF!<>"",#REF!,"") -> #REF! | Q53: =IF(#REF!<>"",#REF!,"") -> #REF! | R53: =IF(#REF!<>"",#REF!,"") -> #REF! | S53: =IF(#REF!<>"",#REF!,"") -> #REF! | ... W53: =IF(#REF!<>"",#REF!,"") -> #REF!
K54: Actual | L54: =IF(#REF!<>"",#REF!,"") -> #REF! | M54: =IF(#REF!<>"",#REF!,"") -> #REF! | N54: =IF(#REF!<>"",#REF!,"") -> #REF! | O54: =IF(#REF!<>"",#REF!,"") -> #REF! | P54: =IF(#REF!<>"",#REF!,"") -> #REF! | Q54: =IF(#REF!<>"",#REF!,"") -> #REF! | R54: =IF(#REF!<>"",#REF!,"") -> #REF! | S54: =IF(#REF!<>"",#REF!,"") -> #REF! | ... W54: =IF(#REF!<>"",#REF!,"") -> #REF!
C55: =IF(#REF!<>"",#REF!,"") -> #REF! | D55: Intekhab M | E55: =IF(#REF!<>"",#REF!,"") -> #REF! | F55: =IF(#REF!<>"",#REF!,"") -> #REF! | G55: =IF(#REF!<>"",#REF!,"") -> #REF! | H55: =IF(#REF!<>"",#REF!,"") -> #REF! | I55: =IF(#REF!<>"",#REF!,"") -> #REF! | J55: =IF(#REF!<>"",#REF!,"") -> #REF! | K55: Target | L55: =IF(#REF!<>"",#REF!,"") -> #REF! | M55: =IF(#REF!<>"",#REF!,"") -> #REF! | N55: =IF(#REF!<>"",#REF!,"") -> #REF! | O55: =IF(#REF!<>"",#REF!,"") -> #REF! | P55: =IF(#REF!<>"",#REF!,"") -> #REF! | Q55: =IF(#REF!<>"",#REF!,"") -> #REF! | R55: =IF(#REF!<>"",#REF!,"") -> #REF! | S55: =IF(#REF!<>"",#REF!,"") -> #REF! | ... W55: =IF(#REF!<>"",#REF!,"") -> #REF!
K56: Actual | L56: =IF(#REF!<>"",#REF!,"") -> #REF! | M56: =IF(#REF!<>"",#REF!,"") -> #REF! | N56: =IF(#REF!<>"",#REF!,"") -> #REF! | O56: =IF(#REF!<>"",#REF!,"") -> #REF! | P56: =IF(#REF!<>"",#REF!,"") -> #REF! | Q56: =IF(#REF!<>"",#REF!,"") -> #REF! | R56: =IF(#REF!<>"",#REF!,"") -> #REF! | S56: =IF(#REF!<>"",#REF!,"") -> #REF! | ... W56: =IF(#REF!<>"",#REF!,"") -> #REF!
C57: =IF(#REF!<>"",#REF!,"") -> #REF! | D57: Intekhab M | E57: =IF(#REF!<>"",#REF!,"") -> #REF! | F57: =IF(#REF!<>"",#REF!,"") -> #REF! | G57: =IF(#REF!<>"",#REF!,"") -> #REF! | H57: =IF(#REF!<>"",#REF!,"") -> #REF! | I57: =IF(#REF!<>"",#REF!,"") -> #REF! | J57: =IF(#REF!<>"",#REF!,"") -> #REF! | K57: Target | L57: =IF(#REF!<>"",#REF!,"") -> #REF! | M57: =IF(#REF!<>"",#REF!,"") -> #REF! | N57: =IF(#REF!<>"",#REF!,"") -> #REF! | O57: =IF(#REF!<>"",#REF!,"") -> #REF! | P57: =IF(#REF!<>"",#REF!,"") -> #REF! | Q57: =IF(#REF!<>"",#REF!,"") -> #REF! | R57: =IF(#REF!<>"",#REF!,"") -> #REF! | S57: =IF(#REF!<>"",#REF!,"") -> #REF! | ... W57: =IF(#REF!<>"",#REF!,"") -> #REF!
K58: Actual | L58: =IF(#REF!<>"",#REF!,"") -> #REF! | M58: =IF(#REF!<>"",#REF!,"") -> #REF! | N58: =IF(#REF!<>"",#REF!,"") -> #REF! | O58: =IF(#REF!<>"",#REF!,"") -> #REF! | P58: =IF(#REF!<>"",#REF!,"") -> #REF! | Q58: =IF(#REF!<>"",#REF!,"") -> #REF! | R58: =IF(#REF!<>"",#REF!,"") -> #REF! | S58: =IF(#REF!<>"",#REF!,"") -> #REF! | ... W58: =IF(#REF!<>"",#REF!,"") -> #REF!
A59: 4. Integrated Supply Chain | C59: =IF('3.ISC '!A6<>"",'3.ISC '!A6,"") -> Sales | D59: Rupali J | E59: =IF('3.ISC '!B6<>"",'3.ISC '!B6,"") -> Revenue in M | F59: =IF('3.ISC '!C6<>"",'3.ISC '!C6,"") -> > | G59: =IF('3.ISC '!D6<>"",'3.ISC '!D6,"") -> 141/143 | H59: =IF('3.ISC '!E6<>"",'3.ISC '!E6,"") -> Mn | I59: =IF('3.ISC '!F6<>"",'3.ISC '!F6,"") -> Higher the better | J59: =IF('3.ISC '!G6<>"",'3.ISC '!G6,"") -> Monthly | K59: Target | L59: =IF('3.ISC '!I6<>"",'3.ISC '!I6,"") -> 8.6903065 | M59: =IF('3.ISC '!J6<>"",'3.ISC '!J6,"") -> 14.057193 | N59: =IF('3.ISC '!K6<>"",'3.ISC '!K6,"") -> 24.179072 | O59: =IF('3.ISC '!L6<>"",'3.ISC '!L6,"") -> 33.551326 | P59: =IF('3.ISC '!M6<>"",'3.ISC '!M6,"") -> 41.442864 | Q59: =IF('3.ISC '!N6<>"",'3.ISC '!N6,"") -> 60.823993 | R59: =IF('3.ISC '!O6<>"",'3.ISC '!O6,"") -> 72.557892 | S59: =IF('3.ISC '!P6<>"",'3.ISC '!P6,"") -> 82.449741 | ... W59: =IF('3.ISC '!T6<>"",'3.ISC '!T6,"") -> 144.52879
K60: Actual | L60: =IF('3.ISC '!I7<>"",'3.ISC '!I7,"") -> 4.1 | M60: =IF('3.ISC '!J7<>"",'3.ISC '!J7,"") -> 9.8 | N60: =IF('3.ISC '!K7<>"",'3.ISC '!K7,"") -> 25.3 | O60: =IF('3.ISC '!L7<>"",'3.ISC '!L7,"") -> 31.44 | P60: =IF('3.ISC '!M7<>"",'3.ISC '!M7,"") -> 40.9 | Q60: =IF('3.ISC '!N7<>"",'3.ISC '!N7,"") -> 55.18 | R60: =IF('3.ISC '!O7<>"",'3.ISC '!O7,"") -> 61.4 | S60: =IF('3.ISC '!P7<>"",'3.ISC '!P7,"") | ... W60: =IF('3.ISC '!T7<>"",'3.ISC '!T7,"")
C61: =IF('3.ISC '!A8<>"",'3.ISC '!A8,"") -> OTIF | D61: Rupali J | E61: =IF('3.ISC '!B8<>"",'3.ISC '!B8,"") -> CDD adherance | F61: =IF('3.ISC '!C8<>"",'3.ISC '!C8,"") -> > | G61: =IF('3.ISC '!D8<>"",'3.ISC '!D8,"") -> 0.85 | H61: =IF('3.ISC '!E8<>"",'3.ISC '!E8,"") -> % | I61: =IF('3.ISC '!F8<>"",'3.ISC '!F8,"") -> Higher the better | J61: =IF('3.ISC '!G8<>"",'3.ISC '!G8,"") -> Monthly | K61: Target | L61: =IF('3.ISC '!I8<>"",'3.ISC '!I8,"") -> 0.69 | M61: =IF('3.ISC '!J8<>"",'3.ISC '!J8,"") -> 0.69 | N61: =IF('3.ISC '!K8<>"",'3.ISC '!K8,"") -> 0.69 | O61: =IF('3.ISC '!L8<>"",'3.ISC '!L8,"") -> 0.72 | P61: =IF('3.ISC '!M8<>"",'3.ISC '!M8,"") -> 0.72 | Q61: =IF('3.ISC '!N8<>"",'3.ISC '!N8,"") -> 0.72 | R61: =IF('3.ISC '!O8<>"",'3.ISC '!O8,"") -> 0.74 | S61: =IF('3.ISC '!P8<>"",'3.ISC '!P8,"") -> 0.74 | ... W61: =IF('3.ISC '!T8<>"",'3.ISC '!T8,"") -> 0.8
K62: Actual | L62: =IF('3.ISC '!I9<>"",'3.ISC '!I9,"") -> 0.83 | M62: =IF('3.ISC '!J9<>"",'3.ISC '!J9,"") -> 0.82 | N62: =IF('3.ISC '!K9<>"",'3.ISC '!K9,"") -> 0.81 | O62: =IF('3.ISC '!L9<>"",'3.ISC '!L9,"") -> 0.6 | P62: =IF('3.ISC '!M9<>"",'3.ISC '!M9,"") -> 0.87 | Q62: =IF('3.ISC '!N9<>"",'3.ISC '!N9,"") -> 0.77 | R62: =IF('3.ISC '!O9<>"",'3.ISC '!O9,"") -> 0.7 | S62: =IF('3.ISC '!P9<>"",'3.ISC '!P9,"") | ... W62: =IF('3.ISC '!T9<>"",'3.ISC '!T9,"")
C63: =IF('3.ISC '!A10<>"",'3.ISC '!A10,"") -> Inventory | D63: Rupali J | E63: =IF('3.ISC '!B10<>"",'3.ISC '!B10,"") -> (Business+Market+Service ) as % of sales | F63: =IF('3.ISC '!C10<>"",'3.ISC '!C10,"") -> < | G63: =IF('3.ISC '!D10<>"",'3.ISC '!D10,"") -> 22% / 49 M | H63: =IF('3.ISC '!E10<>"",'3.ISC '!E10,"") -> % | I63: =IF('3.ISC '!F10<>"",'3.ISC '!F10,"") -> Lower the better | J63: =IF('3.ISC '!G10<>"",'3.ISC '!G10,"") -> Monthly | K63: Target | L63: =IF('3.ISC '!I10<>"",'3.ISC '!I10,"") -> 0.283 | M63: =IF('3.ISC '!J10<>"",'3.ISC '!J10,"") -> 0.28 | N63: =IF('3.ISC '!K10<>"",'3.ISC '!K10,"") -> 0.29 | O63: =IF('3.ISC '!L10<>"",'3.ISC '!L10,"") -> 0.28678379 | P63: =IF('3.ISC '!M10<>"",'3.ISC '!M10,"") -> 0.26777766 | Q63: =IF('3.ISC '!N10<>"",'3.ISC '!N10,"") -> 0.25862821 | R63: =IF('3.ISC '!O10<>"",'3.ISC '!O10,"") -> 0.24073532 | S63: =IF('3.ISC '!P10<>"",'3.ISC '!P10,"") -> 0.23371552 | ... W63: =IF('3.ISC '!T10<>"",'3.ISC '!T10,"") -> 0.21107105
K64: Actual | L64: =IF('3.ISC '!I11<>"",'3.ISC '!I11,"") -> 0.274 | M64: =IF('3.ISC '!J11<>"",'3.ISC '!J11,"") -> 0.29 | N64: =IF('3.ISC '!K11<>"",'3.ISC '!K11,"") -> 0.29 | O64: =IF('3.ISC '!L11<>"",'3.ISC '!L11,"") -> 0.3 | P64: =IF('3.ISC '!M11<>"",'3.ISC '!M11,"") -> 0.3 | Q64: =IF('3.ISC '!N11<>"",'3.ISC '!N11,"") -> 0.29 | R64: =IF('3.ISC '!O11<>"",'3.ISC '!O11,"") -> 0.3 | S64: =IF('3.ISC '!P11<>"",'3.ISC '!P11,"") | ... W64: =IF('3.ISC '!T11<>"",'3.ISC '!T11,"")
C65: =IF('4.Procurement'!A6<>"",'4.Procurement'!A6,"") -> Productivity ( Nego) | D65: Anand P | E65: =IF('4.Procurement'!B6<>"",'4.Procurement'!B6,"") -> 1% of Spend | F65: =IF('4.Procurement'!C6<>"",'4.Procurement'!C6,"") -> <= | G65: =IF('4.Procurement'!D6<>"",'4.Procurement'!D6,"") -> 0.4 M € 0.7 M € Stretch | H65: =IF('4.Procurement'!E6<>"",'4.Procurement'!E6,"") -> % | I65: =IF('4.Procurement'!F6<>"",'4.Procurement'!F6,"") -> Higher the better | J65: =IF('4.Procurement'!G6<>"",'4.Procurement'!G6,"") -> Monthly | K65: Target | L65: =IF('4.Procurement'!I6<>"",'4.Procurement'!I6,"") -> 0.035 | M65: =IF('4.Procurement'!J6<>"",'4.Procurement'!J6,"") -> 0.07 | N65: =IF('4.Procurement'!K6<>"",'4.Procurement'!K6,"") -> 0.105 | O65: =IF('4.Procurement'!L6<>"",'4.Procurement'!L6,"") -> 0.14 | P65: =IF('4.Procurement'!M6<>"",'4.Procurement'!M6,"") -> 0.175 | Q65: =IF('4.Procurement'!N6<>"",'4.Procurement'!N6,"") -> 0.21 | R65: =IF('4.Procurement'!O6<>"",'4.Procurement'!O6,"") -> 0.23 | S65: =IF('4.Procurement'!P6<>"",'4.Procurement'!P6,"") -> 0.265 | ... W65: =IF('4.Procurement'!T6<>"",'4.Procurement'!T6,"") -> 0.4
K66: Actual | L66: =IF('4.Procurement'!I7<>"",'4.Procurement'!I7,"") -> 0.020673 | M66: =IF('4.Procurement'!J7<>"",'4.Procurement'!J7,"") -> 0.058772 | N66: =IF('4.Procurement'!K7<>"",'4.Procurement'!K7,"") -> 0.105659 | O66: =IF('4.Procurement'!L7<>"",'4.Procurement'!L7,"") -> 0.152422 | P66: =IF('4.Procurement'!M7<>"",'4.Procurement'!M7,"") -> 0.19 | Q66: =IF('4.Procurement'!N7<>"",'4.Procurement'!N7,"") -> 0.21 | R66: =IF('4.Procurement'!O7<>"",'4.Procurement'!O7,"") -> 0.23 | S66: =IF('4.Procurement'!P7<>"",'4.Procurement'!P7,"") | ... W66: =IF('4.Procurement'!T7<>"",'4.Procurement'!T7,"")
C67: =IF('4.Procurement'!A8<>"",'4.Procurement'!A8,"") -> Material Availability (escalation) | D67: Anand P | E67: =IF('4.Procurement'!B8<>"",'4.Procurement'!B8,"") -> Clear to build material avaialbility | F67: =IF('4.Procurement'!C8<>"",'4.Procurement'!C8,"") -> >= | G67: =IF('4.Procurement'!D8<>"",'4.Procurement'!D8,"") -> 0.9 | H67: =IF('4.Procurement'!E8<>"",'4.Procurement'!E8,"") -> % | I67: =IF('4.Procurement'!F8<>"",'4.Procurement'!F8,"") -> Higher the better | J67: =IF('4.Procurement'!G8<>"",'4.Procurement'!G8,"") -> Monthly | K67: Target | L67: =IF('4.Procurement'!I8<>"",'4.Procurement'!I8,"") -> 0.9 | M67: =IF('4.Procurement'!J8<>"",'4.Procurement'!J8,"") -> 0.9 | N67: =IF('4.Procurement'!K8<>"",'4.Procurement'!K8,"") -> 0.9 | O67: =IF('4.Procurement'!L8<>"",'4.Procurement'!L8,"") -> 0.9 | P67: =IF('4.Procurement'!M8<>"",'4.Procurement'!M8,"") -> 0.9 | Q67: =IF('4.Procurement'!N8<>"",'4.Procurement'!N8,"") -> 0.9 | R67: =IF('4.Procurement'!O8<>"",'4.Procurement'!O8,"") -> 0.9 | S67: =IF('4.Procurement'!P8<>"",'4.Procurement'!P8,"") -> 0.9 | ... W67: =IF('4.Procurement'!T8<>"",'4.Procurement'!T8,"") -> 0.9
K68: Actual | L68: =IF('4.Procurement'!I9<>"",'4.Procurement'!I9,"") -> 1 | M68: =IF('4.Procurement'!J9<>"",'4.Procurement'!J9,"") -> 1 | N68: =IF('4.Procurement'!K9<>"",'4.Procurement'!K9,"") -> 1 | O68: =IF('4.Procurement'!L9<>"",'4.Procurement'!L9,"") -> 0.88 | P68: =IF('4.Procurement'!M9<>"",'4.Procurement'!M9,"") -> 0.93 | Q68: =IF('4.Procurement'!N9<>"",'4.Procurement'!N9,"") -> 0.85714286 | R68: =IF('4.Procurement'!O9<>"",'4.Procurement'!O9,"") -> 1 | S68: =IF('4.Procurement'!P9<>"",'4.Procurement'!P9,"") | ... W68: =IF('4.Procurement'!T9<>"",'4.Procurement'!T9,"")
C69: =IF('4.Procurement'!A10<>"",'4.Procurement'!A10,"") -> NPI / MLD | D69: Anand P | E69: =IF('4.Procurement'!B10<>"",'4.Procurement'!B10,"") -> NPI gate readiness | F69: =IF('4.Procurement'!C10<>"",'4.Procurement'!C10,"") -> = | G69: =IF('4.Procurement'!D10<>"",'4.Procurement'!D10,"") -> 1 | H69: =IF('4.Procurement'!E10<>"",'4.Procurement'!E10,"") -> % | I69: =IF('4.Procurement'!F10<>"",'4.Procurement'!F10,"") -> Higher the better | J69: =IF('4.Procurement'!G10<>"",'4.Procurement'!G10,"") -> Monthly | K69: Target | L69: =IF('4.Procurement'!I10<>"",'4.Procurement'!I10,"") -> 0 | M69: =IF('4.Procurement'!J10<>"",'4.Procurement'!J10,"") -> 0 | N69: =IF('4.Procurement'!K10<>"",'4.Procurement'!K10,"") -> 0 | O69: =IF('4.Procurement'!L10<>"",'4.Procurement'!L10,"") -> 1 | P69: =IF('4.Procurement'!M10<>"",'4.Procurement'!M10,"") -> 0 | Q69: =IF('4.Procurement'!N10<>"",'4.Procurement'!N10,"") -> 0 | R69: =IF('4.Procurement'!O10<>"",'4.Procurement'!O10,"") -> 1 | S69: =IF('4.Procurement'!P10<>"",'4.Procurement'!P10,"") -> 1 | ... W69: =IF('4.Procurement'!T10<>"",'4.Procurement'!T10,"") -> 0
K70: Actual | L70: =IF('4.Procurement'!I11<>"",'4.Procurement'!I11,"") -> - | M70: =IF('4.Procurement'!J11<>"",'4.Procurement'!J11,"") -> - | N70: =IF('4.Procurement'!K11<>"",'4.Procurement'!K11,"") -> - | O70: =IF('4.Procurement'!L11<>"",'4.Procurement'!L11,"") -> - | P70: =IF('4.Procurement'!M11<>"",'4.Procurement'!M11,"") -> - | Q70: =IF('4.Procurement'!N11<>"",'4.Procurement'!N11,"") -> - | R70: =IF('4.Procurement'!O11<>"",'4.Procurement'!O11,"") -> 1 | S70: =IF('4.Procurement'!P11<>"",'4.Procurement'!P11,"") | ... W70: =IF('4.Procurement'!T11<>"",'4.Procurement'!T11,"")
A71: 5. Improve Profitability | C71: =IF('12.FINANCE'!A6<>"",'12.FINANCE'!A6,"") -> EBIT | D71: Chetan | E71: =IF('12.FINANCE'!B6<>"",'12.FINANCE'!B6,"") | F71: =IF('12.FINANCE'!C6<>"",'12.FINANCE'!C6,"") | G71: =IF('12.FINANCE'!D6<>"",'12.FINANCE'!D6,"") | H71: =IF('12.FINANCE'!E6<>"",'12.FINANCE'!E6,"") | I71: =IF('12.FINANCE'!F6<>"",'12.FINANCE'!F6,"") | J71: =IF('12.FINANCE'!G6<>"",'12.FINANCE'!G6,"") | K71: Target | L71: =IF('12.FINANCE'!I6<>"",'12.FINANCE'!I6,"") | M71: =IF('12.FINANCE'!J6<>"",'12.FINANCE'!J6,"") | N71: =IF('12.FINANCE'!K6<>"",'12.FINANCE'!K6,"") | O71: =IF('12.FINANCE'!L6<>"",'12.FINANCE'!L6,"") | P71: =IF('12.FINANCE'!M6<>"",'12.FINANCE'!M6,"") | Q71: =IF('12.FINANCE'!N6<>"",'12.FINANCE'!N6,"") | R71: =IF('12.FINANCE'!O6<>"",'12.FINANCE'!O6,"") | S71: =IF('12.FINANCE'!P6<>"",'12.FINANCE'!P6,"") | ... W71: =IF('12.FINANCE'!T6<>"",'12.FINANCE'!T6,"")
K72: Actual | L72: =IF('12.FINANCE'!I7<>"",'12.FINANCE'!I7,"") | M72: =IF('12.FINANCE'!J7<>"",'12.FINANCE'!J7,"") | N72: =IF('12.FINANCE'!K7<>"",'12.FINANCE'!K7,"") | O72: =IF('12.FINANCE'!L7<>"",'12.FINANCE'!L7,"") | P72: =IF('12.FINANCE'!M7<>"",'12.FINANCE'!M7,"") | Q72: =IF('12.FINANCE'!N7<>"",'12.FINANCE'!N7,"") | R72: =IF('12.FINANCE'!O7<>"",'12.FINANCE'!O7,"") | S72: =IF('12.FINANCE'!P7<>"",'12.FINANCE'!P7,"") | ... W72: =IF('12.FINANCE'!T7<>"",'12.FINANCE'!T7,"")
C73: =IF('12.FINANCE'!A8<>"",'12.FINANCE'!A8,"") -> IGM | D73: Chetan | E73: =IF('12.FINANCE'!B8<>"",'12.FINANCE'!B8,"") | F73: =IF('12.FINANCE'!C8<>"",'12.FINANCE'!C8,"") | G73: =IF('12.FINANCE'!D8<>"",'12.FINANCE'!D8,"") | H73: =IF('12.FINANCE'!E8<>"",'12.FINANCE'!E8,"") | I73: =IF('12.FINANCE'!F8<>"",'12.FINANCE'!F8,"") | J73: =IF('12.FINANCE'!G8<>"",'12.FINANCE'!G8,"") | K73: Target | L73: =IF('12.FINANCE'!I8<>"",'12.FINANCE'!I8,"") | M73: =IF('12.FINANCE'!J8<>"",'12.FINANCE'!J8,"") | N73: =IF('12.FINANCE'!K8<>"",'12.FINANCE'!K8,"") | O73: =IF('12.FINANCE'!L8<>"",'12.FINANCE'!L8,"") | P73: =IF('12.FINANCE'!M8<>"",'12.FINANCE'!M8,"") | Q73: =IF('12.FINANCE'!N8<>"",'12.FINANCE'!N8,"") | R73: =IF('12.FINANCE'!O8<>"",'12.FINANCE'!O8,"") | S73: =IF('12.FINANCE'!P8<>"",'12.FINANCE'!P8,"") | ... W73: =IF('12.FINANCE'!T8<>"",'12.FINANCE'!T8,"")
K74: Actual | L74: =IF('12.FINANCE'!I9<>"",'12.FINANCE'!I9,"") | M74: =IF('12.FINANCE'!J9<>"",'12.FINANCE'!J9,"") | N74: =IF('12.FINANCE'!K9<>"",'12.FINANCE'!K9,"") | O74: =IF('12.FINANCE'!L9<>"",'12.FINANCE'!L9,"") | P74: =IF('12.FINANCE'!M9<>"",'12.FINANCE'!M9,"") | Q74: =IF('12.FINANCE'!N9<>"",'12.FINANCE'!N9,"") | R74: =IF('12.FINANCE'!O9<>"",'12.FINANCE'!O9,"") | S74: =IF('12.FINANCE'!P9<>"",'12.FINANCE'!P9,"") | ... W74: =IF('12.FINANCE'!T9<>"",'12.FINANCE'!T9,"")
C75: =IF('12.FINANCE'!A10<>"",'12.FINANCE'!A10,"") -> Productivity | D75: Chetan | E75: =IF('12.FINANCE'!B10<>"",'12.FINANCE'!B10,"") | F75: =IF('12.FINANCE'!C10<>"",'12.FINANCE'!C10,"") | G75: =IF('12.FINANCE'!D10<>"",'12.FINANCE'!D10,"") | H75: =IF('12.FINANCE'!E10<>"",'12.FINANCE'!E10,"") | I75: =IF('12.FINANCE'!F10<>"",'12.FINANCE'!F10,"") | J75: =IF('12.FINANCE'!G10<>"",'12.FINANCE'!G10,"") | K75: Target | L75: =IF('12.FINANCE'!I10<>"",'12.FINANCE'!I10,"") | M75: =IF('12.FINANCE'!J10<>"",'12.FINANCE'!J10,"") | N75: =IF('12.FINANCE'!K10<>"",'12.FINANCE'!K10,"") | O75: =IF('12.FINANCE'!L10<>"",'12.FINANCE'!L10,"") | P75: =IF('12.FINANCE'!M10<>"",'12.FINANCE'!M10,"") | Q75: =IF('12.FINANCE'!N10<>"",'12.FINANCE'!N10,"") | R75: =IF('12.FINANCE'!O10<>"",'12.FINANCE'!O10,"") | S75: =IF('12.FINANCE'!P10<>"",'12.FINANCE'!P10,"") | ... W75: =IF('12.FINANCE'!T10<>"",'12.FINANCE'!T10,"")
K76: Actual | L76: =IF('12.FINANCE'!I11<>"",'12.FINANCE'!I11,"") | M76: =IF('12.FINANCE'!J11<>"",'12.FINANCE'!J11,"") | N76: =IF('12.FINANCE'!K11<>"",'12.FINANCE'!K11,"") | O76: =IF('12.FINANCE'!L11<>"",'12.FINANCE'!L11,"") | P76: =IF('12.FINANCE'!M11<>"",'12.FINANCE'!M11,"") | Q76: =IF('12.FINANCE'!N11<>"",'12.FINANCE'!N11,"") | R76: =IF('12.FINANCE'!O11<>"",'12.FINANCE'!O11,"") | S76: =IF('12.FINANCE'!P11<>"",'12.FINANCE'!P11,"") | ... W76: =IF('12.FINANCE'!T11<>"",'12.FINANCE'!T11,"")
A77: 6. Impact W Care | C77: EES | D77: Kiran P | J77: Half yearly | K77: Target
K78: Actual
A79: 7. Customer Service | C79: =IF('7.Customer Service'!A6<>"",'7.Customer Service'!A6,"") -> Customer Satisfaction | D79: Sangram T | E79: =IF('7.Customer Service'!B6<>"",'7.Customer Service'!B6,"") -> NPS | F79: =IF('7.Customer Service'!C6<>"",'7.Customer Service'!C6,"") -> >= | G79: =IF('7.Customer Service'!D6<>"",'7.Customer Service'!D6,"") -> 0.79 | H79: =IF('7.Customer Service'!E6<>"",'7.Customer Service'!E6,"") -> % | I79: =IF('7.Customer Service'!F6<>"",'7.Customer Service'!F6,"") -> Higher the better | J79: =IF('7.Customer Service'!G6<>"",'7.Customer Service'!G6,"") -> Quarterly | K79: Target | L79: =IF('7.Customer Service'!I6<>"",'7.Customer Service'!I6,"") | M79: =IF('7.Customer Service'!J6<>"",'7.Customer Service'!J6,"") | N79: =IF('7.Customer Service'!K6<>"",'7.Customer Service'!K6,"") -> 0.79 | O79: =IF('7.Customer Service'!L6<>"",'7.Customer Service'!L6,"") | P79: =IF('7.Customer Service'!M6<>"",'7.Customer Service'!M6,"") | Q79: =IF('7.Customer Service'!N6<>"",'7.Customer Service'!N6,"") -> 0.79 | R79: =IF('7.Customer Service'!O6<>"",'7.Customer Service'!O6,"") | S79: =IF('7.Customer Service'!P6<>"",'7.Customer Service'!P6,"") | ... W79: =IF('7.Customer Service'!T6<>"",'7.Customer Service'!T6,"") -> 0.79
K80: Actual | L80: =IF('7.Customer Service'!I7<>"",'7.Customer Service'!I7,"") | M80: =IF('7.Customer Service'!J7<>"",'7.Customer Service'!J7,"") | N80: =IF('7.Customer Service'!K7<>"",'7.Customer Service'!K7,"") -> 0.92 | O80: =IF('7.Customer Service'!L7<>"",'7.Customer Service'!L7,"") | P80: =IF('7.Customer Service'!M7<>"",'7.Customer Service'!M7,"") | Q80: =IF('7.Customer Service'!N7<>"",'7.Customer Service'!N7,"") -> 0.91 | R80: =IF('7.Customer Service'!O7<>"",'7.Customer Service'!O7,"") | S80: =IF('7.Customer Service'!P7<>"",'7.Customer Service'!P7,"") | ... W80: =IF('7.Customer Service'!T7<>"",'7.Customer Service'!T7,"")
C81: =IF('7.Customer Service'!A8<>"",'7.Customer Service'!A8,"") -> CS Sales | D81: Sangram T | E81: =IF('7.Customer Service'!B8<>"",'7.Customer Service'!B8,"") -> CS Revenue | F81: =IF('7.Customer Service'!C8<>"",'7.Customer Service'!C8,"") -> >= | G81: =IF('7.Customer Service'!D8<>"",'7.Customer Service'!D8,"") -> 77.4 | H81: =IF('7.Customer Service'!E8<>"",'7.Customer Service'!E8,"") -> Mn | I81: =IF('7.Customer Service'!F8<>"",'7.Customer Service'!F8,"") -> Higher the better | J81: =IF('7.Customer Service'!G8<>"",'7.Customer Service'!G8,"") -> Monthly | K81: Target | L81: =IF('7.Customer Service'!I8<>"",'7.Customer Service'!I8,"") -> 5.87 | M81: =IF('7.Customer Service'!J8<>"",'7.Customer Service'!J8,"") -> 11.52 | N81: =IF('7.Customer Service'!K8<>"",'7.Customer Service'!K8,"") -> 18 | O81: =IF('7.Customer Service'!L8<>"",'7.Customer Service'!L8,"") -> 24.1 | P81: =IF('7.Customer Service'!M8<>"",'7.Customer Service'!M8,"") -> 30.33 | Q81: =IF('7.Customer Service'!N8<>"",'7.Customer Service'!N8,"") -> 36.89 | R81: =IF('7.Customer Service'!O8<>"",'7.Customer Service'!O8,"") -> 43.25 | S81: =IF('7.Customer Service'!P8<>"",'7.Customer Service'!P8,"") | ... W81: =IF('7.Customer Service'!T8<>"",'7.Customer Service'!T8,"")
K82: Actual | L82: =IF('7.Customer Service'!I9<>"",'7.Customer Service'!I9,"") -> 5.77 | M82: =IF('7.Customer Service'!J9<>"",'7.Customer Service'!J9,"") -> 11.29 | N82: =IF('7.Customer Service'!K9<>"",'7.Customer Service'!K9,"") -> 17.7 | O82: =IF('7.Customer Service'!L9<>"",'7.Customer Service'!L9,"") -> 23.77 | P82: =IF('7.Customer Service'!M9<>"",'7.Customer Service'!M9,"") -> 29.8 | Q82: =IF('7.Customer Service'!N9<>"",'7.Customer Service'!N9,"") -> 36.26 | R82: =IF('7.Customer Service'!O9<>"",'7.Customer Service'!O9,"") -> 42.54 | S82: =IF('7.Customer Service'!P9<>"",'7.Customer Service'!P9,"") | ... W82: =IF('7.Customer Service'!T9<>"",'7.Customer Service'!T9,"")
C83: =IF('7.Customer Service'!A10<>"",'7.Customer Service'!A10,"") -> CS Profitability | D83: Sangram T | E83: =IF('7.Customer Service'!B10<>"",'7.Customer Service'!B10,"") -> Margins IGM% | F83: =IF('7.Customer Service'!C10<>"",'7.Customer Service'!C10,"") -> >= | G83: =IF('7.Customer Service'!D10<>"",'7.Customer Service'!D10,"") -> 0.527 | H83: =IF('7.Customer Service'!E10<>"",'7.Customer Service'!E10,"") -> % | I83: =IF('7.Customer Service'!F10<>"",'7.Customer Service'!F10,"") -> Higher the better | J83: =IF('7.Customer Service'!G10<>"",'7.Customer Service'!G10,"") -> Monthly | K83: Target | L83: =IF('7.Customer Service'!I10<>"",'7.Customer Service'!I10,"") -> 0.453 | M83: =IF('7.Customer Service'!J10<>"",'7.Customer Service'!J10,"") -> 0.464 | N83: =IF('7.Customer Service'!K10<>"",'7.Customer Service'!K10,"") -> 0.493 | O83: =IF('7.Customer Service'!L10<>"",'7.Customer Service'!L10,"") -> 0.491 | P83: =IF('7.Customer Service'!M10<>"",'7.Customer Service'!M10,"") -> 0.488 | Q83: =IF('7.Customer Service'!N10<>"",'7.Customer Service'!N10,"") -> 0.492 | R83: =IF('7.Customer Service'!O10<>"",'7.Customer Service'!O10,"") -> 0.492 | S83: =IF('7.Customer Service'!P10<>"",'7.Customer Service'!P10,"") -> 0.495 | ... W83: =IF('7.Customer Service'!T10<>"",'7.Customer Service'!T10,"") -> 0.507
K84: Actual | L84: =IF('7.Customer Service'!I11<>"",'7.Customer Service'!I11,"") -> 0.403 | M84: =IF('7.Customer Service'!J11<>"",'7.Customer Service'!J11,"") -> 0.402 | N84: =IF('7.Customer Service'!K11<>"",'7.Customer Service'!K11,"") -> 0.424 | O84: =IF('7.Customer Service'!L11<>"",'7.Customer Service'!L11,"") -> 0.428 | P84: =IF('7.Customer Service'!M11<>"",'7.Customer Service'!M11,"") -> 0.43 | Q84: =IF('7.Customer Service'!N11<>"",'7.Customer Service'!N11,"") -> 0.45 | R84: =IF('7.Customer Service'!O11<>"",'7.Customer Service'!O11,"") -> 0.447 | S84: =IF('7.Customer Service'!P11<>"",'7.Customer Service'!P11,"") | ... W84: =IF('7.Customer Service'!T11<>"",'7.Customer Service'!T11,"")
C85: Customer Escalations Closure | E85: Customer escalations closure<= 90 days | G85: >=90% | H85: No. | J85: Monthly | K85: Target | L85: 0.9 | M85: 0.9 | N85: 0.9 | O85: 0.9 | P85: 0.9 | Q85: 0.9 | R85: 0.9 | S85: 0.9 | T85: 0.9 | U85: 0.9 | V85: 0.9
K86: Actual | L86: 0.9778 | M86: 0.9798 | N86: 0.97 | O86: 0.96 | P86: 0.95 | Q86: 0.95 | R86: 0.95 | S86: 0.94 | T86: 0.94 | U86: 0.94 | V86: 0.93

Sheet MasterSheet
A1: Mastersheet
A3: Quality DMB
A4: KPI Name | B4: KPI Definition | C4: Operators | D4: Target AOP 2026 | E4: Units | F4: Metric nature | G4: Frequency | H4: Target/ Actual | I4: Jan-2026 | J4: Feb-2026 | K4: Mar-2026 | L4: Apr-2026 | M4: May-2026 | N4: Jun-2026 | O4: Jul-2026 | P4: Aug-2026 | Q4: Sep-2026 | R4: Oct-2026 | S4: Nov-2026 | T4: Dec-2026
A5: ='1.Quality'!A20 -> % CAPA implementation Tasks on time | B5: ='1.Quality'!B20 -> Number of actions completed without extension / Number of CAPA actions planned in that month as per Plan | C5: ='1.Quality'!C20 -> > | D5: ='1.Quality'!D20 -> 95 | E5: ='1.Quality'!E20 -> % | F5: ='1.Quality'!F20 -> Higher the better | G5: ='1.Quality'!G20 -> Monthly | H5: =IF('1.Quality'!H20="","",'1.Quality'!H20) -> Target | I5: =IF('1.Quality'!I20="","",'1.Quality'!I20) -> 0.95 | J5: =IF('1.Quality'!J20="","",'1.Quality'!J20) -> 0.95 | K5: =IF('1.Quality'!K20="","",'1.Quality'!K20) -> 0.95 | L5: =IF('1.Quality'!L20="","",'1.Quality'!L20) -> 0.95 | M5: =IF('1.Quality'!M20="","",'1.Quality'!M20) -> 0.95 | N5: =IF('1.Quality'!N20="","",'1.Quality'!N20) -> 0.95 | O5: =IF('1.Quality'!O20="","",'1.Quality'!O20) -> 0.95 | ... T5: =IF('1.Quality'!T20="","",'1.Quality'!T20) -> 0.95
A6: ='1.Quality'!A20 -> % CAPA implementation Tasks on time | B6: ='1.Quality'!B20 -> Number of actions completed without extension / Number of CAPA actions planned in that month as per Plan | C6: ='1.Quality'!C20 -> > | D6: ='1.Quality'!D20 -> 95 | E6: ='1.Quality'!E20 -> % | F6: ='1.Quality'!F20 -> Higher the better | G6: ='1.Quality'!G20 -> Monthly | H6: =IF('1.Quality'!H21="","",'1.Quality'!H21) -> Actual | I6: =IF('1.Quality'!I21="","",'1.Quality'!I21) -> 0.22 | J6: =IF('1.Quality'!J21="","",'1.Quality'!J21) -> 0.4 | K6: =IF('1.Quality'!K21="","",'1.Quality'!K21) -> 0.22 | L6: =IF('1.Quality'!L21="","",'1.Quality'!L21) -> 0.4 | M6: =IF('1.Quality'!M21="","",'1.Quality'!M21) -> 0.875 | N6: =IF('1.Quality'!N21="","",'1.Quality'!N21) -> 0.3 | O6: =IF('1.Quality'!O21="","",'1.Quality'!O21) -> 0.4 | ... T6: =IF('1.Quality'!T21="","",'1.Quality'!T21)
A7: ='1.Quality'!A22 -> # of C&R in pre- release(Track remaining C&R) | B7: ='1.Quality'!B22 -> # of C&Rs waiting on C&R initiation | C7: ='1.Quality'!C22 -> <= | D7: ='1.Quality'!D22 -> 10 | E7: ='1.Quality'!E22 -> No. | F7: ='1.Quality'!F22 -> Lower the better | G7: ='1.Quality'!G22 -> Monthly | H7: =IF('1.Quality'!H22="","",'1.Quality'!H22) -> Target | I7: =IF('1.Quality'!I22="","",'1.Quality'!I22) -> 6 | J7: =IF('1.Quality'!J22="","",'1.Quality'!J22) -> 5 | K7: =IF('1.Quality'!K22="","",'1.Quality'!K22) -> 5 | L7: =IF('1.Quality'!L22="","",'1.Quality'!L22) -> 4 | M7: =IF('1.Quality'!M22="","",'1.Quality'!M22) -> 4 | N7: =IF('1.Quality'!N22="","",'1.Quality'!N22) -> 4 | O7: =IF('1.Quality'!O22="","",'1.Quality'!O22) -> 4 | ... T7: =IF('1.Quality'!T22="","",'1.Quality'!T22) -> 0
A8: ='1.Quality'!A22 -> # of C&R in pre- release(Track remaining C&R) | B8: ='1.Quality'!B22 -> # of C&Rs waiting on C&R initiation | C8: ='1.Quality'!C22 -> <= | D8: ='1.Quality'!D22 -> 10 | E8: ='1.Quality'!E22 -> No. | F8: ='1.Quality'!F22 -> Lower the better | G8: ='1.Quality'!G22 -> Monthly | H8: =IF('1.Quality'!H23="","",'1.Quality'!H23) -> Actual | I8: =IF('1.Quality'!I23="","",'1.Quality'!I23) -> 6 | J8: =IF('1.Quality'!J23="","",'1.Quality'!J23) -> 5 | K8: =IF('1.Quality'!K23="","",'1.Quality'!K23) -> 5 | L8: =IF('1.Quality'!L23="","",'1.Quality'!L23) -> 4 | M8: =IF('1.Quality'!M23="","",'1.Quality'!M23) -> 4 | N8: =IF('1.Quality'!N23="","",'1.Quality'!N23) -> 4 | O8: =IF('1.Quality'!O23="","",'1.Quality'!O23) -> 4 | ... T8: =IF('1.Quality'!T23="","",'1.Quality'!T23)
A9: ='1.Quality'!#REF! -> #REF! | B9: ='1.Quality'!#REF! -> #REF! | C9: ='1.Quality'!#REF! -> #REF! | D9: ='1.Quality'!#REF! -> #REF! | E9: ='1.Quality'!#REF! -> #REF! | F9: ='1.Quality'!#REF! -> #REF! | G9: ='1.Quality'!#REF! -> #REF! | H9: =IF('1.Quality'!#REF!="","",'1.Quality'!#REF!) -> #REF! | I9: =IF('1.Quality'!#REF!="","",'1.Quality'!#REF!) -> #REF! | J9: =IF('1.Quality'!#REF!="","",'1.Quality'!#REF!) -> #REF! | K9: =IF('1.Quality'!#REF!="","",'1.Quality'!#REF!) -> #REF! | L9: =IF('1.Quality'!#REF!="","",'1.Quality'!#REF!) -> #REF! | M9: =IF('1.Quality'!#REF!="","",'1.Quality'!#REF!) -> #REF! | N9: =IF('1.Quality'!#REF!="","",'1.Quality'!#REF!) -> #REF! | O9: =IF('1.Quality'!#REF!="","",'1.Quality'!#REF!) -> #REF! | ... T9: =IF('1.Quality'!#REF!="","",'1.Quality'!#REF!) -> #REF!
A10: ='1.Quality'!#REF! -> #REF! | B10: ='1.Quality'!#REF! -> #REF! | C10: ='1.Quality'!#REF! -> #REF! | D10: ='1.Quality'!#REF! -> #REF! | E10: ='1.Quality'!#REF! -> #REF! | F10: ='1.Quality'!#REF! -> #REF! | G10: ='1.Quality'!#REF! -> #REF! | H10: =IF('1.Quality'!#REF!="","",'1.Quality'!#REF!) -> #REF! | I10: =IF('1.Quality'!#REF!="","",'1.Quality'!#REF!) -> #REF! | J10: =IF('1.Quality'!#REF!="","",'1.Quality'!#REF!) -> #REF! | K10: =IF('1.Quality'!#REF!="","",'1.Quality'!#REF!) -> #REF! | L10: =IF('1.Quality'!#REF!="","",'1.Quality'!#REF!) -> #REF! | M10: =IF('1.Quality'!#REF!="","",'1.Quality'!#REF!) -> #REF! | N10: =IF('1.Quality'!#REF!="","",'1.Quality'!#REF!) -> #REF! | O10: =IF('1.Quality'!#REF!="","",'1.Quality'!#REF!) -> #REF! | ... T10: =IF('1.Quality'!#REF!="","",'1.Quality'!#REF!) -> #REF!
A11: ='1.Quality'!#REF! -> #REF! | B11: ='1.Quality'!#REF! -> #REF! | C11: ='1.Quality'!#REF! -> #REF! | D11: ='1.Quality'!#REF! -> #REF! | E11: ='1.Quality'!#REF! -> #REF! | F11: ='1.Quality'!#REF! -> #REF! | G11: ='1.Quality'!#REF! -> #REF! | H11: =IF('1.Quality'!#REF!="","",'1.Quality'!#REF!) -> #REF! | I11: =IF('1.Quality'!#REF!="","",'1.Quality'!#REF!) -> #REF! | J11: =IF('1.Quality'!#REF!="","",'1.Quality'!#REF!) -> #REF! | K11: =IF('1.Quality'!#REF!="","",'1.Quality'!#REF!) -> #REF! | L11: =IF('1.Quality'!#REF!="","",'1.Quality'!#REF!) -> #REF! | M11: =IF('1.Quality'!#REF!="","",'1.Quality'!#REF!) -> #REF! | N11: =IF('1.Quality'!#REF!="","",'1.Quality'!#REF!) -> #REF! | O11: =IF('1.Quality'!#REF!="","",'1.Quality'!#REF!) -> #REF! | ... T11: =IF('1.Quality'!#REF!="","",'1.Quality'!#REF!) -> #REF!
A12: ='1.Quality'!#REF! -> #REF! | B12: ='1.Quality'!#REF! -> #REF! | C12: ='1.Quality'!#REF! -> #REF! | D12: ='1.Quality'!#REF! -> #REF! | E12: ='1.Quality'!#REF! -> #REF! | F12: ='1.Quality'!#REF! -> #REF! | G12: ='1.Quality'!#REF! -> #REF! | H12: =IF('1.Quality'!#REF!="","",'1.Quality'!#REF!) -> #REF! | I12: =IF('1.Quality'!#REF!="","",'1.Quality'!#REF!) -> #REF! | J12: =IF('1.Quality'!#REF!="","",'1.Quality'!#REF!) -> #REF! | K12: =IF('1.Quality'!#REF!="","",'1.Quality'!#REF!) -> #REF! | L12: =IF('1.Quality'!#REF!="","",'1.Quality'!#REF!) -> #REF! | M12: =IF('1.Quality'!#REF!="","",'1.Quality'!#REF!) -> #REF! | N12: =IF('1.Quality'!#REF!="","",'1.Quality'!#REF!) -> #REF! | O12: =IF('1.Quality'!#REF!="","",'1.Quality'!#REF!) -> #REF! | ... T12: =IF('1.Quality'!#REF!="","",'1.Quality'!#REF!) -> #REF!
A13: ='1.Quality'!A24 -> Audit | B13: ='1.Quality'!B24 -> # Major Findings in external audits | C13: ='1.Quality'!C24 -> = | D13: ='1.Quality'!D24 -> 0 | E13: ='1.Quality'!E24 -> No. | F13: ='1.Quality'!F24 -> Lower the better | G13: ='1.Quality'!G24 -> Half yearly | H13: =IF('1.Quality'!H24="","",'1.Quality'!H24) -> Target | I13: =IF('1.Quality'!I24="","",'1.Quality'!I24) -> 0 | J13: =IF('1.Quality'!J24="","",'1.Quality'!J24) -> 0 | K13: =IF('1.Quality'!K24="","",'1.Quality'!K24) -> 0 | L13: =IF('1.Quality'!L24="","",'1.Quality'!L24) -> 0 | M13: =IF('1.Quality'!M24="","",'1.Quality'!M24) -> 0 | N13: =IF('1.Quality'!N24="","",'1.Quality'!N24) -> 0 | O13: =IF('1.Quality'!O24="","",'1.Quality'!O24) -> 0 | ... T13: =IF('1.Quality'!T24="","",'1.Quality'!T24) -> 0
A14: ='1.Quality'!A24 -> Audit | B14: ='1.Quality'!B24 -> # Major Findings in external audits | C14: ='1.Quality'!C24 -> = | D14: ='1.Quality'!D24 -> 0 | E14: ='1.Quality'!E24 -> No. | F14: ='1.Quality'!F24 -> Lower the better | G14: ='1.Quality'!G24 -> Half yearly | H14: =IF('1.Quality'!H25="","",'1.Quality'!H25) -> Actual | I14: =IF('1.Quality'!I25="","",'1.Quality'!I25) -> 0 | J14: =IF('1.Quality'!J25="","",'1.Quality'!J25) -> 0 | K14: =IF('1.Quality'!K25="","",'1.Quality'!K25) -> 0 | L14: =IF('1.Quality'!L25="","",'1.Quality'!L25) -> 0 | M14: =IF('1.Quality'!M25="","",'1.Quality'!M25) -> 0 | N14: =IF('1.Quality'!N25="","",'1.Quality'!N25) -> 0 | O14: =IF('1.Quality'!O25="","",'1.Quality'!O25) -> 0 | ... T14: =IF('1.Quality'!T25="","",'1.Quality'!T25)
A16: Regulatory
A17: KPI Name | B17: KPI Definition | C17: Operators | D17: Target AOP 2026 | E17: Units | F17: Metric nature | G17: Frequency | H17: Target/ Actual | I17: Jan-2026 | J17: Feb-2026 | K17: Mar-2026 | L17: Apr-2026 | M17: May-2026 | N17: Jun-2026 | O17: Jul-2026 | P17: Aug-2026 | Q17: Sep-2026 | R17: Oct-2026 | S17: Nov-2026 | T17: Dec-2026
A18: ='2.Regulatory'!A14 -> Country readiness | B18: ='2.Regulatory'!B14 -> (Orders impacted due to regulatory or other readiness-related blocks) *100/ Total orders planned for that month | C18: ='2.Regulatory'!C14 -> <= | D18: ='2.Regulatory'!D14 -> 0.1 | E18: ='2.Regulatory'!E14 -> % | F18: ='2.Regulatory'!F14 -> Lower the better | G18: ='2.Regulatory'!G14 -> Monthly | H18: =IF('2.Regulatory'!H14="","",'2.Regulatory'!H14) -> Target | I18: =IF('2.Regulatory'!I14="","",'2.Regulatory'!I14) -> 0.1 | J18: =IF('2.Regulatory'!J14="","",'2.Regulatory'!J14) -> 0.1 | K18: =IF('2.Regulatory'!K14="","",'2.Regulatory'!K14) -> 0.1 | L18: =IF('2.Regulatory'!L14="","",'2.Regulatory'!L14) -> 0.1 | M18: =IF('2.Regulatory'!M14="","",'2.Regulatory'!M14) -> 0.1 | N18: =IF('2.Regulatory'!N14="","",'2.Regulatory'!N14) -> 0.1 | O18: =IF('2.Regulatory'!O14="","",'2.Regulatory'!O14) -> 0.1 | ... T18: =IF('2.Regulatory'!T14="","",'2.Regulatory'!T14) -> 0.1
A19: ='2.Regulatory'!A14 -> Country readiness | B19: ='2.Regulatory'!B14 -> (Orders impacted due to regulatory or other readiness-related blocks) *100/ Total orders planned for that month | C19: ='2.Regulatory'!C14 -> <= | D19: ='2.Regulatory'!D14 -> 0.1 | E19: ='2.Regulatory'!E14 -> % | F19: ='2.Regulatory'!F14 -> Lower the better | G19: ='2.Regulatory'!G14 -> Monthly | H19: =IF('2.Regulatory'!H15="","",'2.Regulatory'!H15) -> Actual | I19: =IF('2.Regulatory'!I15="","",'2.Regulatory'!I15) -> 0 | J19: =IF('2.Regulatory'!J15="","",'2.Regulatory'!J15) -> 0.011111111 | K19: =IF('2.Regulatory'!K15="","",'2.Regulatory'!K15) -> 0 | L19: =IF('2.Regulatory'!L15="","",'2.Regulatory'!L15) -> 0 | M19: =IF('2.Regulatory'!M15="","",'2.Regulatory'!M15) -> 0 | N19: =IF('2.Regulatory'!N15="","",'2.Regulatory'!N15) -> 0 | O19: =IF('2.Regulatory'!O15="","",'2.Regulatory'!O15) -> 0 | ... T19: =IF('2.Regulatory'!T15="","",'2.Regulatory'!T15)
A20: ='2.Regulatory'!A16 -> Product Change assessment | B20: ='2.Regulatory'!B16 -> (Product change assessments completed by Regulatory within 6 weeks from the date of request) *100/ Total change assessments completion planned during that month | C20: ='2.Regulatory'!C16 -> >= | D20: ='2.Regulatory'!D16 -> 0.95 | E20: ='2.Regulatory'!E16 -> % | F20: ='2.Regulatory'!F16 -> Higher the better | G20: ='2.Regulatory'!G16 -> Monthly | H20: =IF('2.Regulatory'!H16="","",'2.Regulatory'!H16) -> Target | I20: =IF('2.Regulatory'!I16="","",'2.Regulatory'!I16) -> 0.95 | J20: =IF('2.Regulatory'!J16="","",'2.Regulatory'!J16) -> 0.95 | K20: =IF('2.Regulatory'!K16="","",'2.Regulatory'!K16) -> 0.95 | L20: =IF('2.Regulatory'!L16="","",'2.Regulatory'!L16) -> 0.95 | M20: =IF('2.Regulatory'!M16="","",'2.Regulatory'!M16) -> 0.95 | N20: =IF('2.Regulatory'!N16="","",'2.Regulatory'!N16) -> 0.95 | O20: =IF('2.Regulatory'!O16="","",'2.Regulatory'!O16) -> 0.95 | ... T20: =IF('2.Regulatory'!T16="","",'2.Regulatory'!T16) -> 0.95
A21: ='2.Regulatory'!A16 -> Product Change assessment | B21: ='2.Regulatory'!B16 -> (Product change assessments completed by Regulatory within 6 weeks from the date of request) *100/ Total change assessments completion planned during that month | C21: ='2.Regulatory'!C16 -> >= | D21: ='2.Regulatory'!D16 -> 0.95 | E21: ='2.Regulatory'!E16 -> % | F21: ='2.Regulatory'!F16 -> Higher the better | G21: ='2.Regulatory'!G16 -> Monthly | H21: =IF('2.Regulatory'!H17="","",'2.Regulatory'!H17) -> Actual | I21: =IF('2.Regulatory'!I17="","",'2.Regulatory'!I17) -> 1 | J21: =IF('2.Regulatory'!J17="","",'2.Regulatory'!J17) -> 0.5 | K21: =IF('2.Regulatory'!K17="","",'2.Regulatory'!K17) -> 1 | L21: =IF('2.Regulatory'!L17="","",'2.Regulatory'!L17) -> 0 | M21: =IF('2.Regulatory'!M17="","",'2.Regulatory'!M17) -> 1 | N21: =IF('2.Regulatory'!N17="","",'2.Regulatory'!N17) -> 1 | O21: =IF('2.Regulatory'!O17="","",'2.Regulatory'!O17) -> 1 | ... T21: =IF('2.Regulatory'!T17="","",'2.Regulatory'!T17)
A22: ='2.Regulatory'!A18 -> Submission readiness | B22: ='2.Regulatory'!B18 -> (Completed regulatory submission documents) *100/ Total submission deliverables needed for each planned country submission | C22: ='2.Regulatory'!C18 -> = | D22: ='2.Regulatory'!D18 -> 1 | E22: ='2.Regulatory'!E18 -> % | F22: ='2.Regulatory'!F18 -> Higher the better | G22: ='2.Regulatory'!G18 -> Monthly | H22: =IF('2.Regulatory'!H18="","",'2.Regulatory'!H18) -> Target | I22: =IF('2.Regulatory'!I18="","",'2.Regulatory'!I18) -> 1 | J22: =IF('2.Regulatory'!J18="","",'2.Regulatory'!J18) -> 1 | K22: =IF('2.Regulatory'!K18="","",'2.Regulatory'!K18) -> 1 | L22: =IF('2.Regulatory'!L18="","",'2.Regulatory'!L18) -> 1 | M22: =IF('2.Regulatory'!M18="","",'2.Regulatory'!M18) -> 1 | N22: =IF('2.Regulatory'!N18="","",'2.Regulatory'!N18) -> 1 | O22: =IF('2.Regulatory'!O18="","",'2.Regulatory'!O18) -> 1 | ... T22: =IF('2.Regulatory'!T18="","",'2.Regulatory'!T18) -> 1
A23: ='2.Regulatory'!A18 -> Submission readiness | B23: ='2.Regulatory'!B18 -> (Completed regulatory submission documents) *100/ Total submission deliverables needed for each planned country submission | C23: ='2.Regulatory'!C18 -> = | D23: ='2.Regulatory'!D18 -> 1 | E23: ='2.Regulatory'!E18 -> % | F23: ='2.Regulatory'!F18 -> Higher the better | G23: ='2.Regulatory'!G18 -> Monthly | H23: =IF('2.Regulatory'!H19="","",'2.Regulatory'!H19) -> Actual | I23: =IF('2.Regulatory'!I19="","",'2.Regulatory'!I19) -> 1 | J23: =IF('2.Regulatory'!J19="","",'2.Regulatory'!J19) -> 1 | K23: =IF('2.Regulatory'!K19="","",'2.Regulatory'!K19) -> 1 | L23: =IF('2.Regulatory'!L19="","",'2.Regulatory'!L19) -> 0.93939394 | M23: =IF('2.Regulatory'!M19="","",'2.Regulatory'!M19) -> 1 | N23: =IF('2.Regulatory'!N19="","",'2.Regulatory'!N19) -> 1 | O23: =IF('2.Regulatory'!O19="","",'2.Regulatory'!O19) -> 1 | ... T23: =IF('2.Regulatory'!T19="","",'2.Regulatory'!T19)
A24: ='2.Regulatory'!A20 -> Quality of submission | B24: ='2.Regulatory'!B20 -> (Planned regulatory submissions accepted first-time-right) *100/ Total submission submitted in that month | C24: ='2.Regulatory'!C20 -> >= | D24: ='2.Regulatory'!D20 -> 0.95 | E24: ='2.Regulatory'!E20 -> % | F24: ='2.Regulatory'!F20 -> Higher the better | G24: ='2.Regulatory'!G20 -> Monthly | H24: =IF('2.Regulatory'!H20="","",'2.Regulatory'!H20) -> Target | I24: =IF('2.Regulatory'!I20="","",'2.Regulatory'!I20) -> 0.95 | J24: =IF('2.Regulatory'!J20="","",'2.Regulatory'!J20) -> 0.95 | K24: =IF('2.Regulatory'!K20="","",'2.Regulatory'!K20) -> 0.95 | L24: =IF('2.Regulatory'!L20="","",'2.Regulatory'!L20) -> 0.95 | M24: =IF('2.Regulatory'!M20="","",'2.Regulatory'!M20) -> 0.95 | N24: =IF('2.Regulatory'!N20="","",'2.Regulatory'!N20) -> 0.95 | O24: =IF('2.Regulatory'!O20="","",'2.Regulatory'!O20) -> 0.95 | ... T24: =IF('2.Regulatory'!T20="","",'2.Regulatory'!T20) -> 0.95
A25: ='2.Regulatory'!A20 -> Quality of submission | B25: ='2.Regulatory'!B20 -> (Planned regulatory submissions accepted first-time-right) *100/ Total submission submitted in that month | C25: ='2.Regulatory'!C20 -> >= | D25: ='2.Regulatory'!D20 -> 0.95 | E25: ='2.Regulatory'!E20 -> % | F25: ='2.Regulatory'!F20 -> Higher the better | G25: ='2.Regulatory'!G20 -> Monthly | H25: =IF('2.Regulatory'!H21="","",'2.Regulatory'!H21) -> Actual | I25: =IF('2.Regulatory'!I21="","",'2.Regulatory'!I21) -> 1 | J25: =IF('2.Regulatory'!J21="","",'2.Regulatory'!J21) -> 1 | K25: =IF('2.Regulatory'!K21="","",'2.Regulatory'!K21) -> 0.97058824 | L25: =IF('2.Regulatory'!L21="","",'2.Regulatory'!L21) -> 1 | M25: =IF('2.Regulatory'!M21="","",'2.Regulatory'!M21) -> 1 | N25: =IF('2.Regulatory'!N21="","",'2.Regulatory'!N21) -> 1 | O25: =IF('2.Regulatory'!O21="","",'2.Regulatory'!O21) -> 1 | ... T25: =IF('2.Regulatory'!T21="","",'2.Regulatory'!T21)
A27: ISC
A28: KPI Name | B28: KPI Definition | C28: Operators | D28: Target AOP 2026 | E28: Units | F28: Metric nature | G28: Frequency | H28: Target/ Actual | I28: Jan-2026 | J28: Feb-2026 | K28: Mar-2026 | L28: Apr-2026 | M28: May-2026 | N28: Jun-2026 | O28: Jul-2026 | P28: Aug-2026 | Q28: Sep-2026 | R28: Oct-2026 | S28: Nov-2026 | T28: Dec-2026
A29: ='3.ISC '!A14 -> Ontime supply | B29: ='3.ISC '!B14 -> FSD adherance | C29: ='3.ISC '!C14 -> > | D29: ='3.ISC '!D14 -> 0.9 | E29: ='3.ISC '!E14 -> % | F29: ='3.ISC '!F14 -> Higher the better | G29: ='3.ISC '!G14 -> Monthly | H29: =IF('3.ISC '!H14="","",'3.ISC '!H14) -> Target | I29: =IF('3.ISC '!I14="","",'3.ISC '!I14) -> 0.9 | J29: =IF('3.ISC '!J14="","",'3.ISC '!J14) -> 0.9 | K29: =IF('3.ISC '!K14="","",'3.ISC '!K14) -> 0.9 | L29: =IF('3.ISC '!L14="","",'3.ISC '!L14) -> 0.9 | M29: =IF('3.ISC '!M14="","",'3.ISC '!M14) -> 0.9 | N29: =IF('3.ISC '!N14="","",'3.ISC '!N14) -> 0.9 | O29: =IF('3.ISC '!O14="","",'3.ISC '!O14) -> 0.9 | ... T29: =IF('3.ISC '!T14="","",'3.ISC '!T14) -> 0.9
A30: ='3.ISC '!A14 -> Ontime supply | B30: ='3.ISC '!B14 -> FSD adherance | C30: ='3.ISC '!C14 -> > | D30: ='3.ISC '!D14 -> 0.9 | E30: ='3.ISC '!E14 -> % | F30: ='3.ISC '!F14 -> Higher the better | G30: ='3.ISC '!G14 -> Monthly | H30: =IF('3.ISC '!H15="","",'3.ISC '!H15) -> Actual | I30: =IF('3.ISC '!I15="","",'3.ISC '!I15) -> 0.91 | J30: =IF('3.ISC '!J15="","",'3.ISC '!J15) -> 0.96 | K30: =IF('3.ISC '!K15="","",'3.ISC '!K15) -> 0.66 | L30: =IF('3.ISC '!L15="","",'3.ISC '!L15) -> 0.73 | M30: =IF('3.ISC '!M15="","",'3.ISC '!M15) -> 0.71 | N30: =IF('3.ISC '!N15="","",'3.ISC '!N15) -> 0.95 | O30: =IF('3.ISC '!O15="","",'3.ISC '!O15) -> 0.92 | ... T30: =IF('3.ISC '!T15="","",'3.ISC '!T15)
A31: ='3.ISC '!A16 -> Production units | B31: ='3.ISC '!B16 -> Production number | C31: ='3.ISC '!C16 -> > | D31: ='3.ISC '!D16 -> 1332/1400 | E31: ='3.ISC '!E16 -> No. | F31: ='3.ISC '!F16 -> Higher the better | G31: ='3.ISC '!G16 -> Monthly | H31: =IF('3.ISC '!H16="","",'3.ISC '!H16) -> Target | I31: =IF('3.ISC '!I16="","",'3.ISC '!I16) | J31: =IF('3.ISC '!J16="","",'3.ISC '!J16) -> 118 | K31: =IF('3.ISC '!K16="","",'3.ISC '!K16) -> 124 | L31: =IF('3.ISC '!L16="","",'3.ISC '!L16) -> 129 | M31: =IF('3.ISC '!M16="","",'3.ISC '!M16) -> 132 | N31: =IF('3.ISC '!N16="","",'3.ISC '!N16) -> 130 | O31: =IF('3.ISC '!O16="","",'3.ISC '!O16) -> 125 | ... T31: =IF('3.ISC '!T16="","",'3.ISC '!T16) -> 79
A32: ='3.ISC '!A16 -> Production units | B32: ='3.ISC '!B16 -> Production number | C32: ='3.ISC '!C16 -> > | D32: ='3.ISC '!D16 -> 1332/1400 | E32: ='3.ISC '!E16 -> No. | F32: ='3.ISC '!F16 -> Higher the better | G32: ='3.ISC '!G16 -> Monthly | H32: =IF('3.ISC '!H17="","",'3.ISC '!H17) -> Actual | I32: =IF('3.ISC '!I17="","",'3.ISC '!I17) -> 113 | J32: =IF('3.ISC '!J17="","",'3.ISC '!J17) -> 119 | K32: =IF('3.ISC '!K17="","",'3.ISC '!K17) -> 111 | L32: =IF('3.ISC '!L17="","",'3.ISC '!L17) -> 89 | M32: =IF('3.ISC '!M17="","",'3.ISC '!M17) -> 113 | N32: =IF('3.ISC '!N17="","",'3.ISC '!N17) -> 109 | O32: =IF('3.ISC '!O17="","",'3.ISC '!O17) -> 116 | ... T32: =IF('3.ISC '!T17="","",'3.ISC '!T17)
A33: ='3.ISC '!A18 -> CTB (12 weeks) | B33: ='3.ISC '!B18 -> Clear to build material avaialbility | C33: ='3.ISC '!C18 -> > | D33: ='3.ISC '!D18 -> 0.9 | E33: ='3.ISC '!E18 -> % | F33: ='3.ISC '!F18 -> Higher the better | G33: ='3.ISC '!G18 -> Monthly | H33: =IF('3.ISC '!H18="","",'3.ISC '!H18) -> Target | I33: =IF('3.ISC '!I18="","",'3.ISC '!I18) -> 0.85 | J33: =IF('3.ISC '!J18="","",'3.ISC '!J18) -> 0.87 | K33: =IF('3.ISC '!K18="","",'3.ISC '!K18) -> 0.9 | L33: =IF('3.ISC '!L18="","",'3.ISC '!L18) -> 0.9 | M33: =IF('3.ISC '!M18="","",'3.ISC '!M18) -> 0.9 | N33: =IF('3.ISC '!N18="","",'3.ISC '!N18) -> 0.9 | O33: =IF('3.ISC '!O18="","",'3.ISC '!O18) -> 0.9 | ... T33: =IF('3.ISC '!T18="","",'3.ISC '!T18) -> 0.92
A34: ='3.ISC '!A18 -> CTB (12 weeks) | B34: ='3.ISC '!B18 -> Clear to build material avaialbility | C34: ='3.ISC '!C18 -> > | D34: ='3.ISC '!D18 -> 0.9 | E34: ='3.ISC '!E18 -> % | F34: ='3.ISC '!F18 -> Higher the better | G34: ='3.ISC '!G18 -> Monthly | H34: =IF('3.ISC '!H19="","",'3.ISC '!H19) -> Actual | I34: =IF('3.ISC '!I19="","",'3.ISC '!I19) -> 0.93 | J34: =IF('3.ISC '!J19="","",'3.ISC '!J19) -> 0.89 | K34: =IF('3.ISC '!K19="","",'3.ISC '!K19) -> 0.88 | L34: =IF('3.ISC '!L19="","",'3.ISC '!L19) -> 0.84 | M34: =IF('3.ISC '!M19="","",'3.ISC '!M19) -> 0.93 | N34: =IF('3.ISC '!N19="","",'3.ISC '!N19) -> 0.93 | O34: =IF('3.ISC '!O19="","",'3.ISC '!O19) -> 0.92 | ... T34: =IF('3.ISC '!T19="","",'3.ISC '!T19)
A35: ='3.ISC '!A20 -> OOH % | B35: ='3.ISC '!B20 -> OOH % for revnue in the Qtr | C35: ='3.ISC '!C20 -> > | D35: ='3.ISC '!D20 -> % | E35: ='3.ISC '!E20 -> % | F35: ='3.ISC '!F20 -> Higher the better | G35: ='3.ISC '!G20 -> Monthly | H35: =IF('3.ISC '!H20="","",'3.ISC '!H20) -> Target | I35: =IF('3.ISC '!I20="","",'3.ISC '!I20) -> 0.8 | J35: =IF('3.ISC '!J20="","",'3.ISC '!J20) -> 0.9 | K35: =IF('3.ISC '!K20="","",'3.ISC '!K20) -> 0.95 | L35: =IF('3.ISC '!L20="","",'3.ISC '!L20) -> 0.8 | M35: =IF('3.ISC '!M20="","",'3.ISC '!M20) -> 0.9 | N35: =IF('3.ISC '!N20="","",'3.ISC '!N20) -> 0.95 | O35: =IF('3.ISC '!O20="","",'3.ISC '!O20) -> 0.8 | ... T35: =IF('3.ISC '!T20="","",'3.ISC '!T20)
A36: ='3.ISC '!A20 -> OOH % | B36: ='3.ISC '!B20 -> OOH % for revnue in the Qtr | C36: ='3.ISC '!C20 -> > | D36: ='3.ISC '!D20 -> % | E36: ='3.ISC '!E20 -> % | F36: ='3.ISC '!F20 -> Higher the better | G36: ='3.ISC '!G20 -> Monthly | H36: =IF('3.ISC '!H21="","",'3.ISC '!H21) -> Actual | I36: =IF('3.ISC '!I21="","",'3.ISC '!I21) -> 0.8 | J36: =IF('3.ISC '!J21="","",'3.ISC '!J21) -> 0.9 | K36: =IF('3.ISC '!K21="","",'3.ISC '!K21) -> 1.02 | L36: =IF('3.ISC '!L21="","",'3.ISC '!L21) -> 0.6 | M36: =IF('3.ISC '!M21="","",'3.ISC '!M21) -> 0.72 | N36: =IF('3.ISC '!N21="","",'3.ISC '!N21) -> 0.81 | O36: =IF('3.ISC '!O21="","",'3.ISC '!O21) -> 0.56 | ... T36: =IF('3.ISC '!T21="","",'3.ISC '!T21)
A37: ='3.ISC '!A22 -> Market Inventory | B37: ='3.ISC '!B22 -> Market inventory | C37: ='3.ISC '!C22 -> < | D37: ='3.ISC '!D22 -> 10 % reduction | E37: ='3.ISC '!E22 -> Mn | F37: ='3.ISC '!F22 -> Lower the better | G37: ='3.ISC '!G22 -> Monthly | H37: =IF('3.ISC '!H22="","",'3.ISC '!H22) -> Target | I37: =IF('3.ISC '!I22="","",'3.ISC '!I22) -> 11.540479 | J37: =IF('3.ISC '!J22="","",'3.ISC '!J22) -> 13.985593 | K37: =IF('3.ISC '!K22="","",'3.ISC '!K22) -> 14.900208 | L37: =IF('3.ISC '!L22="","",'3.ISC '!L22) -> 15.546561 | M37: =IF('3.ISC '!M22="","",'3.ISC '!M22) -> 12.923735 | N37: =IF('3.ISC '!N22="","",'3.ISC '!N22) -> 13.018238 | O37: =IF('3.ISC '!O22="","",'3.ISC '!O22) -> 11.345502 | ... T37: =IF('3.ISC '!T22="","",'3.ISC '!T22) -> 9.5717963
A38: ='3.ISC '!A22 -> Market Inventory | B38: ='3.ISC '!B22 -> Market inventory | C38: ='3.ISC '!C22 -> < | D38: ='3.ISC '!D22 -> 10 % reduction | E38: ='3.ISC '!E22 -> Mn | F38: ='3.ISC '!F22 -> Lower the better | G38: ='3.ISC '!G22 -> Monthly | H38: =IF('3.ISC '!H23="","",'3.ISC '!H23) -> Actual | I38: =IF('3.ISC '!I23="","",'3.ISC '!I23) -> 17.3 | J38: =IF('3.ISC '!J23="","",'3.ISC '!J23) -> 21.89 | K38: =IF('3.ISC '!K23="","",'3.ISC '!K23) -> 21.44 | L38: =IF('3.ISC '!L23="","",'3.ISC '!L23) -> 24.02 | M38: =IF('3.ISC '!M23="","",'3.ISC '!M23) -> 24.1 | N38: =IF('3.ISC '!N23="","",'3.ISC '!N23) -> 22.5 | O38: =IF('3.ISC '!O23="","",'3.ISC '!O23) -> 23 | ... T38: =IF('3.ISC '!T23="","",'3.ISC '!T23)
A39: ='3.ISC '!A24 -> CDD push out / month | B39: ='3.ISC '!B24 -> CDD move out during to execution | C39: ='3.ISC '!C24 -> <= | D39: ='3.ISC '!D24 -> 15 | E39: ='3.ISC '!E24 -> No. | F39: ='3.ISC '!F24 -> Lower the better | G39: ='3.ISC '!G24 -> Monthly | H39: =IF('3.ISC '!H24="","",'3.ISC '!H24) -> Target | I39: =IF('3.ISC '!I24="","",'3.ISC '!I24) -> 15 | J39: =IF('3.ISC '!J24="","",'3.ISC '!J24) -> 15 | K39: =IF('3.ISC '!K24="","",'3.ISC '!K24) -> 15 | L39: =IF('3.ISC '!L24="","",'3.ISC '!L24) -> 15 | M39: =IF('3.ISC '!M24="","",'3.ISC '!M24) -> 15 | N39: =IF('3.ISC '!N24="","",'3.ISC '!N24) -> 15 | O39: =IF('3.ISC '!O24="","",'3.ISC '!O24) -> 15 | ... T39: =IF('3.ISC '!T24="","",'3.ISC '!T24) -> 15
A40: ='3.ISC '!A24 -> CDD push out / month | B40: ='3.ISC '!B24 -> CDD move out during to execution | C40: ='3.ISC '!C24 -> <= | D40: ='3.ISC '!D24 -> 15 | E40: ='3.ISC '!E24 -> No. | F40: ='3.ISC '!F24 -> Lower the better | G40: ='3.ISC '!G24 -> Monthly | H40: =IF('3.ISC '!H25="","",'3.ISC '!H25) -> Actual | I40: =IF('3.ISC '!I25="","",'3.ISC '!I25) -> 7 | J40: =IF('3.ISC '!J25="","",'3.ISC '!J25) -> 8 | K40: =IF('3.ISC '!K25="","",'3.ISC '!K25) -> 28 | L40: =IF('3.ISC '!L25="","",'3.ISC '!L25) -> 16 | M40: =IF('3.ISC '!M25="","",'3.ISC '!M25) -> 20 | N40: =IF('3.ISC '!N25="","",'3.ISC '!N25) -> 9 | O40: =IF('3.ISC '!O25="","",'3.ISC '!O25) -> 13 | ... T40: =IF('3.ISC '!T25="","",'3.ISC '!T25)
A42: Supplier Quality
A43: KPI Name | B43: KPI Definition | C43: Operators | D43: Target AOP 2026 | E43: Units | F43: Metric nature | G43: Frequency | H43: Target/ Actual | I43: Jan-2026 | J43: Feb-2026 | K43: Mar-2026 | L43: Apr-2026 | M43: May-2026 | N43: Jun-2026 | O43: Jul-2026 | P43: Aug-2026 | Q43: Sep-2026 | R43: Oct-2026 | S43: Nov-2026 | T43: Dec-2026
A44: ='3.ISC '!#REF! -> #REF! | B44: ='3.ISC '!#REF! -> #REF! | C44: ='3.ISC '!#REF! -> #REF! | D44: ='3.ISC '!#REF! -> #REF! | E44: ='3.ISC '!#REF! -> #REF! | F44: ='3.ISC '!#REF! -> #REF! | G44: ='3.ISC '!#REF! -> #REF! | H44: =IF('3.ISC '!#REF!="","",'3.ISC '!#REF!) -> #REF! | I44: =IF('3.ISC '!#REF!="","",'3.ISC '!#REF!) -> #REF! | J44: =IF('3.ISC '!#REF!="","",'3.ISC '!#REF!) -> #REF! | K44: =IF('3.ISC '!#REF!="","",'3.ISC '!#REF!) -> #REF! | L44: =IF('3.ISC '!#REF!="","",'3.ISC '!#REF!) -> #REF! | M44: =IF('3.ISC '!#REF!="","",'3.ISC '!#REF!) -> #REF! | N44: =IF('3.ISC '!#REF!="","",'3.ISC '!#REF!) -> #REF! | O44: =IF('3.ISC '!#REF!="","",'3.ISC '!#REF!) -> #REF! | ... T44: =IF('3.ISC '!#REF!="","",'3.ISC '!#REF!) -> #REF!
A45: ='3.ISC '!#REF! -> #REF! | B45: ='3.ISC '!#REF! -> #REF! | C45: ='3.ISC '!#REF! -> #REF! | D45: ='3.ISC '!#REF! -> #REF! | E45: ='3.ISC '!#REF! -> #REF! | F45: ='3.ISC '!#REF! -> #REF! | G45: ='3.ISC '!#REF! -> #REF! | H45: =IF('3.ISC '!#REF!="","",'3.ISC '!#REF!) -> #REF! | I45: =IF('3.ISC '!#REF!="","",'3.ISC '!#REF!) -> #REF! | J45: =IF('3.ISC '!#REF!="","",'3.ISC '!#REF!) -> #REF! | K45: =IF('3.ISC '!#REF!="","",'3.ISC '!#REF!) -> #REF! | L45: =IF('3.ISC '!#REF!="","",'3.ISC '!#REF!) -> #REF! | M45: =IF('3.ISC '!#REF!="","",'3.ISC '!#REF!) -> #REF! | N45: =IF('3.ISC '!#REF!="","",'3.ISC '!#REF!) -> #REF! | O45: =IF('3.ISC '!#REF!="","",'3.ISC '!#REF!) -> #REF! | ... T45: =IF('3.ISC '!#REF!="","",'3.ISC '!#REF!) -> #REF!
A46: ='3.ISC '!#REF! -> #REF! | B46: ='3.ISC '!#REF! -> #REF! | C46: ='3.ISC '!#REF! -> #REF! | D46: ='3.ISC '!#REF! -> #REF! | E46: ='3.ISC '!#REF! -> #REF! | F46: ='3.ISC '!#REF! -> #REF! | G46: ='3.ISC '!#REF! -> #REF! | H46: =IF('3.ISC '!#REF!="","",'3.ISC '!#REF!) -> #REF! | I46: =IF('3.ISC '!#REF!="","",'3.ISC '!#REF!) -> #REF! | J46: =IF('3.ISC '!#REF!="","",'3.ISC '!#REF!) -> #REF! | K46: =IF('3.ISC '!#REF!="","",'3.ISC '!#REF!) -> #REF! | L46: =IF('3.ISC '!#REF!="","",'3.ISC '!#REF!) -> #REF! | M46: =IF('3.ISC '!#REF!="","",'3.ISC '!#REF!) -> #REF! | N46: =IF('3.ISC '!#REF!="","",'3.ISC '!#REF!) -> #REF! | O46: =IF('3.ISC '!#REF!="","",'3.ISC '!#REF!) -> #REF! | ... T46: =IF('3.ISC '!#REF!="","",'3.ISC '!#REF!) -> #REF!
A47: ='3.ISC '!#REF! -> #REF! | B47: ='3.ISC '!#REF! -> #REF! | C47: ='3.ISC '!#REF! -> #REF! | D47: ='3.ISC '!#REF! -> #REF! | E47: ='3.ISC '!#REF! -> #REF! | F47: ='3.ISC '!#REF! -> #REF! | G47: ='3.ISC '!#REF! -> #REF! | H47: =IF('3.ISC '!#REF!="","",'3.ISC '!#REF!) -> #REF! | I47: =IF('3.ISC '!#REF!="","",'3.ISC '!#REF!) -> #REF! | J47: =IF('3.ISC '!#REF!="","",'3.ISC '!#REF!) -> #REF! | K47: =IF('3.ISC '!#REF!="","",'3.ISC '!#REF!) -> #REF! | L47: =IF('3.ISC '!#REF!="","",'3.ISC '!#REF!) -> #REF! | M47: =IF('3.ISC '!#REF!="","",'3.ISC '!#REF!) -> #REF! | N47: =IF('3.ISC '!#REF!="","",'3.ISC '!#REF!) -> #REF! | O47: =IF('3.ISC '!#REF!="","",'3.ISC '!#REF!) -> #REF! | ... T47: =IF('3.ISC '!#REF!="","",'3.ISC '!#REF!) -> #REF!
A49: Procurement
A50: KPI Name | B50: KPI Definition | C50: Operators | D50: Target AOP 2026 | E50: Units | F50: Metric nature | G50: Frequency | H50: Target/ Actual | I50: Jan-2026 | J50: Feb-2026 | K50: Mar-2026 | L50: Apr-2026 | M50: May-2026 | N50: Jun-2026 | O50: Jul-2026 | P50: Aug-2026 | Q50: Sep-2026 | R50: Oct-2026 | S50: Nov-2026 | T50: Dec-2026
A51: ='4.Procurement'!A14 -> RFQ closure to meet NPI / MLD deliverables | B51: ='4.Procurement'!B14 -> No of RFQ closed on time | C51: ='4.Procurement'!C14 -> <= | D51: ='4.Procurement'!D14 -> 1 | E51: ='4.Procurement'!E14 -> % | F51: ='4.Procurement'!F14 -> Higher the better | G51: ='4.Procurement'!G14 -> Monthly | H51: =IF('4.Procurement'!H14="","",'4.Procurement'!H14) -> Target | I51: =IF('4.Procurement'!I14="","",'4.Procurement'!I14) -> 15 | J51: =IF('4.Procurement'!J14="","",'4.Procurement'!J14) -> 10 | K51: =IF('4.Procurement'!K14="","",'4.Procurement'!K14) -> 15 | L51: =IF('4.Procurement'!L14="","",'4.Procurement'!L14) -> 22 | M51: =IF('4.Procurement'!M14="","",'4.Procurement'!M14) -> 1 | N51: =IF('4.Procurement'!N14="","",'4.Procurement'!N14) -> 10 | O51: =IF('4.Procurement'!O14="","",'4.Procurement'!O14) -> 1 | ... T51: =IF('4.Procurement'!T14="","",'4.Procurement'!T14) -> 0
A52: ='4.Procurement'!A14 -> RFQ closure to meet NPI / MLD deliverables | B52: ='4.Procurement'!B14 -> No of RFQ closed on time | C52: ='4.Procurement'!C14 -> <= | D52: ='4.Procurement'!D14 -> 1 | E52: ='4.Procurement'!E14 -> % | F52: ='4.Procurement'!F14 -> Higher the better | G52: ='4.Procurement'!G14 -> Monthly | H52: =IF('4.Procurement'!H15="","",'4.Procurement'!H15) -> Actual | I52: =IF('4.Procurement'!I15="","",'4.Procurement'!I15) -> 15 | J52: =IF('4.Procurement'!J15="","",'4.Procurement'!J15) -> 9 | K52: =IF('4.Procurement'!K15="","",'4.Procurement'!K15) -> 15 | L52: =IF('4.Procurement'!L15="","",'4.Procurement'!L15) -> 22 | M52: =IF('4.Procurement'!M15="","",'4.Procurement'!M15) -> 1 | N52: =IF('4.Procurement'!N15="","",'4.Procurement'!N15) -> 10 | O52: =IF('4.Procurement'!O15="","",'4.Procurement'!O15) -> 1 | ... T52: =IF('4.Procurement'!T15="","",'4.Procurement'!T15)
A53: ='4.Procurement'!A16 -> Supplier selection to meet NPI / MLD deliverables | B53: ='4.Procurement'!B16 -> supplier selection per 12 NC for NPI | C53: ='4.Procurement'!C16 -> <= | D53: ='4.Procurement'!D16 -> 1 | E53: ='4.Procurement'!E16 -> % | F53: ='4.Procurement'!F16 -> Higher the better | G53: ='4.Procurement'!G16 -> Monthly | H53: =IF('4.Procurement'!H16="","",'4.Procurement'!H16) -> Target | I53: =IF('4.Procurement'!I16="","",'4.Procurement'!I16) -> 5 | J53: =IF('4.Procurement'!J16="","",'4.Procurement'!J16) -> 8 | K53: =IF('4.Procurement'!K16="","",'4.Procurement'!K16) -> 0 | L53: =IF('4.Procurement'!L16="","",'4.Procurement'!L16) -> 0 | M53: =IF('4.Procurement'!M16="","",'4.Procurement'!M16) -> 0 | N53: =IF('4.Procurement'!N16="","",'4.Procurement'!N16) -> 0 | O53: =IF('4.Procurement'!O16="","",'4.Procurement'!O16) -> 0 | ... T53: =IF('4.Procurement'!T16="","",'4.Procurement'!T16) -> 0
A54: ='4.Procurement'!A16 -> Supplier selection to meet NPI / MLD deliverables | B54: ='4.Procurement'!B16 -> supplier selection per 12 NC for NPI | C54: ='4.Procurement'!C16 -> <= | D54: ='4.Procurement'!D16 -> 1 | E54: ='4.Procurement'!E16 -> % | F54: ='4.Procurement'!F16 -> Higher the better | G54: ='4.Procurement'!G16 -> Monthly | H54: =IF('4.Procurement'!H17="","",'4.Procurement'!H17) -> Actual | I54: =IF('4.Procurement'!I17="","",'4.Procurement'!I17) -> 5 | J54: =IF('4.Procurement'!J17="","",'4.Procurement'!J17) -> 7 | K54: =IF('4.Procurement'!K17="","",'4.Procurement'!K17) -> - | L54: =IF('4.Procurement'!L17="","",'4.Procurement'!L17) -> - | M54: =IF('4.Procurement'!M17="","",'4.Procurement'!M17) -> - | N54: =IF('4.Procurement'!N17="","",'4.Procurement'!N17) -> - | O54: =IF('4.Procurement'!O17="","",'4.Procurement'!O17) -> 0 | ... T54: =IF('4.Procurement'!T17="","",'4.Procurement'!T17)
A55: ='4.Procurement'!A18 -> CTB (12 weeks) | B55: ='4.Procurement'!B18 -> Clear to build material avaialbility | C55: ='4.Procurement'!C18 -> <= | D55: ='4.Procurement'!D18 -> 0.8 | E55: ='4.Procurement'!E18 -> % | F55: ='4.Procurement'!F18 -> Higher the better | G55: ='4.Procurement'!G18 -> Monthly | H55: =IF('4.Procurement'!H18="","",'4.Procurement'!H18) -> Target | I55: =IF('4.Procurement'!I18="","",'4.Procurement'!I18) -> 0.8 | J55: =IF('4.Procurement'!J18="","",'4.Procurement'!J18) -> 0.8 | K55: =IF('4.Procurement'!K18="","",'4.Procurement'!K18) -> 0.8 | L55: =IF('4.Procurement'!L18="","",'4.Procurement'!L18) -> 0.8 | M55: =IF('4.Procurement'!M18="","",'4.Procurement'!M18) -> 0.8 | N55: =IF('4.Procurement'!N18="","",'4.Procurement'!N18) -> 0.8 | O55: =IF('4.Procurement'!O18="","",'4.Procurement'!O18) -> 0.8 | ... T55: =IF('4.Procurement'!T18="","",'4.Procurement'!T18) -> 0.8
A56: ='4.Procurement'!A18 -> CTB (12 weeks) | B56: ='4.Procurement'!B18 -> Clear to build material avaialbility | C56: ='4.Procurement'!C18 -> <= | D56: ='4.Procurement'!D18 -> 0.8 | E56: ='4.Procurement'!E18 -> % | F56: ='4.Procurement'!F18 -> Higher the better | G56: ='4.Procurement'!G18 -> Monthly | H56: =IF('4.Procurement'!H19="","",'4.Procurement'!H19) -> Actual | I56: =IF('4.Procurement'!I19="","",'4.Procurement'!I19) -> 0.93 | J56: =IF('4.Procurement'!J19="","",'4.Procurement'!J19) -> 0.89 | K56: =IF('4.Procurement'!K19="","",'4.Procurement'!K19) -> 0.88 | L56: =IF('4.Procurement'!L19="","",'4.Procurement'!L19) -> 0.84 | M56: =IF('4.Procurement'!M19="","",'4.Procurement'!M19) -> 0.93 | N56: =IF('4.Procurement'!N19="","",'4.Procurement'!N19) -> 0.93 | O56: =IF('4.Procurement'!O19="","",'4.Procurement'!O19) -> 1 | ... T56: =IF('4.Procurement'!T19="","",'4.Procurement'!T19)
A57: =IF('4.Procurement'!A20= "","",'4.Procurement'!A20) | B57: =IF('4.Procurement'!B20= "","",'4.Procurement'!B20) | C57: =IF('4.Procurement'!C20= "","",'4.Procurement'!C20) | D57: =IF('4.Procurement'!D20= "","",'4.Procurement'!D20) | E57: =IF('4.Procurement'!E20= "","",'4.Procurement'!E20) | F57: =IF('4.Procurement'!F20= "","",'4.Procurement'!F20) | G57: =IF('4.Procurement'!G20= "","",'4.Procurement'!G20) | H57: =IF('4.Procurement'!H20="","",'4.Procurement'!H20) -> Target | I57: =IF('4.Procurement'!I20="","",'4.Procurement'!I20) -> 0 | J57: =IF('4.Procurement'!J20="","",'4.Procurement'!J20) -> 0 | K57: =IF('4.Procurement'!K20="","",'4.Procurement'!K20) -> 0 | L57: =IF('4.Procurement'!L20="","",'4.Procurement'!L20) -> 0 | M57: =IF('4.Procurement'!M20="","",'4.Procurement'!M20) -> 0 | N57: =IF('4.Procurement'!N20="","",'4.Procurement'!N20) -> 0 | O57: =IF('4.Procurement'!O20="","",'4.Procurement'!O20) -> 0 | ... T57: =IF('4.Procurement'!T20="","",'4.Procurement'!T20) -> 0
A58: =IF('4.Procurement'!A20= "","",'4.Procurement'!A20) | B58: =IF('4.Procurement'!B20= "","",'4.Procurement'!B20) | C58: =IF('4.Procurement'!C20= "","",'4.Procurement'!C20) | D58: =IF('4.Procurement'!D20= "","",'4.Procurement'!D20) | E58: =IF('4.Procurement'!E20= "","",'4.Procurement'!E20) | F58: =IF('4.Procurement'!F20= "","",'4.Procurement'!F20) | G58: =IF('4.Procurement'!G20= "","",'4.Procurement'!G20) | H58: =IF('4.Procurement'!H21="","",'4.Procurement'!H21) -> Actual | I58: =IF('4.Procurement'!I21="","",'4.Procurement'!I21) | J58: =IF('4.Procurement'!J21="","",'4.Procurement'!J21) | K58: =IF('4.Procurement'!K21="","",'4.Procurement'!K21) | L58: =IF('4.Procurement'!L21="","",'4.Procurement'!L21) | M58: =IF('4.Procurement'!M21="","",'4.Procurement'!M21) | N58: =IF('4.Procurement'!N21="","",'4.Procurement'!N21) | O58: =IF('4.Procurement'!O21="","",'4.Procurement'!O21) | ... T58: =IF('4.Procurement'!T21="","",'4.Procurement'!T21)
A60: R&D
A61: KPI Name | B61: KPI Definition | C61: Operators | D61: Target AOP 2026 | E61: Units | F61: Metric nature | G61: Frequency | H61: Target/ Actual | I61: Jan-2026 | J61: Feb-2026 | K61: Mar-2026 | L61: Apr-2026 | M61: May-2026 | N61: Jun-2026 | O61: Jul-2026 | P61: Aug-2026 | Q61: Sep-2026 | R61: Oct-2026 | S61: Nov-2026 | T61: Dec-2026
A62: ='5.R&D '!A14 -> NPI -Design Maturity Index (%) | B62: ='5.R&D '!B14 -> % of design Completion with zero major Quality Issues 1) Design Maturity 2) Integration Quality / Forecast - PLC till SVAL 3) Risk Technical - PLC till SVAL | C62: ='5.R&D '!C14 -> >= | D62: ='5.R&D '!D14 -> 100 | E62: ='5.R&D '!E14 -> % | F62: ='5.R&D '!F14 -> Higher the better | G62: ='5.R&D '!G14 -> Monthly | H62: =IF('5.R&D '!H14="","",'5.R&D '!H14) -> Target | I62: =IF('5.R&D '!I14="","",'5.R&D '!I14) -> 60 | J62: =IF('5.R&D '!J14="","",'5.R&D '!J14) -> 65 | K62: =IF('5.R&D '!K14="","",'5.R&D '!K14) -> 68 | L62: =IF('5.R&D '!L14="","",'5.R&D '!L14) -> 70 | M62: =IF('5.R&D '!M14="","",'5.R&D '!M14) -> 72 | N62: =IF('5.R&D '!N14="","",'5.R&D '!N14) -> 75 | O62: =IF('5.R&D '!O14="","",'5.R&D '!O14) -> 75 | ... T62: =IF('5.R&D '!T14="","",'5.R&D '!T14) -> 100
A63: ='5.R&D '!A14 -> NPI -Design Maturity Index (%) | B63: ='5.R&D '!B14 -> % of design Completion with zero major Quality Issues 1) Design Maturity 2) Integration Quality / Forecast - PLC till SVAL 3) Risk Technical - PLC till SVAL | C63: ='5.R&D '!C14 -> >= | D63: ='5.R&D '!D14 -> 100 | E63: ='5.R&D '!E14 -> % | F63: ='5.R&D '!F14 -> Higher the better | G63: ='5.R&D '!G14 -> Monthly | H63: =IF('5.R&D '!H15="","",'5.R&D '!H15) -> Actual | I63: =IF('5.R&D '!I15="","",'5.R&D '!I15) -> 54 | J63: =IF('5.R&D '!J15="","",'5.R&D '!J15) -> 58 | K63: =IF('5.R&D '!K15="","",'5.R&D '!K15) -> 64 | L63: =IF('5.R&D '!L15="","",'5.R&D '!L15) -> 68 | M63: =IF('5.R&D '!M15="","",'5.R&D '!M15) -> 68 | N63: =IF('5.R&D '!N15="","",'5.R&D '!N15) -> 73 | O63: =IF('5.R&D '!O15="","",'5.R&D '!O15) -> 75 | ... T63: =IF('5.R&D '!T15="","",'5.R&D '!T15)
A64: ='5.R&D '!A16 -> NPI Dhruv - Say-Do Ratio (%) | B64: ='5.R&D '!B16 -> % Monthly Planned Deliverables vs Actual (LOD Checkist - burndown) PLC-161 ; SVER- ; SVAL- ; RFD | C64: ='5.R&D '!C16 -> >= | D64: ='5.R&D '!D16 -> 90 | E64: ='5.R&D '!E16 -> % | F64: ='5.R&D '!F16 -> Higher the better | G64: ='5.R&D '!G16 -> Monthly | H64: =IF('5.R&D '!H16="","",'5.R&D '!H16) -> Target | I64: =IF('5.R&D '!I16="","",'5.R&D '!I16) -> 95 | J64: =IF('5.R&D '!J16="","",'5.R&D '!J16) -> 95 | K64: =IF('5.R&D '!K16="","",'5.R&D '!K16) -> 95 | L64: =IF('5.R&D '!L16="","",'5.R&D '!L16) -> 95 | M64: =IF('5.R&D '!M16="","",'5.R&D '!M16) -> 95 | N64: =IF('5.R&D '!N16="","",'5.R&D '!N16) -> 95 | O64: =IF('5.R&D '!O16="","",'5.R&D '!O16) -> 95 | ... T64: =IF('5.R&D '!T16="","",'5.R&D '!T16) -> 95
A65: ='5.R&D '!A16 -> NPI Dhruv - Say-Do Ratio (%) | B65: ='5.R&D '!B16 -> % Monthly Planned Deliverables vs Actual (LOD Checkist - burndown) PLC-161 ; SVER- ; SVAL- ; RFD | C65: ='5.R&D '!C16 -> >= | D65: ='5.R&D '!D16 -> 90 | E65: ='5.R&D '!E16 -> % | F65: ='5.R&D '!F16 -> Higher the better | G65: ='5.R&D '!G16 -> Monthly | H65: =IF('5.R&D '!H17="","",'5.R&D '!H17) -> Actual | I65: =IF('5.R&D '!I17="","",'5.R&D '!I17) -> 100 | J65: =IF('5.R&D '!J17="","",'5.R&D '!J17) -> 90 | K65: =IF('5.R&D '!K17="","",'5.R&D '!K17) -> 95 | L65: =IF('5.R&D '!L17="","",'5.R&D '!L17) -> 93 | M65: =IF('5.R&D '!M17="","",'5.R&D '!M17) -> 94 | N65: =IF('5.R&D '!N17="","",'5.R&D '!N17) -> 90 | O65: =IF('5.R&D '!O17="","",'5.R&D '!O17) -> 95 | ... T65: =IF('5.R&D '!T17="","",'5.R&D '!T17)
A66: ='5.R&D '!A18 -> NPI -Supplier Readiness Completion (%) | B66: ='5.R&D '!B18 -> % supplier deliverables completed and approved as per NPI plan up to PLC, SVAL milestones . ( 130 Part/Assy ) (Sec 5 - DFM - SRPQP)- PSW Signoff) till PLC ( Sec 6 - PSW part Mfg) - PSW Signoff Till Ser (Sec 7 - IQ-PSW signoff) - SVAL | C66: ='5.R&D '!C18 -> >= | D66: ='5.R&D '!D18 -> 95 | E66: ='5.R&D '!E18 -> % | F66: ='5.R&D '!F18 -> Higher the better | G66: ='5.R&D '!G18 -> Monthly | H66: =IF('5.R&D '!H18="","",'5.R&D '!H18) -> Target | I66: =IF('5.R&D '!I18="","",'5.R&D '!I18) -> 10 | J66: =IF('5.R&D '!J18="","",'5.R&D '!J18) -> 20 | K66: =IF('5.R&D '!K18="","",'5.R&D '!K18) -> 40 | L66: =IF('5.R&D '!L18="","",'5.R&D '!L18) -> 50 | M66: =IF('5.R&D '!M18="","",'5.R&D '!M18) -> 68 | N66: =IF('5.R&D '!N18="","",'5.R&D '!N18) -> 82 | O66: =IF('5.R&D '!O18="","",'5.R&D '!O18) -> 82 | ... T66: =IF('5.R&D '!T18="","",'5.R&D '!T18)
A67: ='5.R&D '!A18 -> NPI -Supplier Readiness Completion (%) | B67: ='5.R&D '!B18 -> % supplier deliverables completed and approved as per NPI plan up to PLC, SVAL milestones . ( 130 Part/Assy ) (Sec 5 - DFM - SRPQP)- PSW Signoff) till PLC ( Sec 6 - PSW part Mfg) - PSW Signoff Till Ser (Sec 7 - IQ-PSW signoff) - SVAL | C67: ='5.R&D '!C18 -> >= | D67: ='5.R&D '!D18 -> 95 | E67: ='5.R&D '!E18 -> % | F67: ='5.R&D '!F18 -> Higher the better | G67: ='5.R&D '!G18 -> Monthly | H67: =IF('5.R&D '!H19="","",'5.R&D '!H19) -> Actual | I67: =IF('5.R&D '!I19="","",'5.R&D '!I19) -> 5 | J67: =IF('5.R&D '!J19="","",'5.R&D '!J19) -> 6 | K67: =IF('5.R&D '!K19="","",'5.R&D '!K19) -> 7 | L67: =IF('5.R&D '!L19="","",'5.R&D '!L19) -> 18 | M67: =IF('5.R&D '!M19="","",'5.R&D '!M19) -> 33 | N67: =IF('5.R&D '!N19="","",'5.R&D '!N19) -> 64 | O67: =IF('5.R&D '!O19="","",'5.R&D '!O19) -> 64 | ... T67: =IF('5.R&D '!T19="","",'5.R&D '!T19)
A68: ='5.R&D '!A26 -> Critical & MLD Milestone Delivery On-Time (%) | B68: ='5.R&D '!B26 -> % of intermediate milestones achieved as per plan | C68: ='5.R&D '!C26 -> >= | D68: ='5.R&D '!D26 -> 80 | E68: ='5.R&D '!E26 -> % | F68: ='5.R&D '!F26 -> Higher the better | G68: ='5.R&D '!G26 -> Monthly | H68: =IF('5.R&D '!H26="","",'5.R&D '!H26) -> Target | I68: =IF('5.R&D '!I26="","",'5.R&D '!I26) -> 80 | J68: =IF('5.R&D '!J26="","",'5.R&D '!J26) -> 80 | K68: =IF('5.R&D '!K26="","",'5.R&D '!K26) -> 80 | L68: =IF('5.R&D '!L26="","",'5.R&D '!L26) -> 80 | M68: =IF('5.R&D '!M26="","",'5.R&D '!M26) -> 80 | N68: =IF('5.R&D '!N26="","",'5.R&D '!N26) -> 80 | O68: =IF('5.R&D '!O26="","",'5.R&D '!O26) -> 80 | ... T68: =IF('5.R&D '!T26="","",'5.R&D '!T26) -> 80
A69: ='5.R&D '!A26 -> Critical & MLD Milestone Delivery On-Time (%) | B69: ='5.R&D '!B26 -> % of intermediate milestones achieved as per plan | C69: ='5.R&D '!C26 -> >= | D69: ='5.R&D '!D26 -> 80 | E69: ='5.R&D '!E26 -> % | F69: ='5.R&D '!F26 -> Higher the better | G69: ='5.R&D '!G26 -> Monthly | H69: =IF('5.R&D '!H27="","",'5.R&D '!H27) -> Actual | I69: =IF('5.R&D '!I27="","",'5.R&D '!I27) -> 86 | J69: =IF('5.R&D '!J27="","",'5.R&D '!J27) -> 88 | K69: =IF('5.R&D '!K27="","",'5.R&D '!K27) -> 100 | L69: =IF('5.R&D '!L27="","",'5.R&D '!L27) -> 100 | M69: =IF('5.R&D '!M27="","",'5.R&D '!M27) -> 87.5 | N69: =IF('5.R&D '!N27="","",'5.R&D '!N27) -> 100 | O69: =IF('5.R&D '!O27="","",'5.R&D '!O27) -> 100 | ... T69: =IF('5.R&D '!T27="","",'5.R&D '!T27)
A71: Marketing
A72: KPI Name | B72: KPI Definition | C72: Operators | D72: Target AOP 2026 | E72: Units | F72: Metric nature | G72: Frequency | H72: Target/ Actual | I72: Jan-2026 | J72: Feb-2026 | K72: Mar-2026 | L72: Apr-2026 | M72: May-2026 | N72: Jun-2026 | O72: Jul-2026 | P72: Aug-2026 | Q72: Sep-2026 | R72: Oct-2026 | S72: Nov-2026 | T72: Dec-2026
A73: =#REF! -> #REF! | B73: =#REF! -> #REF! | C73: =#REF! -> #REF! | D73: =#REF! -> #REF! | E73: =#REF! -> #REF! | F73: =#REF! -> #REF! | G73: =#REF! -> #REF! | H73: =IF(#REF!="","",#REF!) -> #REF! | I73: =IF(#REF!="","",#REF!) -> #REF! | J73: =IF(#REF!="","",#REF!) -> #REF! | K73: =IF(#REF!="","",#REF!) -> #REF! | L73: =IF(#REF!="","",#REF!) -> #REF! | M73: =IF(#REF!="","",#REF!) -> #REF! | N73: =IF(#REF!="","",#REF!) -> #REF! | O73: =IF(#REF!="","",#REF!) -> #REF! | ... T73: =IF(#REF!="","",#REF!) -> #REF!
A74: =#REF! -> #REF! | B74: =#REF! -> #REF! | C74: =#REF! -> #REF! | D74: =#REF! -> #REF! | E74: =#REF! -> #REF! | F74: =#REF! -> #REF! | G74: =#REF! -> #REF! | H74: =IF(#REF!="","",#REF!) -> #REF! | I74: =IF(#REF!="","",#REF!) -> #REF! | J74: =IF(#REF!="","",#REF!) -> #REF! | K74: =IF(#REF!="","",#REF!) -> #REF! | L74: =IF(#REF!="","",#REF!) -> #REF! | M74: =IF(#REF!="","",#REF!) -> #REF! | N74: =IF(#REF!="","",#REF!) -> #REF! | O74: =IF(#REF!="","",#REF!) -> #REF! | ... T74: =IF(#REF!="","",#REF!) -> #REF!
A75: =#REF! -> #REF! | B75: =#REF! -> #REF! | C75: =#REF! -> #REF! | D75: =#REF! -> #REF! | E75: =#REF! -> #REF! | F75: =#REF! -> #REF! | G75: =#REF! -> #REF! | H75: =IF(#REF!="","",#REF!) -> #REF! | I75: =IF(#REF!="","",#REF!) -> #REF! | J75: =IF(#REF!="","",#REF!) -> #REF! | K75: =IF(#REF!="","",#REF!) -> #REF! | L75: =IF(#REF!="","",#REF!) -> #REF! | M75: =IF(#REF!="","",#REF!) -> #REF! | N75: =IF(#REF!="","",#REF!) -> #REF! | O75: =IF(#REF!="","",#REF!) -> #REF! | ... T75: =IF(#REF!="","",#REF!) -> #REF!
A76: =#REF! -> #REF! | B76: =#REF! -> #REF! | C76: =#REF! -> #REF! | D76: =#REF! -> #REF! | E76: =#REF! -> #REF! | F76: =#REF! -> #REF! | G76: =#REF! -> #REF! | H76: =IF(#REF!="","",#REF!) -> #REF! | I76: =IF(#REF!="","",#REF!) -> #REF! | J76: =IF(#REF!="","",#REF!) -> #REF! | K76: =IF(#REF!="","",#REF!) -> #REF! | L76: =IF(#REF!="","",#REF!) -> #REF! | M76: =IF(#REF!="","",#REF!) -> #REF! | N76: =IF(#REF!="","",#REF!) -> #REF! | O76: =IF(#REF!="","",#REF!) -> #REF! | ... T76: =IF(#REF!="","",#REF!) -> #REF!
A77: =#REF! -> #REF! | B77: =#REF! -> #REF! | C77: =#REF! -> #REF! | D77: =#REF! -> #REF! | E77: =#REF! -> #REF! | F77: =#REF! -> #REF! | G77: =#REF! -> #REF! | H77: =IF(#REF!="","",#REF!) -> #REF! | I77: =IF(#REF!="","",#REF!) -> #REF! | J77: =IF(#REF!="","",#REF!) -> #REF! | K77: =IF(#REF!="","",#REF!) -> #REF! | L77: =IF(#REF!="","",#REF!) -> #REF! | M77: =IF(#REF!="","",#REF!) -> #REF! | N77: =IF(#REF!="","",#REF!) -> #REF! | O77: =IF(#REF!="","",#REF!) -> #REF! | ... T77: =IF(#REF!="","",#REF!) -> #REF!
A78: =#REF! -> #REF! | B78: =#REF! -> #REF! | C78: =#REF! -> #REF! | D78: =#REF! -> #REF! | E78: =#REF! -> #REF! | F78: =#REF! -> #REF! | G78: =#REF! -> #REF! | H78: =IF(#REF!="","",#REF!) -> #REF! | I78: =IF(#REF!="","",#REF!) -> #REF! | J78: =IF(#REF!="","",#REF!) -> #REF! | K78: =IF(#REF!="","",#REF!) -> #REF! | L78: =IF(#REF!="","",#REF!) -> #REF! | M78: =IF(#REF!="","",#REF!) -> #REF! | N78: =IF(#REF!="","",#REF!) -> #REF! | O78: =IF(#REF!="","",#REF!) -> #REF! | ... T78: =IF(#REF!="","",#REF!) -> #REF!
A80: Customer Service
A81: KPI Name | B81: KPI Definition | C81: Operators | D81: Target AOP 2026 | E81: Units | F81: Metric nature | G81: Frequency | H81: Target/ Actual | I81: Jan-2026 | J81: Feb-2026 | K81: Mar-2026 | L81: Apr-2026 | M81: May-2026 | N81: Jun-2026 | O81: Jul-2026 | P81: Aug-2026 | Q81: Sep-2026 | R81: Oct-2026 | S81: Nov-2026 | T81: Dec-2026
A82: ='7.Customer Service'!A14 -> CP % | B82: ='7.Customer Service'!B14 -> Contract penetration Exc EOL/EOS System | C82: ='7.Customer Service'!C14 -> >= | D82: ='7.Customer Service'!D14 -> 54.9 | E82: ='7.Customer Service'!E14 -> % | F82: ='7.Customer Service'!F14 -> Higher the better | G82: ='7.Customer Service'!G14 -> Monthly | H82: =IF('7.Customer Service'!H14="","",'7.Customer Service'!H14) -> Target | I82: =IF('7.Customer Service'!I14="","",'7.Customer Service'!I14) -> 0.536 | J82: =IF('7.Customer Service'!J14="","",'7.Customer Service'!J14) -> 0.539 | K82: =IF('7.Customer Service'!K14="","",'7.Customer Service'!K14) -> 0.541 | L82: =IF('7.Customer Service'!L14="","",'7.Customer Service'!L14) -> 0.541 | M82: =IF('7.Customer Service'!M14="","",'7.Customer Service'!M14) -> 0.543 | N82: =IF('7.Customer Service'!N14="","",'7.Customer Service'!N14) -> 0.544 | O82: =IF('7.Customer Service'!O14="","",'7.Customer Service'!O14) -> 0.544 | ... T82: =IF('7.Customer Service'!T14="","",'7.Customer Service'!T14) -> 0.549
A83: ='7.Customer Service'!A14 -> CP % | B83: ='7.Customer Service'!B14 -> Contract penetration Exc EOL/EOS System | C83: ='7.Customer Service'!C14 -> >= | D83: ='7.Customer Service'!D14 -> 54.9 | E83: ='7.Customer Service'!E14 -> % | F83: ='7.Customer Service'!F14 -> Higher the better | G83: ='7.Customer Service'!G14 -> Monthly | H83: =IF('7.Customer Service'!H15="","",'7.Customer Service'!H15) -> Actual | I83: =IF('7.Customer Service'!I15="","",'7.Customer Service'!I15) -> 0.519 | J83: =IF('7.Customer Service'!J15="","",'7.Customer Service'!J15) -> 0.521 | K83: =IF('7.Customer Service'!K15="","",'7.Customer Service'!K15) -> 0.531 | L83: =IF('7.Customer Service'!L15="","",'7.Customer Service'!L15) -> 0.535 | M83: =IF('7.Customer Service'!M15="","",'7.Customer Service'!M15) -> 0.536 | N83: =IF('7.Customer Service'!N15="","",'7.Customer Service'!N15) -> 0.537 | O83: =IF('7.Customer Service'!O15="","",'7.Customer Service'!O15) -> 0.536 | ... T83: =IF('7.Customer Service'!T15="","",'7.Customer Service'!T15)
A84: ='7.Customer Service'!A16 -> POS Contract % | B84: ='7.Customer Service'!B16 -> Point of sale of service contract | C84: ='7.Customer Service'!C16 -> >= | D84: ='7.Customer Service'!D16 -> 40 | E84: ='7.Customer Service'!E16 -> % | F84: ='7.Customer Service'!F16 -> Higher the better | G84: ='7.Customer Service'!G16 -> Monthly | H84: =IF('7.Customer Service'!H16="","",'7.Customer Service'!H16) -> Target | I84: =IF('7.Customer Service'!I16="","",'7.Customer Service'!I16) -> 0.4 | J84: =IF('7.Customer Service'!J16="","",'7.Customer Service'!J16) -> 0.4 | K84: =IF('7.Customer Service'!K16="","",'7.Customer Service'!K16) -> 0.4 | L84: =IF('7.Customer Service'!L16="","",'7.Customer Service'!L16) -> 0.4 | M84: =IF('7.Customer Service'!M16="","",'7.Customer Service'!M16) -> 0.4 | N84: =IF('7.Customer Service'!N16="","",'7.Customer Service'!N16) -> 0.4 | O84: =IF('7.Customer Service'!O16="","",'7.Customer Service'!O16) -> 0.4 | ... T84: =IF('7.Customer Service'!T16="","",'7.Customer Service'!T16) -> 0.4
A85: ='7.Customer Service'!A16 -> POS Contract % | B85: ='7.Customer Service'!B16 -> Point of sale of service contract | C85: ='7.Customer Service'!C16 -> >= | D85: ='7.Customer Service'!D16 -> 40 | E85: ='7.Customer Service'!E16 -> % | F85: ='7.Customer Service'!F16 -> Higher the better | G85: ='7.Customer Service'!G16 -> Monthly | H85: =IF('7.Customer Service'!H17="","",'7.Customer Service'!H17) -> Actual | I85: =IF('7.Customer Service'!I17="","",'7.Customer Service'!I17) -> 0.217 | J85: =IF('7.Customer Service'!J17="","",'7.Customer Service'!J17) -> 0.286 | K85: =IF('7.Customer Service'!K17="","",'7.Customer Service'!K17) -> 0.31 | L85: =IF('7.Customer Service'!L17="","",'7.Customer Service'!L17) -> 0.31 | M85: =IF('7.Customer Service'!M17="","",'7.Customer Service'!M17) -> 0.32 | N85: =IF('7.Customer Service'!N17="","",'7.Customer Service'!N17) -> 0.42 | O85: =IF('7.Customer Service'!O17="","",'7.Customer Service'!O17) -> 0.414 | ... T85: =IF('7.Customer Service'!T17="","",'7.Customer Service'!T17)
A86: ='7.Customer Service'!A18 -> Contract price Improvement (M €) | B86: ='7.Customer Service'!B18 -> Contract target price realisation improvement | C86: ='7.Customer Service'!C18 -> >= | D86: ='7.Customer Service'!D18 -> 0.6 | E86: ='7.Customer Service'!E18 -> Mn | F86: ='7.Customer Service'!F18 -> Higher the better | G86: ='7.Customer Service'!G18 -> Monthly | H86: =IF('7.Customer Service'!H18="","",'7.Customer Service'!H18) -> Target | I86: =IF('7.Customer Service'!I18="","",'7.Customer Service'!I18) -> 0.02 | J86: =IF('7.Customer Service'!J18="","",'7.Customer Service'!J18) -> 0.05 | K86: =IF('7.Customer Service'!K18="","",'7.Customer Service'!K18) -> 0.08 | L86: =IF('7.Customer Service'!L18="","",'7.Customer Service'!L18) -> 0.11 | M86: =IF('7.Customer Service'!M18="","",'7.Customer Service'!M18) -> 0.17 | N86: =IF('7.Customer Service'!N18="","",'7.Customer Service'!N18) -> 0.23 | O86: =IF('7.Customer Service'!O18="","",'7.Customer Service'!O18) -> 0.29 | ... T86: =IF('7.Customer Service'!T18="","",'7.Customer Service'!T18) -> 0.61
A87: ='7.Customer Service'!A18 -> Contract price Improvement (M €) | B87: ='7.Customer Service'!B18 -> Contract target price realisation improvement | C87: ='7.Customer Service'!C18 -> >= | D87: ='7.Customer Service'!D18 -> 0.6 | E87: ='7.Customer Service'!E18 -> Mn | F87: ='7.Customer Service'!F18 -> Higher the better | G87: ='7.Customer Service'!G18 -> Monthly | H87: =IF('7.Customer Service'!H19="","",'7.Customer Service'!H19) -> Actual | I87: =IF('7.Customer Service'!I19="","",'7.Customer Service'!I19) -> 0.07 | J87: =IF('7.Customer Service'!J19="","",'7.Customer Service'!J19) -> 0.07 | K87: =IF('7.Customer Service'!K19="","",'7.Customer Service'!K19) -> 0.24 | L87: =IF('7.Customer Service'!L19="","",'7.Customer Service'!L19) -> 0.32 | M87: =IF('7.Customer Service'!M19="","",'7.Customer Service'!M19) -> 0.4 | N87: =IF('7.Customer Service'!N19="","",'7.Customer Service'!N19) -> 0.53 | O87: =IF('7.Customer Service'!O19="","",'7.Customer Service'!O19) -> 0.53 | ... T87: =IF('7.Customer Service'!T19="","",'7.Customer Service'!T19)
A88: ='7.Customer Service'!A20 -> Service Productivity | B88: ='7.Customer Service'!B20 -> Service Cost Savings | C88: ='7.Customer Service'!C20 -> <= | D88: ='7.Customer Service'!D20 -> 1.3 | E88: ='7.Customer Service'!E20 -> Mn | F88: ='7.Customer Service'!F20 -> Higher the better | G88: ='7.Customer Service'!G20 -> Monthly | H88: =IF('7.Customer Service'!H20="","",'7.Customer Service'!H20) -> Target | I88: =IF('7.Customer Service'!I20="","",'7.Customer Service'!I20) -> 0 | J88: =IF('7.Customer Service'!J20="","",'7.Customer Service'!J20) -> 0.03 | K88: =IF('7.Customer Service'!K20="","",'7.Customer Service'!K20) -> 0.06 | L88: =IF('7.Customer Service'!L20="","",'7.Customer Service'!L20) -> 0.13 | M88: =IF('7.Customer Service'!M20="","",'7.Customer Service'!M20) -> 0.2 | N88: =IF('7.Customer Service'!N20="","",'7.Customer Service'!N20) -> 0.27 | O88: =IF('7.Customer Service'!O20="","",'7.Customer Service'!O20) -> 0.42 | ... T88: =IF('7.Customer Service'!T20="","",'7.Customer Service'!T20) -> 1.3
A89: ='7.Customer Service'!A20 -> Service Productivity | B89: ='7.Customer Service'!B20 -> Service Cost Savings | C89: ='7.Customer Service'!C20 -> <= | D89: ='7.Customer Service'!D20 -> 1.3 | E89: ='7.Customer Service'!E20 -> Mn | F89: ='7.Customer Service'!F20 -> Higher the better | G89: ='7.Customer Service'!G20 -> Monthly | H89: =IF('7.Customer Service'!H21="","",'7.Customer Service'!H21) -> Actual | I89: =IF('7.Customer Service'!I21="","",'7.Customer Service'!I21) -> 0.01 | J89: =IF('7.Customer Service'!J21="","",'7.Customer Service'!J21) -> 0.03 | K89: =IF('7.Customer Service'!K21="","",'7.Customer Service'!K21) -> 0.085 | L89: =IF('7.Customer Service'!L21="","",'7.Customer Service'!L21) -> 0.16 | M89: =IF('7.Customer Service'!M21="","",'7.Customer Service'!M21) -> 0.23 | N89: =IF('7.Customer Service'!N21="","",'7.Customer Service'!N21) -> 0.3 | O89: =IF('7.Customer Service'!O21="","",'7.Customer Service'!O21) -> 0.44 | ... T89: =IF('7.Customer Service'!T21="","",'7.Customer Service'!T21)
A90: ='7.Customer Service'!A22 -> Remote resolution | B90: ='7.Customer Service'!B22 -> Remote resolution cases % | C90: ='7.Customer Service'!C22 -> >= | D90: ='7.Customer Service'!D22 -> 0.236 | E90: ='7.Customer Service'!E22 -> % | F90: ='7.Customer Service'!F22 -> Higher the better | G90: ='7.Customer Service'!G22 -> Monthly | H90: =IF('7.Customer Service'!H22="","",'7.Customer Service'!H22) -> Target | I90: =IF('7.Customer Service'!I22="","",'7.Customer Service'!I22) -> 0.22053895 | J90: =IF('7.Customer Service'!J22="","",'7.Customer Service'!J22) -> 0.22198023 | K90: =IF('7.Customer Service'!K22="","",'7.Customer Service'!K22) -> 0.22342151 | L90: =IF('7.Customer Service'!L22="","",'7.Customer Service'!L22) -> 0.22486279 | M90: =IF('7.Customer Service'!M22="","",'7.Customer Service'!M22) -> 0.22630407 | N90: =IF('7.Customer Service'!N22="","",'7.Customer Service'!N22) -> 0.22774535 | O90: =IF('7.Customer Service'!O22="","",'7.Customer Service'!O22) -> 0.22918662 | ... T90: =IF('7.Customer Service'!T22="","",'7.Customer Service'!T22) -> 0.23639301
A91: ='7.Customer Service'!A22 -> Remote resolution | B91: ='7.Customer Service'!B22 -> Remote resolution cases % | C91: ='7.Customer Service'!C22 -> >= | D91: ='7.Customer Service'!D22 -> 0.236 | E91: ='7.Customer Service'!E22 -> % | F91: ='7.Customer Service'!F22 -> Higher the better | G91: ='7.Customer Service'!G22 -> Monthly | H91: =IF('7.Customer Service'!H23="","",'7.Customer Service'!H23) -> Actual | I91: =IF('7.Customer Service'!I23="","",'7.Customer Service'!I23) -> 0.215 | J91: =IF('7.Customer Service'!J23="","",'7.Customer Service'!J23) -> 0.213 | K91: =IF('7.Customer Service'!K23="","",'7.Customer Service'!K23) -> 0.212 | L91: =IF('7.Customer Service'!L23="","",'7.Customer Service'!L23) -> 0.221 | M91: =IF('7.Customer Service'!M23="","",'7.Customer Service'!M23) -> 0.227 | N91: =IF('7.Customer Service'!N23="","",'7.Customer Service'!N23) -> 0.2204 | O91: =IF('7.Customer Service'!O23="","",'7.Customer Service'!O23) -> 0.24 | ... T91: =IF('7.Customer Service'!T23="","",'7.Customer Service'!T23)
A92: ='7.Customer Service'!A24 -> OPF% | B92: ='7.Customer Service'!B24 -> One part Fix % | C92: ='7.Customer Service'!C24 -> >= | D92: ='7.Customer Service'!D24 -> 0.816 | E92: ='7.Customer Service'!E24 -> % | F92: ='7.Customer Service'!F24 -> Higher the better | G92: ='7.Customer Service'!G24 -> Monthly | H92: =IF('7.Customer Service'!H24="","",'7.Customer Service'!H24) -> Target | I92: =IF('7.Customer Service'!I24="","",'7.Customer Service'!I24) -> 0.804 | J92: =IF('7.Customer Service'!J24="","",'7.Customer Service'!J24) -> 0.805 | K92: =IF('7.Customer Service'!K24="","",'7.Customer Service'!K24) -> 0.806 | L92: =IF('7.Customer Service'!L24="","",'7.Customer Service'!L24) -> 0.807 | M92: =IF('7.Customer Service'!M24="","",'7.Customer Service'!M24) -> 0.808 | N92: =IF('7.Customer Service'!N24="","",'7.Customer Service'!N24) -> 0.809 | O92: =IF('7.Customer Service'!O24="","",'7.Customer Service'!O24) -> 0.81 | ... T92: =IF('7.Customer Service'!T24="","",'7.Customer Service'!T24) -> 0.816
A93: ='7.Customer Service'!A24 -> OPF% | B93: ='7.Customer Service'!B24 -> One part Fix % | C93: ='7.Customer Service'!C24 -> >= | D93: ='7.Customer Service'!D24 -> 0.816 | E93: ='7.Customer Service'!E24 -> % | F93: ='7.Customer Service'!F24 -> Higher the better | G93: ='7.Customer Service'!G24 -> Monthly | H93: =IF('7.Customer Service'!H25="","",'7.Customer Service'!H25) -> Actual | I93: =IF('7.Customer Service'!I25="","",'7.Customer Service'!I25) -> 0.8188 | J93: =IF('7.Customer Service'!J25="","",'7.Customer Service'!J25) -> 0.814 | K93: =IF('7.Customer Service'!K25="","",'7.Customer Service'!K25) -> 0.8 | L93: =IF('7.Customer Service'!L25="","",'7.Customer Service'!L25) -> 0.802 | M93: =IF('7.Customer Service'!M25="","",'7.Customer Service'!M25) -> 0.804 | N93: =IF('7.Customer Service'!N25="","",'7.Customer Service'!N25) -> 0.8056 | O93: =IF('7.Customer Service'!O25="","",'7.Customer Service'!O25) -> 0.81 | ... T93: =IF('7.Customer Service'!T25="","",'7.Customer Service'!T25)
A94: ='7.Customer Service'!A26 -> First Vist Fix (Parts) | B94: ='7.Customer Service'!B26 -> Customer Satisfaction -on resolution | C94: ='7.Customer Service'!C26 -> <= | D94: ='7.Customer Service'!D26 -> 0.709 | E94: ='7.Customer Service'!E26 -> % | F94: ='7.Customer Service'!F26 -> Higher the better | G94: ='7.Customer Service'!G26 -> Monthly | H94: =IF('7.Customer Service'!H26="","",'7.Customer Service'!H26) -> Target | I94: =IF('7.Customer Service'!I26="","",'7.Customer Service'!I26) -> 0.7 | J94: =IF('7.Customer Service'!J26="","",'7.Customer Service'!J26) -> 0.7 | K94: =IF('7.Customer Service'!K26="","",'7.Customer Service'!K26) -> 0.7 | L94: =IF('7.Customer Service'!L26="","",'7.Customer Service'!L26) -> 0.7 | M94: =IF('7.Customer Service'!M26="","",'7.Customer Service'!M26) -> 0.7 | N94: =IF('7.Customer Service'!N26="","",'7.Customer Service'!N26) -> 0.7 | O94: =IF('7.Customer Service'!O26="","",'7.Customer Service'!O26) -> 0.7 | ... T94: =IF('7.Customer Service'!T26="","",'7.Customer Service'!T26) -> 0.7
A95: ='7.Customer Service'!A26 -> First Vist Fix (Parts) | B95: ='7.Customer Service'!B26 -> Customer Satisfaction -on resolution | C95: ='7.Customer Service'!C26 -> <= | D95: ='7.Customer Service'!D26 -> 0.709 | E95: ='7.Customer Service'!E26 -> % | F95: ='7.Customer Service'!F26 -> Higher the better | G95: ='7.Customer Service'!G26 -> Monthly | H95: =IF('7.Customer Service'!H27="","",'7.Customer Service'!H27) -> Actual | I95: =IF('7.Customer Service'!I27="","",'7.Customer Service'!I27) -> 0.695 | J95: =IF('7.Customer Service'!J27="","",'7.Customer Service'!J27) -> 0.648 | K95: =IF('7.Customer Service'!K27="","",'7.Customer Service'!K27) -> 0.681 | L95: =IF('7.Customer Service'!L27="","",'7.Customer Service'!L27) -> 0.695 | M95: =IF('7.Customer Service'!M27="","",'7.Customer Service'!M27) -> 0.7 | N95: =IF('7.Customer Service'!N27="","",'7.Customer Service'!N27) -> 0.7 | O95: =IF('7.Customer Service'!O27="","",'7.Customer Service'!O27) -> 0.697 | ... T95: =IF('7.Customer Service'!T27="","",'7.Customer Service'!T27)
A97: Commercial Excellence
A98: KPI Name | B98: KPI Definition | C98: Operators | D98: Target AOP 2026 | E98: Units | F98: Metric nature | G98: Frequency | H98: Target/ Actual | I98: Jan-2026 | J98: Feb-2026 | K98: Mar-2026 | L98: Apr-2026 | M98: May-2026 | N98: Jun-2026 | O98: Jul-2026 | P98: Aug-2026 | Q98: Sep-2026 | R98: Oct-2026 | S98: Nov-2026 | T98: Dec-2026
A99: ='8.Commercial Excellence'!A14 -> Funnel with 70%++ probabilty of winning | B99: ='8.Commercial Excellence'!B14 -> BC with FC Flag + Commit+ Order Booked | C99: ='8.Commercial Excellence'!C14 -> >= | D99: ='8.Commercial Excellence'!D14 -> 145 | E99: ='8.Commercial Excellence'!E14 -> % | F99: ='8.Commercial Excellence'!F14 -> Higher the better | G99: ='8.Commercial Excellence'!G14 -> Monthly | H99: =IF('8.Commercial Excellence'!H14="","",'8.Commercial Excellence'!H14) -> Target | I99: =IF('8.Commercial Excellence'!I14="","",'8.Commercial Excellence'!I14) -> 6.9 | J99: =IF('8.Commercial Excellence'!J14="","",'8.Commercial Excellence'!J14) -> 8.5 | K99: =IF('8.Commercial Excellence'!K14="","",'8.Commercial Excellence'!K14) -> 12.6 | L99: =IF('8.Commercial Excellence'!L14="","",'8.Commercial Excellence'!L14) -> 9.5 | M99: =IF('8.Commercial Excellence'!M14="","",'8.Commercial Excellence'!M14) -> 10.6 | N99: =IF('8.Commercial Excellence'!N14="","",'8.Commercial Excellence'!N14) -> 15.6 | O99: =IF('8.Commercial Excellence'!O14="","",'8.Commercial Excellence'!O14) -> 8.9 | ... T99: =IF('8.Commercial Excellence'!T14="","",'8.Commercial Excellence'!T14) -> 16.9
A100: ='8.Commercial Excellence'!A14 -> Funnel with 70%++ probabilty of winning | B100: ='8.Commercial Excellence'!B14 -> BC with FC Flag + Commit+ Order Booked | C100: ='8.Commercial Excellence'!C14 -> >= | D100: ='8.Commercial Excellence'!D14 -> 145 | E100: ='8.Commercial Excellence'!E14 -> % | F100: ='8.Commercial Excellence'!F14 -> Higher the better | G100: ='8.Commercial Excellence'!G14 -> Monthly | H100: =IF('8.Commercial Excellence'!H15="","",'8.Commercial Excellence'!H15) -> Actual | I100: =IF('8.Commercial Excellence'!I15="","",'8.Commercial Excellence'!I15) -> 7.6 | J100: =IF('8.Commercial Excellence'!J15="","",'8.Commercial Excellence'!J15) -> 8.9 | K100: =IF('8.Commercial Excellence'!K15="","",'8.Commercial Excellence'!K15) -> 18.8 | L100: =IF('8.Commercial Excellence'!L15="","",'8.Commercial Excellence'!L15) -> 7.5 | M100: =IF('8.Commercial Excellence'!M15="","",'8.Commercial Excellence'!M15) | N100: =IF('8.Commercial Excellence'!N15="","",'8.Commercial Excellence'!N15) | O100: =IF('8.Commercial Excellence'!O15="","",'8.Commercial Excellence'!O15) | ... T100: =IF('8.Commercial Excellence'!T15="","",'8.Commercial Excellence'!T15)
A101: ='8.Commercial Excellence'!A16 -> Demo Utilization | B101: ='8.Commercial Excellence'!B16 -> How much of our Demo inventory is being used actively. | C101: ='8.Commercial Excellence'!C16 -> >= | D101: ='8.Commercial Excellence'!D16 -> 1 | E101: ='8.Commercial Excellence'!E16 -> % | F101: ='8.Commercial Excellence'!F16 -> Higher the better | G101: ='8.Commercial Excellence'!G16 -> Monthly | H101: =IF('8.Commercial Excellence'!H16="","",'8.Commercial Excellence'!H16) -> Target | I101: =IF('8.Commercial Excellence'!I16="","",'8.Commercial Excellence'!I16) | J101: =IF('8.Commercial Excellence'!J16="","",'8.Commercial Excellence'!J16) | K101: =IF('8.Commercial Excellence'!K16="","",'8.Commercial Excellence'!K16) | L101: =IF('8.Commercial Excellence'!L16="","",'8.Commercial Excellence'!L16) | M101: =IF('8.Commercial Excellence'!M16="","",'8.Commercial Excellence'!M16) | N101: =IF('8.Commercial Excellence'!N16="","",'8.Commercial Excellence'!N16) | O101: =IF('8.Commercial Excellence'!O16="","",'8.Commercial Excellence'!O16) | ... T101: =IF('8.Commercial Excellence'!T16="","",'8.Commercial Excellence'!T16)
A102: ='8.Commercial Excellence'!A16 -> Demo Utilization | B102: ='8.Commercial Excellence'!B16 -> How much of our Demo inventory is being used actively. | C102: ='8.Commercial Excellence'!C16 -> >= | D102: ='8.Commercial Excellence'!D16 -> 1 | E102: ='8.Commercial Excellence'!E16 -> % | F102: ='8.Commercial Excellence'!F16 -> Higher the better | G102: ='8.Commercial Excellence'!G16 -> Monthly | H102: =IF('8.Commercial Excellence'!H17="","",'8.Commercial Excellence'!H17) -> Actual | I102: =IF('8.Commercial Excellence'!I17="","",'8.Commercial Excellence'!I17) | J102: =IF('8.Commercial Excellence'!J17="","",'8.Commercial Excellence'!J17) | K102: =IF('8.Commercial Excellence'!K17="","",'8.Commercial Excellence'!K17) | L102: =IF('8.Commercial Excellence'!L17="","",'8.Commercial Excellence'!L17) | M102: =IF('8.Commercial Excellence'!M17="","",'8.Commercial Excellence'!M17) | N102: =IF('8.Commercial Excellence'!N17="","",'8.Commercial Excellence'!N17) | O102: =IF('8.Commercial Excellence'!O17="","",'8.Commercial Excellence'!O17) | ... T102: =IF('8.Commercial Excellence'!T17="","",'8.Commercial Excellence'!T17)
A103: ='8.Commercial Excellence'!A18 -> Demo Refurb | B103: ='8.Commercial Excellence'!B18 -> % Of Demo Units Going through Refurb Process per Quarter | C103: ='8.Commercial Excellence'!C18 -> >= | D103: ='8.Commercial Excellence'!D18 -> 1 | E103: ='8.Commercial Excellence'!E18 -> % | F103: ='8.Commercial Excellence'!F18 -> Higher the better | G103: ='8.Commercial Excellence'!G18 -> Quarterly | H103: =IF('8.Commercial Excellence'!H18="","",'8.Commercial Excellence'!H18) -> Target | I103: =IF('8.Commercial Excellence'!I18="","",'8.Commercial Excellence'!I18) | J103: =IF('8.Commercial Excellence'!J18="","",'8.Commercial Excellence'!J18) | K103: =IF('8.Commercial Excellence'!K18="","",'8.Commercial Excellence'!K18) | L103: =IF('8.Commercial Excellence'!L18="","",'8.Commercial Excellence'!L18) | M103: =IF('8.Commercial Excellence'!M18="","",'8.Commercial Excellence'!M18) | N103: =IF('8.Commercial Excellence'!N18="","",'8.Commercial Excellence'!N18) | O103: =IF('8.Commercial Excellence'!O18="","",'8.Commercial Excellence'!O18) | ... T103: =IF('8.Commercial Excellence'!T18="","",'8.Commercial Excellence'!T18)
A104: ='8.Commercial Excellence'!A18 -> Demo Refurb | B104: ='8.Commercial Excellence'!B18 -> % Of Demo Units Going through Refurb Process per Quarter | C104: ='8.Commercial Excellence'!C18 -> >= | D104: ='8.Commercial Excellence'!D18 -> 1 | E104: ='8.Commercial Excellence'!E18 -> % | F104: ='8.Commercial Excellence'!F18 -> Higher the better | G104: ='8.Commercial Excellence'!G18 -> Quarterly | H104: =IF('8.Commercial Excellence'!H19="","",'8.Commercial Excellence'!H19) -> Actual | I104: =IF('8.Commercial Excellence'!I19="","",'8.Commercial Excellence'!I19) | J104: =IF('8.Commercial Excellence'!J19="","",'8.Commercial Excellence'!J19) | K104: =IF('8.Commercial Excellence'!K19="","",'8.Commercial Excellence'!K19) | L104: =IF('8.Commercial Excellence'!L19="","",'8.Commercial Excellence'!L19) | M104: =IF('8.Commercial Excellence'!M19="","",'8.Commercial Excellence'!M19) | N104: =IF('8.Commercial Excellence'!N19="","",'8.Commercial Excellence'!N19) | O104: =IF('8.Commercial Excellence'!O19="","",'8.Commercial Excellence'!O19) | ... T104: =IF('8.Commercial Excellence'!T19="","",'8.Commercial Excellence'!T19)
A105: ='8.Commercial Excellence'!A20 -> Demo Win rate | B105: ='8.Commercial Excellence'!B20 -> ITM Demo Winrate | C105: ='8.Commercial Excellence'!C20 -> >= | D105: ='8.Commercial Excellence'!D20 -> 0.6 | E105: ='8.Commercial Excellence'!E20 -> % | F105: ='8.Commercial Excellence'!F20 -> Higher the better | G105: ='8.Commercial Excellence'!G20 -> Monthly | H105: =IF('8.Commercial Excellence'!H20="","",'8.Commercial Excellence'!H20) -> Target | I105: =IF('8.Commercial Excellence'!I20="","",'8.Commercial Excellence'!I20) -> 0.6 | J105: =IF('8.Commercial Excellence'!J20="","",'8.Commercial Excellence'!J20) -> 0.6 | K105: =IF('8.Commercial Excellence'!K20="","",'8.Commercial Excellence'!K20) -> 0.6 | L105: =IF('8.Commercial Excellence'!L20="","",'8.Commercial Excellence'!L20) | M105: =IF('8.Commercial Excellence'!M20="","",'8.Commercial Excellence'!M20) | N105: =IF('8.Commercial Excellence'!N20="","",'8.Commercial Excellence'!N20) | O105: =IF('8.Commercial Excellence'!O20="","",'8.Commercial Excellence'!O20) | ... T105: =IF('8.Commercial Excellence'!T20="","",'8.Commercial Excellence'!T20)
A106: ='8.Commercial Excellence'!A20 -> Demo Win rate | B106: ='8.Commercial Excellence'!B20 -> ITM Demo Winrate | C106: ='8.Commercial Excellence'!C20 -> >= | D106: ='8.Commercial Excellence'!D20 -> 0.6 | E106: ='8.Commercial Excellence'!E20 -> % | F106: ='8.Commercial Excellence'!F20 -> Higher the better | G106: ='8.Commercial Excellence'!G20 -> Monthly | H106: =IF('8.Commercial Excellence'!H21="","",'8.Commercial Excellence'!H21) -> Actual | I106: =IF('8.Commercial Excellence'!I21="","",'8.Commercial Excellence'!I21) -> 0.6 | J106: =IF('8.Commercial Excellence'!J21="","",'8.Commercial Excellence'!J21) -> 0.56 | K106: =IF('8.Commercial Excellence'!K21="","",'8.Commercial Excellence'!K21) -> 0.58 | L106: =IF('8.Commercial Excellence'!L21="","",'8.Commercial Excellence'!L21) | M106: =IF('8.Commercial Excellence'!M21="","",'8.Commercial Excellence'!M21) | N106: =IF('8.Commercial Excellence'!N21="","",'8.Commercial Excellence'!N21) | O106: =IF('8.Commercial Excellence'!O21="","",'8.Commercial Excellence'!O21) | ... T106: =IF('8.Commercial Excellence'!T21="","",'8.Commercial Excellence'!T21)
A107: ='8.Commercial Excellence'!A22 -> # of Demos | B107: ='8.Commercial Excellence'!B22 -> Number of Demos per Month | C107: ='8.Commercial Excellence'!C22 -> >= | D107: ='8.Commercial Excellence'!D22 -> 596 | E107: ='8.Commercial Excellence'!E22 -> No. | F107: ='8.Commercial Excellence'!F22 -> Higher the better | G107: ='8.Commercial Excellence'!G22 -> Monthly | H107: =IF('8.Commercial Excellence'!H22="","",'8.Commercial Excellence'!H22) -> Target | I107: =IF('8.Commercial Excellence'!I22="","",'8.Commercial Excellence'!I22) -> 28 | J107: =IF('8.Commercial Excellence'!J22="","",'8.Commercial Excellence'!J22) -> 35 | K107: =IF('8.Commercial Excellence'!K22="","",'8.Commercial Excellence'!K22) -> 52 | L107: =IF('8.Commercial Excellence'!L22="","",'8.Commercial Excellence'!L22) -> 39 | M107: =IF('8.Commercial Excellence'!M22="","",'8.Commercial Excellence'!M22) -> 44 | N107: =IF('8.Commercial Excellence'!N22="","",'8.Commercial Excellence'!N22) -> 64 | O107: =IF('8.Commercial Excellence'!O22="","",'8.Commercial Excellence'!O22) -> 37 | ... T107: =IF('8.Commercial Excellence'!T22="","",'8.Commercial Excellence'!T22) -> 69
A108: ='8.Commercial Excellence'!A22 -> # of Demos | B108: ='8.Commercial Excellence'!B22 -> Number of Demos per Month | C108: ='8.Commercial Excellence'!C22 -> >= | D108: ='8.Commercial Excellence'!D22 -> 596 | E108: ='8.Commercial Excellence'!E22 -> No. | F108: ='8.Commercial Excellence'!F22 -> Higher the better | G108: ='8.Commercial Excellence'!G22 -> Monthly | H108: =IF('8.Commercial Excellence'!H23="","",'8.Commercial Excellence'!H23) -> Actual | I108: =IF('8.Commercial Excellence'!I23="","",'8.Commercial Excellence'!I23) -> 20 | J108: =IF('8.Commercial Excellence'!J23="","",'8.Commercial Excellence'!J23) -> 25 | K108: =IF('8.Commercial Excellence'!K23="","",'8.Commercial Excellence'!K23) -> 43 | L108: =IF('8.Commercial Excellence'!L23="","",'8.Commercial Excellence'!L23) | M108: =IF('8.Commercial Excellence'!M23="","",'8.Commercial Excellence'!M23) | N108: =IF('8.Commercial Excellence'!N23="","",'8.Commercial Excellence'!N23) | O108: =IF('8.Commercial Excellence'!O23="","",'8.Commercial Excellence'!O23) | ... T108: =IF('8.Commercial Excellence'!T23="","",'8.Commercial Excellence'!T23)
A110: NAR
...

Sheet 1.Quality
A1: Month | B1: 46023 | C1: MT Owner: | D1: Neena S | E1: MT Delegate: | W1: Actual green | X1: =IF(I21<>"",IF($F20="Higher the better",IF(I21>=I20,I21,NA()),IF(I21<=I20,I21,NA())),NA()) -> #N/A | Y1: =IF(J21<>"",IF($F20="Higher the better",IF(J21>=J20,J21,NA()),IF(J21<=J20,J21,NA())),NA()) -> #N/A | Z1: =IF(K21<>"",IF($F20="Higher the better",IF(K21>=K20,K21,NA()),IF(K21<=K20,K21,NA())),NA()) -> #N/A | AA1: =IF(L21<>"",IF($F20="Higher the better",IF(L21>=L20,L21,NA()),IF(L21<=L20,L21,NA())),NA()) -> #N/A | AB1: =IF(M21<>"",IF($F20="Higher the better",IF(M21>=M20,M21,NA()),IF(M21<=M20,M21,NA())),NA()) -> #N/A | AC1: =IF(N21<>"",IF($F20="Higher the better",IF(N21>=N20,N21,NA()),IF(N21<=N20,N21,NA())),NA()) -> #N/A | AD1: =IF(O21<>"",IF($F20="Higher the better",IF(O21>=O20,O21,NA()),IF(O21<=O20,O21,NA())),NA()) -> #N/A | AE1: =IF(P21<>"",IF($F20="Higher the better",IF(P21>=P20,P21,NA()),IF(P21<=P20,P21,NA())),NA()) -> #N/A | ... AI1: =IF(T21<>"",IF($F20="Higher the better",IF(T21>=T20,T21,NA()),IF(T21<=T20,T21,NA())),NA()) -> #N/A
W2: Actual red | X2: =IF(I21<>"",IF($F20="Higher the better",IF(I21<I20,I21,NA()),IF(I21>I20,I21,NA())),NA()) -> 0.22 | Y2: =IF(J21<>"",IF($F20="Higher the better",IF(J21<J20,J21,NA()),IF(J21>J20,J21,NA())),NA()) -> 0.4 | Z2: =IF(K21<>"",IF($F20="Higher the better",IF(K21<K20,K21,NA()),IF(K21>K20,K21,NA())),NA()) -> 0.22 | AA2: =IF(L21<>"",IF($F20="Higher the better",IF(L21<L20,L21,NA()),IF(L21>L20,L21,NA())),NA()) -> 0.4 | AB2: =IF(M21<>"",IF($F20="Higher the better",IF(M21<M20,M21,NA()),IF(M21>M20,M21,NA())),NA()) -> 0.875 | AC2: =IF(N21<>"",IF($F20="Higher the better",IF(N21<N20,N21,NA()),IF(N21>N20,N21,NA())),NA()) -> 0.3 | AD2: =IF(O21<>"",IF($F20="Higher the better",IF(O21<O20,O21,NA()),IF(O21>O20,O21,NA())),NA()) -> 0.4 | AE2: =IF(P21<>"",IF($F20="Higher the better",IF(P21<P20,P21,NA()),IF(P21>P20,P21,NA())),NA()) -> 0.83 | ... AI2: =IF(T21<>"",IF($F20="Higher the better",IF(T21<T20,T21,NA()),IF(T21>T20,T21,NA())),NA()) -> #N/A
A3: Patient Safety & Quality DMB | W3: Actual green | X3: =IF(I23<>"",IF($F22="Higher the better",IF(I23>=I22,I23,NA()),IF(I23<=I22,I23,NA())),NA()) -> 6 | Y3: =IF(J23<>"",IF($F22="Higher the better",IF(J23>=J22,J23,NA()),IF(J23<=J22,J23,NA())),NA()) -> 5 | Z3: =IF(K23<>"",IF($F22="Higher the better",IF(K23>=K22,K23,NA()),IF(K23<=K22,K23,NA())),NA()) -> 5 | AA3: =IF(L23<>"",IF($F22="Higher the better",IF(L23>=L22,L23,NA()),IF(L23<=L22,L23,NA())),NA()) -> 4 | AB3: =IF(M23<>"",IF($F22="Higher the better",IF(M23>=M22,M23,NA()),IF(M23<=M22,M23,NA())),NA()) -> 4 | AC3: =IF(N23<>"",IF($F22="Higher the better",IF(N23>=N22,N23,NA()),IF(N23<=N22,N23,NA())),NA()) -> 4 | AD3: =IF(O23<>"",IF($F22="Higher the better",IF(O23>=O22,O23,NA()),IF(O23<=O22,O23,NA())),NA()) -> 4 | AE3: =IF(P23<>"",IF($F22="Higher the better",IF(P23>=P22,P23,NA()),IF(P23<=P22,P23,NA())),NA()) -> 2 | ... AI3: =IF(T23<>"",IF($F22="Higher the better",IF(T23>=T22,T23,NA()),IF(T23<=T22,T23,NA())),NA()) -> #N/A
A4: Mandatory Outcome KPI's (1-3) | W4: Actual red | X4: {=IF(I23<>"",IF($F22="Higher the better",IF(I23<X5I22,I23,NA()),IF(I23>I22,I23,NA())),NA())} -> #N/A | Y4: =IF(J23<>"",IF($F22="Higher the better",IF(J23<J22,J23,NA()),IF(J23>J22,J23,NA())),NA()) -> #N/A | Z4: =IF(K23<>"",IF($F22="Higher the better",IF(K23<K22,K23,NA()),IF(K23>K22,K23,NA())),NA()) -> #N/A | AA4: =IF(L23<>"",IF($F22="Higher the better",IF(L23<L22,L23,NA()),IF(L23>L22,L23,NA())),NA()) -> #N/A | AB4: =IF(M23<>"",IF($F22="Higher the better",IF(M23<M22,M23,NA()),IF(M23>M22,M23,NA())),NA()) -> #N/A | AC4: =IF(N23<>"",IF($F22="Higher the better",IF(N23<N22,N23,NA()),IF(N23>N22,N23,NA())),NA()) -> #N/A | AD4: =IF(O23<>"",IF($F22="Higher the better",IF(O23<O22,O23,NA()),IF(O23>O22,O23,NA())),NA()) -> #N/A | AE4: =IF(P23<>"",IF($F22="Higher the better",IF(P23<P22,P23,NA()),IF(P23>P22,P23,NA())),NA()) -> #N/A | AF4: =IF(Q23<>"",IF($F22="Higher the better",IF(Q23<Q22,Q23,NA()),IF(Q23>Q22,Q23,NA())),NA()) -> #N/A | ... AI4: =IF(T23<>"",IF($F22="Higher the better",IF(T23<T22,T23,NA()),IF(T23>T22,T23,NA())),NA()) -> #N/A
A5: KPI Name | B5: KPI Definition | C5: Operators | D5: Target AOP 2026 | E5: Units | F5: Metric nature | G5: Frequency | H5: Target/ Actual | I5: 46023 | J5: 46054 | K5: 46082 | L5: 46113 | M5: 46143 | N5: 46174 | O5: 46204 | P5: 46235 | Q5: 46266 | R5: 46296 | S5: 46327 | T5: 46357 | W5: Actual green | X5: =IF(#REF!<>"",IF(#REF!="Higher the better",IF(#REF!>=#REF!,#REF!,NA()),IF(#REF!<=#REF!,#REF!,NA())),NA()) -> #REF! | Y5: =IF(#REF!<>"",IF(#REF!="Higher the better",IF(#REF!>=#REF!,#REF!,NA()),IF(#REF!<=#REF!,#REF!,NA())),NA()) -> #REF! | Z5: =IF(#REF!<>"",IF(#REF!="Higher the better",IF(#REF!>=#REF!,#REF!,NA()),IF(#REF!<=#REF!,#REF!,NA())),NA()) -> #REF! | AA5: =IF(#REF!<>"",IF(#REF!="Higher the better",IF(#REF!>=#REF!,#REF!,NA()),IF(#REF!<=#REF!,#REF!,NA())),NA()) -> #REF! | AB5: =IF(#REF!<>"",IF(#REF!="Higher the better",IF(#REF!>=#REF!,#REF!,NA()),IF(#REF!<=#REF!,#REF!,NA())),NA()) -> #REF! | AC5: =IF(#REF!<>"",IF(#REF!="Higher the better",IF(#REF!>=#REF!,#REF!,NA()),IF(#REF!<=#REF!,#REF!,NA())),NA()) -> #REF! | AD5: =IF(#REF!<>"",IF(#REF!="Higher the better",IF(#REF!>=#REF!,#REF!,NA()),IF(#REF!<=#REF!,#REF!,NA())),NA()) -> #REF! | AE5: =IF(#REF!<>"",IF(#REF!="Higher the better",IF(#REF!>=#REF!,#REF!,NA()),IF(#REF!<=#REF!,#REF!,NA())),NA()) -> #REF! | ... AI5: =IF(#REF!<>"",IF(#REF!="Higher the better",IF(#REF!>=#REF!,#REF!,NA()),IF(#REF!<=#REF!,#REF!,NA())),NA()) -> #REF!
A6: % CAPA Investigations Currently ≤ 90 days | B6: Timeliness of investigations | C6: >= | D6: 90 | E6: % | F6: Higher the better | G6: Monthly | H6: Target | I6: 0.9 | J6: 0.9 | K6: 0.9 | L6: 0.9 | M6: 0.9 | N6: 0.9 | O6: 0.9 | P6: 0.9 | Q6: 0.9 | R6: 0.9 | S6: 0.9 | T6: 0.9 | W6: Actual red | X6: =IF(#REF!<>"",IF(#REF!="Higher the better",IF(#REF!<#REF!,#REF!,NA()),IF(#REF!>#REF!,#REF!,NA())),NA()) -> #REF! | Y6: =IF(#REF!<>"",IF(#REF!="Higher the better",IF(#REF!<#REF!,#REF!,NA()),IF(#REF!>#REF!,#REF!,NA())),NA()) -> #REF! | Z6: =IF(#REF!<>"",IF(#REF!="Higher the better",IF(#REF!<#REF!,#REF!,NA()),IF(#REF!>#REF!,#REF!,NA())),NA()) -> #REF! | AA6: =IF(#REF!<>"",IF(#REF!="Higher the better",IF(#REF!<#REF!,#REF!,NA()),IF(#REF!>#REF!,#REF!,NA())),NA()) -> #REF! | AB6: =IF(#REF!<>"",IF(#REF!="Higher the better",IF(#REF!<#REF!,#REF!,NA()),IF(#REF!>#REF!,#REF!,NA())),NA()) -> #REF! | AC6: =IF(#REF!<>"",IF(#REF!="Higher the better",IF(#REF!<#REF!,#REF!,NA()),IF(#REF!>#REF!,#REF!,NA())),NA()) -> #REF! | AD6: =IF(#REF!<>"",IF(#REF!="Higher the better",IF(#REF!<#REF!,#REF!,NA()),IF(#REF!>#REF!,#REF!,NA())),NA()) -> #REF! | AE6: =IF(#REF!<>"",IF(#REF!="Higher the better",IF(#REF!<#REF!,#REF!,NA()),IF(#REF!>#REF!,#REF!,NA())),NA()) -> #REF! | ... AI6: =IF(#REF!<>"",IF(#REF!="Higher the better",IF(#REF!<#REF!,#REF!,NA()),IF(#REF!>#REF!,#REF!,NA())),NA()) -> #REF!
H7: Actual | I7: 1 | J7: 0.75 | K7: 0.4 | L7: 0 | M7: 0 | N7: 0 | O7: 1 | P7: 1 | W7: Actual green | X7: =IF(#REF!<>"",IF(#REF!="Higher the better",IF(#REF!>=#REF!,#REF!,NA()),IF(#REF!<=#REF!,#REF!,NA())),NA()) -> #REF! | Y7: =IF(#REF!<>"",IF(#REF!="Higher the better",IF(#REF!>=#REF!,#REF!,NA()),IF(#REF!<=#REF!,#REF!,NA())),NA()) -> #REF! | Z7: =IF(#REF!<>"",IF(#REF!="Higher the better",IF(#REF!>=#REF!,#REF!,NA()),IF(#REF!<=#REF!,#REF!,NA())),NA()) -> #REF! | AA7: =IF(#REF!<>"",IF(#REF!="Higher the better",IF(#REF!>=#REF!,#REF!,NA()),IF(#REF!<=#REF!,#REF!,NA())),NA()) -> #REF! | AB7: =IF(#REF!<>"",IF(#REF!="Higher the better",IF(#REF!>=#REF!,#REF!,NA()),IF(#REF!<=#REF!,#REF!,NA())),NA()) -> #REF! | AC7: =IF(#REF!<>"",IF(#REF!="Higher the better",IF(#REF!>=#REF!,#REF!,NA()),IF(#REF!<=#REF!,#REF!,NA())),NA()) -> #REF! | AD7: =IF(#REF!<>"",IF(#REF!="Higher the better",IF(#REF!>=#REF!,#REF!,NA()),IF(#REF!<=#REF!,#REF!,NA())),NA()) -> #REF! | AE7: =IF(#REF!<>"",IF(#REF!="Higher the better",IF(#REF!>=#REF!,#REF!,NA()),IF(#REF!<=#REF!,#REF!,NA())),NA()) -> #REF! | ... AI7: =IF(#REF!<>"",IF(#REF!="Higher the better",IF(#REF!>=#REF!,#REF!,NA()),IF(#REF!<=#REF!,#REF!,NA())),NA()) -> #REF!
A8: % Complaints Open > 90 days | B8: Measures complaint closures | C8: <= | D8: Q1 (8%), Q2 (7%) Q3 (6%) Q4 (5%) | E8: % | F8: Lower the better | G8: Monthly | H8: Target | I8: 0.08 | J8: 0.08 | K8: 0.08 | L8: 0.07 | M8: 0.07 | N8: 0.07 | O8: 0.06 | P8: 0.06 | Q8: 0.06 | R8: 0.05 | S8: 0.05 | T8: 0.05 | W8: Actual red | X8: =IF(#REF!<>"",IF(#REF!="Higher the better",IF(#REF!<#REF!,#REF!,NA()),IF(#REF!>#REF!,#REF!,NA())),NA()) -> #REF! | Y8: =IF(#REF!<>"",IF(#REF!="Higher the better",IF(#REF!<#REF!,#REF!,NA()),IF(#REF!>#REF!,#REF!,NA())),NA()) -> #REF! | Z8: =IF(#REF!<>"",IF(#REF!="Higher the better",IF(#REF!<#REF!,#REF!,NA()),IF(#REF!>#REF!,#REF!,NA())),NA()) -> #REF! | AA8: =IF(#REF!<>"",IF(#REF!="Higher the better",IF(#REF!<#REF!,#REF!,NA()),IF(#REF!>#REF!,#REF!,NA())),NA()) -> #REF! | AB8: =IF(#REF!<>"",IF(#REF!="Higher the better",IF(#REF!<#REF!,#REF!,NA()),IF(#REF!>#REF!,#REF!,NA())),NA()) -> #REF! | AC8: =IF(#REF!<>"",IF(#REF!="Higher the better",IF(#REF!<#REF!,#REF!,NA()),IF(#REF!>#REF!,#REF!,NA())),NA()) -> #REF! | AD8: =IF(#REF!<>"",IF(#REF!="Higher the better",IF(#REF!<#REF!,#REF!,NA()),IF(#REF!>#REF!,#REF!,NA())),NA()) -> #REF! | AE8: =IF(#REF!<>"",IF(#REF!="Higher the better",IF(#REF!<#REF!,#REF!,NA()),IF(#REF!>#REF!,#REF!,NA())),NA()) -> #REF! | ... AI8: =IF(#REF!<>"",IF(#REF!="Higher the better",IF(#REF!<#REF!,#REF!,NA()),IF(#REF!>#REF!,#REF!,NA())),NA()) -> #REF!
H9: Actual | I9: 0.038 | J9: 0.038 | K9: 0.028 | L9: 0.026 | M9: 0.026 | N9: 0.03 | O9: 0.03 | P9: 0.035 | W9: Actual green | X9: =IF(I25<>"",IF($F24="Higher the better",IF(I25>=I24,I25,NA()),IF(I25<=I24,I25,NA())),NA()) -> 0 | Y9: =IF(J43<>"",IF($F42="Higher the better",IF(J43>=J42,J43,NA()),IF(J43<=J42,J43,NA())),NA()) -> #N/A | Z9: =IF(K43<>"",IF($F42="Higher the better",IF(K43>=K42,K43,NA()),IF(K43<=K42,K43,NA())),NA()) -> #N/A | AA9: =IF(L43<>"",IF($F42="Higher the better",IF(L43>=L42,L43,NA()),IF(L43<=L42,L43,NA())),NA()) -> #N/A | AB9: =IF(M43<>"",IF($F42="Higher the better",IF(M43>=M42,M43,NA()),IF(M43<=M42,M43,NA())),NA()) -> #N/A | AC9: =IF(N43<>"",IF($F42="Higher the better",IF(N43>=N42,N43,NA()),IF(N43<=N42,N43,NA())),NA()) -> #N/A | AD9: =IF(O43<>"",IF($F42="Higher the better",IF(O43>=O42,O43,NA()),IF(O43<=O42,O43,NA())),NA()) -> #N/A | AE9: =IF(P43<>"",IF($F42="Higher the better",IF(P43>=P42,P43,NA()),IF(P43<=P42,P43,NA())),NA()) -> #N/A | AF9: =IF(Q43<>"",IF($F42="Higher the better",IF(Q43>=Q42,Q43,NA()),IF(Q43<=Q42,Q43,NA())),NA()) -> #N/A | ... AI9: =IF(T43<>"",IF($F42="Higher the better",IF(T43>=T42,T43,NA()),IF(T43<=T42,T43,NA())),NA()) -> #N/A
A10: Complaint Rate of NPI products | B10: Complaint rate for Z10 | C10: <= | D10: 1.8 | E10: No. | F10: Lower the better | G10: Monthly | H10: Target | I10: 1.8 | J10: 1.8 | K10: 1.8 | L10: 1.8 | M10: 1.8 | N10: 1.8 | O10: 1.8 | P10: 1.8 | Q10: 1.8 | R10: 1.8 | S10: 1.8 | T10: 1.8 | W10: Actual red | X10: =IF(I25<>"",IF($F24="Higher the better",IF(I25<I24,I25,NA()),IF(I25>I24,I25,NA())),NA()) -> #N/A | Y10: =IF(J25<>"",IF($F24="Higher the better",IF(J25<J24,J25,NA()),IF(J25>J24,J25,NA())),NA()) -> #N/A | Z10: =IF(K25<>"",IF($F24="Higher the better",IF(K25<K24,K25,NA()),IF(K25>K24,K25,NA())),NA()) -> #N/A | AA10: =IF(L25<>"",IF($F24="Higher the better",IF(L25<L24,L25,NA()),IF(L25>L24,L25,NA())),NA()) -> #N/A | AB10: =IF(M25<>"",IF($F24="Higher the better",IF(M25<M24,M25,NA()),IF(M25>M24,M25,NA())),NA()) -> #N/A | AC10: =IF(N25<>"",IF($F24="Higher the better",IF(N25<N24,N25,NA()),IF(N25>N24,N25,NA())),NA()) -> #N/A | AD10: =IF(O25<>"",IF($F24="Higher the better",IF(O25<O24,O25,NA()),IF(O25>O24,O25,NA())),NA()) -> #N/A | AE10: =IF(P25<>"",IF($F24="Higher the better",IF(P25<P24,P25,NA()),IF(P25>P24,P25,NA())),NA()) -> #N/A | ... AI10: =IF(T25<>"",IF($F24="Higher the better",IF(T25<T24,T25,NA()),IF(T25>T24,T25,NA())),NA()) -> #N/A
H11: Actual | I11: 0.93 | J11: 0.8 | K11: 0.92 | L11: 1 | M11: 0.8 | N11: 0.8 | O11: 0.8 | W11: Actual green | X11: =IF(I27<>"",IF($F26="Higher the better",IF(I27>=I26,I27,NA()),IF(I27<=I26,I27,NA())),NA()) -> #N/A | Y11: =IF(J45<>"",IF($F44="Higher the better",IF(J45>=J44,J45,NA()),IF(J45<=J44,J45,NA())),NA()) -> #N/A | Z11: =IF(K45<>"",IF($F44="Higher the better",IF(K45>=K44,K45,NA()),IF(K45<=K44,K45,NA())),NA()) -> #N/A | AA11: =IF(L45<>"",IF($F44="Higher the better",IF(L45>=L44,L45,NA()),IF(L45<=L44,L45,NA())),NA()) -> #N/A | AB11: =IF(M45<>"",IF($F44="Higher the better",IF(M45>=M44,M45,NA()),IF(M45<=M44,M45,NA())),NA()) -> #N/A | AC11: =IF(N45<>"",IF($F44="Higher the better",IF(N45>=N44,N45,NA()),IF(N45<=N44,N45,NA())),NA()) -> #N/A | AD11: =IF(O45<>"",IF($F44="Higher the better",IF(O45>=O44,O45,NA()),IF(O45<=O44,O45,NA())),NA()) -> #N/A | AE11: =IF(P45<>"",IF($F44="Higher the better",IF(P45>=P44,P45,NA()),IF(P45<=P44,P45,NA())),NA()) -> #N/A | AF11: =IF(Q45<>"",IF($F44="Higher the better",IF(Q45>=Q44,Q45,NA()),IF(Q45<=Q44,Q45,NA())),NA()) -> #N/A | ... AI11: =IF(T45<>"",IF($F44="Higher the better",IF(T45>=T44,T45,NA()),IF(T45<=T44,T45,NA())),NA()) -> #N/A
B12: Complaint rate for Z30 | D12: 1.8 | F12: Lower the better | H12: Target | I12: 1.8 | J12: 1.8 | K12: 1.8 | L12: 1.8 | M12: 1.8 | N12: 1.8 | O12: 1.8 | P12: 1.8 | Q12: 1.8 | R12: 1.8 | S12: 1.8 | T12: 1.8 | W12: Actual red | X12: =IF(I27<>"",IF($F26="Higher the better",IF(I27<I26,I27,NA()),IF(I27>I26,I27,NA())),NA()) -> #N/A | Y12: =IF(J27<>"",IF($F26="Higher the better",IF(J27<J26,J27,NA()),IF(J27>J26,J27,NA())),NA()) -> #N/A | Z12: =IF(K27<>"",IF($F26="Higher the better",IF(K27<K26,K27,NA()),IF(K27>K26,K27,NA())),NA()) -> #N/A | AA12: =IF(L27<>"",IF($F26="Higher the better",IF(L27<L26,L27,NA()),IF(L27>L26,L27,NA())),NA()) -> #N/A | AB12: =IF(M27<>"",IF($F26="Higher the better",IF(M27<M26,M27,NA()),IF(M27>M26,M27,NA())),NA()) -> #N/A | AC12: =IF(N27<>"",IF($F26="Higher the better",IF(N27<N26,N27,NA()),IF(N27>N26,N27,NA())),NA()) -> #N/A | AD12: =IF(O27<>"",IF($F26="Higher the better",IF(O27<O26,O27,NA()),IF(O27>O26,O27,NA())),NA()) -> #N/A | AE12: =IF(P27<>"",IF($F26="Higher the better",IF(P27<P26,P27,NA()),IF(P27>P26,P27,NA())),NA()) -> #N/A | ... AI12: =IF(T27<>"",IF($F26="Higher the better",IF(T27<T26,T27,NA()),IF(T27>T26,T27,NA())),NA()) -> #N/A
H13: Actual | I13: 1.53 | J13: 1.53 | K13: 1.53 | L13: 1.7 | M13: 1.8 | N13: 1.4 | O13: 1.4 | W13: Actual green | X13: =IF(I25<>"",IF($F24="Higher the better",IF(I25>=I24,I25,NA()),IF(I25<=I24,I25,NA())),NA()) -> 0 | Y13: =IF(J25<>"",IF($F24="Higher the better",IF(J25>=J24,J25,NA()),IF(J25<=J24,J25,NA())),NA()) -> 0 | Z13: =IF(K25<>"",IF($F24="Higher the better",IF(K25>=K24,K25,NA()),IF(K25<=K24,K25,NA())),NA()) -> 0 | AA13: =IF(L25<>"",IF($F24="Higher the better",IF(L25>=L24,L25,NA()),IF(L25<=L24,L25,NA())),NA()) -> 0 | AB13: =IF(M25<>"",IF($F24="Higher the better",IF(M25>=M24,M25,NA()),IF(M25<=M24,M25,NA())),NA()) -> 0 | AC13: =IF(N25<>"",IF($F24="Higher the better",IF(N25>=N24,N25,NA()),IF(N25<=N24,N25,NA())),NA()) -> 0 | AD13: =IF(O25<>"",IF($F24="Higher the better",IF(O25>=O24,O25,NA()),IF(O25<=O24,O25,NA())),NA()) -> 0 | AE13: =IF(P25<>"",IF($F24="Higher the better",IF(P25>=P24,P25,NA()),IF(P25<=P24,P25,NA())),NA()) -> 0 | ... AI13: =IF(T25<>"",IF($F24="Higher the better",IF(T25>=T24,T25,NA()),IF(T25<=T24,T25,NA())),NA()) -> #N/A
B14: Complaint rate for Z90 | D14: 2.2 | F14: Lower the better | H14: Target | I14: 2.2 | J14: 2.2 | K14: 2.2 | L14: 2.2 | M14: 2.2 | N14: 2.2 | O14: 2.2 | P14: 2.2 | Q14: 2.2 | R14: 2.2 | S14: 2.2 | T14: 2.2 | W14: Actual red | X14: =IF(I25<>"",IF($F24="Higher the better",IF(I25<I24,I25,NA()),IF(I25>I24,I25,NA())),NA()) -> #N/A | Y14: =IF(J25<>"",IF($F24="Higher the better",IF(J25<J24,J25,NA()),IF(J25>J24,J25,NA())),NA()) -> #N/A | Z14: =IF(K25<>"",IF($F24="Higher the better",IF(K25<K24,K25,NA()),IF(K25>K24,K25,NA())),NA()) -> #N/A | AA14: =IF(L25<>"",IF($F24="Higher the better",IF(L25<L24,L25,NA()),IF(L25>L24,L25,NA())),NA()) -> #N/A | AB14: =IF(M25<>"",IF($F24="Higher the better",IF(M25<M24,M25,NA()),IF(M25>M24,M25,NA())),NA()) -> #N/A | AC14: =IF(N25<>"",IF($F24="Higher the better",IF(N25<N24,N25,NA()),IF(N25>N24,N25,NA())),NA()) -> #N/A | AD14: =IF(O25<>"",IF($F24="Higher the better",IF(O25<O24,O25,NA()),IF(O25>O24,O25,NA())),NA()) -> #N/A | AE14: =IF(P25<>"",IF($F24="Higher the better",IF(P25<P24,P25,NA()),IF(P25>P24,P25,NA())),NA()) -> #N/A | ... AI14: =IF(T25<>"",IF($F24="Higher the better",IF(T25<T24,T25,NA()),IF(T25>T24,T25,NA())),NA()) -> #N/A
H15: Actual | I15: 1.7 | J15: 1.76 | K15: 1.78 | L15: 2 | M15: 2.2 | N15: 1.8 | O15: 2
A16: C&R > Global Due date | B16: # of C&Rs that are open beyond plan in market | C16: <= | D16: 3 | E16: No. | F16: Lower the better | G16: Monthly | H16: Target | I16: 1 | J16: 1 | K16: 1 | L16: 1 | M16: 1 | N16: 1 | O16: 1 | P16: 1 | Q16: 1 | R16: 1 | S16: 1 | T16: 1
H17: Actual | I17: 2 | J17: 1 | K17: 1 | L17: 0 | M17: 0 | N17: 0 | O17: 0 | P17: 0
A18: Critical Enabling/Leading KPI's (3-5)
A19: KPI Name | B19: KPI Definition | C19: Operators | D19: Target AOP 2026 | E19: Units | F19: Metric nature | G19: Frequency | H19: Target/ Actual | I19: 46023 | J19: 46054 | K19: 46082 | L19: 46113 | M19: 46143 | N19: 46174 | O19: 46204 | P19: 46235 | Q19: 46266 | R19: 46296 | S19: 46327 | T19: 46357
A20: % CAPA implementation Tasks on time | B20: Number of actions completed without extension / Number of CAPA actions planned in that month as per Plan | C20: > | D20: 95 | E20: % | F20: Higher the better | G20: Monthly | H20: Target | I20: 0.95 | J20: 0.95 | K20: 0.95 | L20: 0.95 | M20: 0.95 | N20: 0.95 | O20: 0.95 | P20: 0.95 | Q20: 0.95 | R20: 0.95 | S20: 0.95 | T20: 0.95
H21: Actual | I21: 0.22 | J21: 0.4 | K21: 0.22 | L21: 0.4 | M21: 0.875 | N21: 0.3 | O21: 0.4 | P21: 0.83
A22: # of C&R in pre- release(Track remaining C&R) | B22: # of C&Rs waiting on C&R initiation | C22: <= | D22: 10 | E22: No. | F22: Lower the better | G22: Monthly | H22: Target | I22: 6 | J22: 5 | K22: 5 | L22: 4 | M22: 4 | N22: 4 | O22: 4 | P22: 2 | Q22: 2 | R22: 0 | S22: 0 | T22: 0
H23: Actual | I23: 6 | J23: 5 | K23: 5 | L23: 4 | M23: 4 | N23: 4 | O23: 4 | P23: 2
A24: Audit | B24: # Major Findings in external audits | C24: = | D24: 0 | E24: No. | F24: Lower the better | G24: Half yearly | H24: Target | I24: 0 | J24: 0 | K24: 0 | L24: 0 | M24: 0 | N24: 0 | O24: 0 | P24: 0 | Q24: 0 | R24: 0 | S24: 0 | T24: 0
H25: Actual | I25: 0 | J25: 0 | K25: 0 | L25: 0 | M25: 0 | N25: 0 | O25: 0 | P25: 0
H26: =IF(OR($F17="Lower the better",$F17="Lower the Better"), IF(I17>I16,$A16,""), IF(OR($F17="Higher the better",$F17="Higher the Better"), IF(I17<I16,$A16,""), "" ) )
A27: PS& Q Trends-
A44: If the KPI is reported Red, fill all the details as mentioned below for analysis & actions:
A46: Root Cause Analysis-
A47: Red KPI | B47: Top Causes
B48: Cause 1 | C48: Cause 2 | D48: Cause 3 | E48: Cause 4 | F48: Cause 5
A49: % CAPA investigation < 90 days | B49: Unavailability of Failed samples for Testing /analysis | C49: Complexity in risk management content alignment
A50: % impact on KPI gap | B50: 0.5 | C50: 0.5
A51: Red KPI | B51: Cause 1 | C51: Cause 2 | D51: Cause 3 | E51: Cause 4 | F51: Cause 5
A52: % CAPA implementation Tasks on time | B52: Lack of Ownership with either action owners or Support functions
A53: % impact on KPI gap | B53: 1
A54: Red KPI | B54: Cause 1 | C54: Cause 2 | D54: Cause 3 | E54: Cause 4 | F54: Cause 5
A55: Factory Yield | B55: SQN | C55: Design | D55: Warehousing | E55: Manufacturing | F55: Transport
A56: % impact on KPI gap | B56: 0.5 | C56: 0.19 | D56: 0.1 | E56: 0.08 | F56: 0.02
A57: Red KPI | B57: Cause 1 | C57: Cause 2 | D57: Cause 3 | E57: Cause 4 | F57: Cause 5
A59: % impact on KPI gap
A60: Red KPI | B60: Cause 1 | C60: Cause 2 | D60: Cause 3 | E60: Cause 4 | F60: Cause 5
A62: % impact on KPI gap
A63: Red KPI | B63: Cause 1 | C63: Cause 2 | D63: Cause 3 | E63: Cause 4 | F63: Cause 5
A65: % impact on KPI gap
A66: Paretos for RCA
A82: Action tracker | H82: Handshake Escalations/Support required
A83: Red KPI | B83: Root cause description | C83: Corrective action | D83: Owner | E83: Due Date | F83: Status | H83: KPI Name | I83: Key Dependency | J83: Function Name | K83: What action/s from Function is expected | L83: Success measure for Action Closure | M83: Handshaked (Yes or No) | N83: Open issue description | O83: Solutions to Open issues
A84: CAPA Investigation <90 Days | B84: Unavailability of Failed samples for Testing /analysis | C84: Evaluate the process of CAPA and arrangement of field samples to ensure timely availability of sample for analysis/investigation | D84: Praveen /Amey | E84: 46157 | F84: 5
A86: CAPA Investigation <90 Days | B86: Delayed Supplier Response for Deisgn owned by Suppiler | C86: Ensuring that CAPA team incudes Procurement and SQE for product CAPA's at the start of CAPA | D86: Praveen | E86: NA | F86: 5
A88: CAPA Investigation <90 Days | B88: Complexity | C88: VSM workshop Optimize process | D88: Praveen | E88: 46167 | F88: 5
A90: CAPA implementation tasks | B90: Lack of Clarity on C&R planning and executionat the time of CAPA action planning | C90: Collaborate with PM team on planning and priorotizing open CAPA Actions | D90: Praveen/Akash | E90: 46232 | F90: 2
A92: CAPA KPI's | B92: Lack of Ownership with either action owners or Support functions | C92: Ownershipd shall be assigned within 3 days from the date of Creation of Event in Appian Tool | D92: Shirpad D | E92: Effective from June 2026 | F92: 5
A93: CAPA KPI's | B93: Lack of Ownership with either action owners or Support functions | C93: Resource allocation /CAPA team formation in alignment with the people managers within 5 days | D93: Shirpad D | E93: Effective from June 2026 | F93: 5
A94: CAPA KPI's | B94: Lack of Ownership with either action owners or Support functions | C94: Checklist for all the new CAPA's for all the needs to perform Timely complation | D94: Akash | E94: 46203 | F94: 5
A95: CAPA KPI's | B95: Lack of Ownership with either action owners or Support functions | C95: Update all cross functional team shall have CAPA kpi as goals | D95: Praveen | E95: 46234 | F95: 2
A96: CAPA KPI's | B96: Lack of Ownership with either action owners or Support functions | C96: Review of CAPA documents shall be done within 3 working days | D96: Shirpad D | E96: Effective from July 2026 | F96: 5
A97: CAPA KPI's | B97: Lack of Ownership with either action owners or Support functions | C97: Ownership and report out on - CAPA investigation ownership - CAPA Implementation ownership ( inlcudes Extension of CAPA Action shall be taken atleast 30 days prior to the due date by the CAPA Action owner) - report out for overall CAPA performance | D97: Abhijit K | E97: Effective from July 2026 | F97: 5
A98: CAPA KPI's | B98: Lack of Ownership with either action owners or Support functions | C98: Escalation Matrix shall be defined for extension , resource alocation and support | D98: Akash/Shripad | E98: 46197 | F98: 5
A99: CAPA KPI's | B99: Lack of Ownership with either action owners or Support functions | C99: Appreciation For CAPA Work and WOW on how | D99: Neena | E99: 46192 | F99: 5
A100: CAPA KPI's | B100: Lack of Ownership with either action owners or Support functions | C100: Roadmap of CAPA implementation actions | D100: Akash | E100: 46198 | F100: 5
A101: CAPA KPI's | B101: Lack of Ownership with either action owners or Support functions/Complexity in risk management content alignment | C101: Capability development in Key document contents - Compile all the feedback/learnings from previous document reviews ( 1 year ) and provide training to respecive stakeholders ( PPMRR/HHE/HHED/CRRB ppt) | D101: Action Owner To be decided with Shripad | E101: 46295 | F101: 2
A102: CAPA KPI's | B102: Lack of Ownership with either action owners or Support functions | C102: Conduct Training to all stakeholders and compile list of CAPA Owners trained on CAPA process | D102: Praveen | E102: Ongoing | F102: 3
F103: 1
F105: 1
A107: Action not assigned | B107: Action assigned | C107: Action started | D107: Action completed | E107: Resolution confirmed

Sheet 2.Regulatory
A1: Month | B1: 46023 | C1: MT Owner: | D1: Sumit K | E1: MT Delegate: | F1: Sagar Paste | V1: Actual green | W1: =IF(I15<>"",IF($F14="Higher the better",IF(I15>=I14,I15,NA()),IF(I15<=I14,I15,NA())),NA()) -> 0 | X1: =IF(J15<>"",IF($F14="Higher the better",IF(J15>=J14,J15,NA()),IF(J15<=J14,J15,NA())),NA()) -> 0.011111111 | Y1: =IF(K15<>"",IF($F14="Higher the better",IF(K15>=K14,K15,NA()),IF(K15<=K14,K15,NA())),NA()) -> 0 | Z1: =IF(L15<>"",IF($F14="Higher the better",IF(L15>=L14,L15,NA()),IF(L15<=L14,L15,NA())),NA()) -> 0 | AA1: =IF(M15<>"",IF($F14="Higher the better",IF(M15>=M14,M15,NA()),IF(M15<=M14,M15,NA())),NA()) -> 0 | AB1: =IF(N15<>"",IF($F14="Higher the better",IF(N15>=N14,N15,NA()),IF(N15<=N14,N15,NA())),NA()) -> 0 | AC1: =IF(O15<>"",IF($F14="Higher the better",IF(O15>=O14,O15,NA()),IF(O15<=O14,O15,NA())),NA()) -> 0 | AD1: =IF(P15<>"",IF($F14="Higher the better",IF(P15>=P14,P15,NA()),IF(P15<=P14,P15,NA())),NA()) -> 0 | ... AH1: =IF(T15<>"",IF($F14="Higher the better",IF(T15>=T14,T15,NA()),IF(T15<=T14,T15,NA())),NA()) -> #N/A
V2: Actual red | W2: =IF(I15<>"",IF($F14="Higher the better",IF(I15<I14,I15,NA()),IF(I15>I14,I15,NA())),NA()) -> #N/A | X2: =IF(J15<>"",IF($F14="Higher the better",IF(J15<J14,J15,NA()),IF(J15>J14,J15,NA())),NA()) -> #N/A | Y2: =IF(K15<>"",IF($F14="Higher the better",IF(K15<K14,K15,NA()),IF(K15>K14,K15,NA())),NA()) -> #N/A | Z2: =IF(L15<>"",IF($F14="Higher the better",IF(L15<L14,L15,NA()),IF(L15>L14,L15,NA())),NA()) -> #N/A | AA2: =IF(M15<>"",IF($F14="Higher the better",IF(M15<M14,M15,NA()),IF(M15>M14,M15,NA())),NA()) -> #N/A | AB2: =IF(N15<>"",IF($F14="Higher the better",IF(N15<N14,N15,NA()),IF(N15>N14,N15,NA())),NA()) -> #N/A | AC2: =IF(O15<>"",IF($F14="Higher the better",IF(O15<O14,O15,NA()),IF(O15>O14,O15,NA())),NA()) -> #N/A | AD2: =IF(P15<>"",IF($F14="Higher the better",IF(P15<P14,P15,NA()),IF(P15>P14,P15,NA())),NA()) -> #N/A | ... AH2: =IF(T15<>"",IF($F14="Higher the better",IF(T15<T14,T15,NA()),IF(T15>T14,T15,NA())),NA()) -> #N/A
A3: Regulatory DMB | V3: Actual green | W3: =IF(I17<>"",IF($F16="Higher the better",IF(I17>=I16,I17,NA()),IF(I17<=I16,I17,NA())),NA()) -> 1 | X3: =IF(J17<>"",IF($F16="Higher the better",IF(J17>=J16,J17,NA()),IF(J17<=J16,J17,NA())),NA()) -> #N/A | Y3: =IF(K17<>"",IF($F16="Higher the better",IF(K17>=K16,K17,NA()),IF(K17<=K16,K17,NA())),NA()) -> 1 | Z3: =IF(L17<>"",IF($F16="Higher the better",IF(L17>=L16,L17,NA()),IF(L17<=L16,L17,NA())),NA()) -> #N/A | AA3: =IF(M17<>"",IF($F16="Higher the better",IF(M17>=M16,M17,NA()),IF(M17<=M16,M17,NA())),NA()) -> 1 | AB3: =IF(N17<>"",IF($F16="Higher the better",IF(N17>=N16,N17,NA()),IF(N17<=N16,N17,NA())),NA()) -> 1 | AC3: =IF(O17<>"",IF($F16="Higher the better",IF(O17>=O16,O17,NA()),IF(O17<=O16,O17,NA())),NA()) -> 1 | AD3: =IF(P17<>"",IF($F16="Higher the better",IF(P17>=P16,P17,NA()),IF(P17<=P16,P17,NA())),NA()) -> 1 | ... AH3: =IF(T17<>"",IF($F16="Higher the better",IF(T17>=T16,T17,NA()),IF(T17<=T16,T17,NA())),NA()) -> #N/A
A4: Mandatory Outcome KPI's (1-3) | V4: Actual red | W4: =IF(I17<>"",IF($F16="Higher the better",IF(I17<I16,I17,NA()),IF(I17>I16,I17,NA())),NA()) -> #N/A | X4: =IF(J17<>"",IF($F16="Higher the better",IF(J17<J16,J17,NA()),IF(J17>J16,J17,NA())),NA()) -> 0.5 | Y4: =IF(K17<>"",IF($F16="Higher the better",IF(K17<K16,K17,NA()),IF(K17>K16,K17,NA())),NA()) -> #N/A | Z4: =IF(L17<>"",IF($F16="Higher the better",IF(L17<L16,L17,NA()),IF(L17>L16,L17,NA())),NA()) -> 0 | AA4: =IF(M17<>"",IF($F16="Higher the better",IF(M17<M16,M17,NA()),IF(M17>M16,M17,NA())),NA()) -> #N/A | AB4: =IF(N17<>"",IF($F16="Higher the better",IF(N17<N16,N17,NA()),IF(N17>N16,N17,NA())),NA()) -> #N/A | AC4: =IF(O17<>"",IF($F16="Higher the better",IF(O17<O16,O17,NA()),IF(O17>O16,O17,NA())),NA()) -> #N/A | AD4: =IF(P17<>"",IF($F16="Higher the better",IF(P17<P16,P17,NA()),IF(P17>P16,P17,NA())),NA()) -> #N/A | ... AH4: =IF(T17<>"",IF($F16="Higher the better",IF(T17<T16,T17,NA()),IF(T17>T16,T17,NA())),NA()) -> #N/A
A5: Mandatory KPI | B5: KPI Definition | C5: Operators | D5: Target AOP 2026 | E5: Units | F5: Metric nature | G5: Frequency | H5: Target/ Actual | I5: 46023 | J5: 46054 | K5: 46082 | L5: 46113 | M5: 46143 | N5: 46174 | O5: 46204 | P5: 46235 | Q5: 46266 | R5: 46296 | S5: 46327 | T5: 46357 | V5: Actual green | W5: =IF(I19<>0,IF($F18="Higher the better",IF(I19>=I18,I19,NA()),IF(I19<=I18,I19,NA())),NA()) -> 1 | X5: =IF(J19<>0,IF($F18="Higher the better",IF(J19>=J18,J19,NA()),IF(J19<=J18,J19,NA())),NA()) -> 1 | Y5: =IF(K19<>0,IF($F18="Higher the better",IF(K19>=K18,K19,NA()),IF(K19<=K18,K19,NA())),NA()) -> 1 | Z5: =IF(L19<>0,IF($F18="Higher the better",IF(L19>=L18,L19,NA()),IF(L19<=L18,L19,NA())),NA()) -> #N/A | AA5: =IF(M19<>0,IF($F18="Higher the better",IF(M19>=M18,M19,NA()),IF(M19<=M18,M19,NA())),NA()) -> 1 | AB5: =IF(N19<>0,IF($F18="Higher the better",IF(N19>=N18,N19,NA()),IF(N19<=N18,N19,NA())),NA()) -> 1 | AC5: =IF(O19<>0,IF($F18="Higher the better",IF(O19>=O18,O19,NA()),IF(O19<=O18,O19,NA())),NA()) -> 1 | AD5: =IF(P19<>0,IF($F18="Higher the better",IF(P19>=P18,P19,NA()),IF(P19<=P18,P19,NA())),NA()) -> 1 | ... AH5: =IF(T19<>0,IF($F18="Higher the better",IF(T19>=T18,T19,NA()),IF(T19<=T18,T19,NA())),NA()) -> #N/A
A6: Registrations & re-certifications on time | B6: (Registration approvals and renewals completed on time) *100/ Total number of approvals planned for the month | C6: >= | D6: 0.97 | E6: % | F6: Higher the better | G6: Monthly | H6: Target | I6: 0.97 | J6: 0.97 | K6: 0.97 | L6: 0.97 | M6: 0.97 | N6: 0.97 | O6: 0.97 | P6: 0.97 | Q6: 0.97 | R6: 0.97 | S6: 0.97 | T6: 0.97 | V6: Actual red | W6: =IF(I19<>0,IF($F18="Higher the better",IF(I19<I18,I19,NA()),IF(I19>I18,I19,NA())),NA()) -> #N/A | X6: =IF(J19<>0,IF($F18="Higher the better",IF(J19<J18,J19,NA()),IF(J19>J18,J19,NA())),NA()) -> #N/A | Y6: =IF(K19<>0,IF($F18="Higher the better",IF(K19<K18,K19,NA()),IF(K19>K18,K19,NA())),NA()) -> #N/A | Z6: =IF(L19<>0,IF($F18="Higher the better",IF(L19<L18,L19,NA()),IF(L19>L18,L19,NA())),NA()) -> 0.93939394 | AA6: =IF(M19<>0,IF($F18="Higher the better",IF(M19<M18,M19,NA()),IF(M19>M18,M19,NA())),NA()) -> #N/A | AB6: =IF(N19<>0,IF($F18="Higher the better",IF(N19<N18,N19,NA()),IF(N19>N18,N19,NA())),NA()) -> #N/A | AC6: =IF(O19<>0,IF($F18="Higher the better",IF(O19<O18,O19,NA()),IF(O19>O18,O19,NA())),NA()) -> #N/A | AD6: =IF(P19<>0,IF($F18="Higher the better",IF(P19<P18,P19,NA()),IF(P19>P18,P19,NA())),NA()) -> #N/A | ... AH6: =IF(T19<>0,IF($F18="Higher the better",IF(T19<T18,T19,NA()),IF(T19>T18,T19,NA())),NA()) -> #N/A
H7: Actual | I7: =13/13 -> 1 | J7: =5/5 -> 1 | K7: =8/8 -> 1 | L7: =6/9 -> 0.66666667 | M7: =3/3 -> 1 | N7: =6/6 -> 1 | O7: =5/5 -> 1 | P7: =6/6 -> 1 | V7: Actual green | W7: =IF(I21<>"",IF($F20="Higher the better",IF(I21>=I20,I21,NA()),IF(I21<=I20,I21,NA())),NA()) -> 1 | X7: =IF(J21<>"",IF($F20="Higher the better",IF(J21>=J20,J21,NA()),IF(J21<=J20,J21,NA())),NA()) -> 1 | Y7: =IF(K21<>"",IF($F20="Higher the better",IF(K21>=K20,K21,NA()),IF(K21<=K20,K21,NA())),NA()) -> 0.97058824 | Z7: =IF(L21<>"",IF($F20="Higher the better",IF(L21>=L20,L21,NA()),IF(L21<=L20,L21,NA())),NA()) -> 1 | AA7: =IF(M21<>"",IF($F20="Higher the better",IF(M21>=M20,M21,NA()),IF(M21<=M20,M21,NA())),NA()) -> 1 | AB7: =IF(N21<>"",IF($F20="Higher the better",IF(N21>=N20,N21,NA()),IF(N21<=N20,N21,NA())),NA()) -> 1 | AC7: =IF(O21<>"",IF($F20="Higher the better",IF(O21>=O20,O21,NA()),IF(O21<=O20,O21,NA())),NA()) -> 1 | AD7: =IF(P21<>"",IF($F20="Higher the better",IF(P21>=P20,P21,NA()),IF(P21<=P20,P21,NA())),NA()) -> 1 | ... AH7: =IF(T21<>"",IF($F20="Higher the better",IF(T21>=T20,T21,NA()),IF(T21<=T20,T21,NA())),NA()) -> #N/A
A8: NPI submission on time | B8: (NPI priority country submissions executed on time) *100/ Total number of submissions planned for the month | C8: >= | D8: 1 | E8: % | F8: Higher the better | G8: Monthly | H8: Target | V8: Actual red | W8: =IF(I21<>0,IF($F20="Higher the better",IF(I21<I20,I21,NA()),IF(I21>I20,I21,NA())),NA()) -> #N/A | X8: =IF(J21<>0,IF($F20="Higher the better",IF(J21<J20,J21,NA()),IF(J21>J20,J21,NA())),NA()) -> #N/A | Y8: =IF(K21<>0,IF($F20="Higher the better",IF(K21<K20,K21,NA()),IF(K21>K20,K21,NA())),NA()) -> #N/A | Z8: =IF(L21<>0,IF($F20="Higher the better",IF(L21<L20,L21,NA()),IF(L21>L20,L21,NA())),NA()) -> #N/A | AA8: =IF(M21<>0,IF($F20="Higher the better",IF(M21<M20,M21,NA()),IF(M21>M20,M21,NA())),NA()) -> #N/A | AB8: =IF(N21<>0,IF($F20="Higher the better",IF(N21<N20,N21,NA()),IF(N21>N20,N21,NA())),NA()) -> #N/A | AC8: =IF(O21<>0,IF($F20="Higher the better",IF(O21<O20,O21,NA()),IF(O21>O20,O21,NA())),NA()) -> #N/A | AD8: =IF(P21<>0,IF($F20="Higher the better",IF(P21<P20,P21,NA()),IF(P21>P20,P21,NA())),NA()) -> #N/A | ... AH8: =IF(T21<>0,IF($F20="Higher the better",IF(T21<T20,T21,NA()),IF(T21>T20,T21,NA())),NA()) -> #N/A
H9: Actual
A10: Submission on Time | B10: (Regulatory submissions executed on time) *100/ Total number of submissions planned for the month | C10: >= | D10: 1 | E10: % | F10: Higher the better | G10: Monthly | H10: Target | I10: 1 | J10: 1 | K10: 1 | L10: 1 | M10: 1 | N10: 1 | O10: 1 | P10: 1 | Q10: 1 | R10: 1 | S10: 1 | T10: 1
H11: Actual | I11: =31/31 -> 1 | J11: =52/52 -> 1 | K11: =60/60 -> 1 | L11: =11/12 -> 0.91666667 | M11: =7/7 -> 1 | N11: =13/13 -> 1 | O11: =8/8 -> 1 | P11: =9/9 -> 1
A12: Critical Enabling/Leading KPI's (3-5)
A13: KPI Name | B13: KPI Definition | C13: Operators | D13: Target AOP 2026 | E13: Units | F13: Metric nature | G13: Frequency | H13: Target/ Actual | I13: 46023 | J13: 46054 | K13: 46082 | L13: 46113 | M13: 46143 | N13: 46174 | O13: 46204 | P13: 46235 | Q13: 46266 | R13: 46296 | S13: 46327 | T13: 46357
A14: Country readiness | B14: (Orders impacted due to regulatory or other readiness-related blocks) *100/ Total orders planned for that month | C14: <= | D14: 0.1 | E14: % | F14: Lower the better | G14: Monthly | H14: Target | I14: 0.1 | J14: 0.1 | K14: 0.1 | L14: 0.1 | M14: 0.1 | N14: 0.1 | O14: 0.1 | P14: 0.1 | Q14: 0.1 | R14: 0.1 | S14: 0.1 | T14: 0.1
H15: Actual | I15: 0 | J15: =1/90 -> 0.011111111 | K15: 0 | L15: =0/92 -> 0 | M15: =0/133 -> 0 | N15: =0/144 -> 0 | O15: 0 | P15: 0
A16: Product Change assessment | B16: (Product change assessments completed by Regulatory within 6 weeks from the date of request) *100/ Total change assessments completion planned during that month | C16: >= | D16: 0.95 | E16: % | F16: Higher the better | G16: Monthly | H16: Target | I16: 0.95 | J16: 0.95 | K16: 0.95 | L16: 0.95 | M16: 0.95 | N16: 0.95 | O16: 0.95 | P16: 0.95 | Q16: 0.95 | R16: 0.95 | S16: 0.95 | T16: 0.95
H17: Actual | I17: =1/1 -> 1 | J17: =1/2 -> 0.5 | K17: =1/1 -> 1 | L17: =0/3 -> 0 | M17: =3/3 -> 1 | N17: =2/2 -> 1 | O17: =1/1 -> 1 | P17: =2/2 -> 1
A18: Submission readiness | B18: (Completed regulatory submission documents) *100/ Total submission deliverables needed for each planned country submission | C18: = | D18: 1 | E18: % | F18: Higher the better | G18: Monthly | H18: Target | I18: 1 | J18: 1 | K18: 1 | L18: 1 | M18: 1 | N18: 1 | O18: 1 | P18: 1 | Q18: 1 | R18: 1 | S18: 1 | T18: 1
H19: Actual | I19: =14/14 -> 1 | J19: 1 | K19: 1 | L19: =124/132 -> 0.93939394 | M19: =25/25 -> 1 | N19: =213/213 -> 1 | O19: =63/63 -> 1 | P19: =68/68 -> 1
A20: Quality of submission | B20: (Planned regulatory submissions accepted first-time-right) *100/ Total submission submitted in that month | C20: >= | D20: 0.95 | E20: % | F20: Higher the better | G20: Monthly | H20: Target | I20: 0.95 | J20: 0.95 | K20: 0.95 | L20: 0.95 | M20: 0.95 | N20: 0.95 | O20: 0.95 | P20: 0.95 | Q20: 0.95 | R20: 0.95 | S20: 0.95 | T20: 0.95
H21: Actual | I21: =31/31 -> 1 | J21: 1 | K21: =33/34 -> 0.97058824 | L21: 1 | M21: 1 | N21: 1 | O21: 1 | P21: 1
H22: =IF(OR($F19="Lower the better",$F19="Lower the Better"), IF(I15>I14,$A18,""), IF(OR($F19="Higher the better",$F19="Higher the Better"), IF(I15<I14,$A18,""), "" ) )
A23: Trends-
A40: If the KPI is reported Red, fill all the details as mentioned below for analysis & actions:
A42: Root Cause Analysis-
A43: Red KPI | B43: Top Causes
B44: Cause 1 | C44: Cause 2 | D44: Cause 3 | E44: Cause 4 | F44: Cause 5
A45: Product Change assessment (Feb-26) | B45: KM RA Resource unavailable during year end holiday
A46: % impact on KPI gap | B46: 1
A47: Red KPI | B47: Cause 1 | C47: Cause 2 | D47: Cause 3 | E47: Cause 4 | F47: Cause 5
A48: Registrations & re-certifications on time (Apr-26) | B48: Renewal of license for Zenition products in Nigeria not received formally due to administrative delay with health authority.
A49: % impact on KPI gap | B49: 1
A50: Red KPI | B50: Cause 1 | C50: Cause 2 | D50: Cause 3 | E50: Cause 4 | F50: Cause 5
A51: Product Change assessment (Apr-26 & May-26) | B51: There were many PCNs to be attended by KM RA within short period of time which resulted in this delay. | C51: KM RA resources did not prioritize these change assessments over other work from IGTS and also other BUs.
A52: % impact on KPI gap | B52: 0.5 | C52: 0.5
A53: Red KPI | B53: Cause 1 | C53: Cause 2 | D53: Cause 3 | E53: Cause 4 | F53: Cause 5
A54: Submission readiness (Apr-26) | B54: Supplier (Trixell) was not ready to share submission documents in desired format due to confidentiality reasons as supplier was new to suchs kind of request.
A55: % impact on KPI gap | B55: 1
A56: Red KPI | B56: Cause 1 | C56: Cause 2 | D56: Cause 3 | E56: Cause 4 | F56: Cause 5
A58: % impact on KPI gap
A59: Red KPI | B59: Cause 1 | C59: Cause 2 | D59: Cause 3 | E59: Cause 4 | F59: Cause 5
A61: % impact on KPI gap
A62: Paretos for RCA
A78: Action tracker | H78: Handshake Escalations/Support required
A79: Red KPI | B79: Root cause description | C79: Corrective action | D79: Owner | E79: Due Date | F79: Status | H79: KPI Name | I79: Key Dependency | J79: Function Name | K79: What action/s from Function is expected | L79: Success measure for Action Closure | M79: Handshaked (Yes or No) | N79: Open issue description | O79: Solutions to Open issues
A80: Product Change assessment (Feb-26) | B80: Resource unavailable during year end holiday | C80: Follow up/escalate to Market RA lead and avoid dependency on one resources for future. | D80: Boobalan/ Viryanti | E80: 46079 | F80: 5
A82: Registrations & re-certifications on time (Apr-26) | B82: Renewal of license Zenition products in Nigeria not received formally due to administrative delay with health authority. | C82: Follow up/escalate to Market RA lead. | D82: Sagar/Madeleine | E82: 46171 | F82: 5
A84: Product Change assessment (Apr-26) | B84: There were many PCNs to be attended by KM RA within short period of time which resulted in this delay. | C84: Where possible Regulatory and PMs to plan and distribute PCN worthy changes evenly so that work is not concentrarted over short period of time. | D84: Sagar/Sumit | E84: 46162 | F84: 5
A86: Product Change assessment (Apr-26) | B86: KM RA resources did not prioritize these change assessments over other work from IGTS and also other BUs. | C86: Ensure KM follow the priorities communicated through monthly calls. And escalate the response delays to KM RA leads. | D86: Sagar/Sumit | E86: 46162 | F86: 5
A88: Submission readiness (Apr-26) | B88: Supplier not ready to share submission documents due to confidentiality reasons | C88: Escalate via Procurement team GSM . RA to proactively plan on such license applications looking at the VCP and get involved at supplier onboarding stage. | D88: Gyanendra/Pavan | E88: 46157 | F88: 5
F90: 1
A92: Action not assigned | B92: Action assigned | C92: Action started | D92: Action completed | E92: Resolution confirmed

Sheet 3.ISC 
A1: Month | B1: 46023 | C1: MT Owner: | D1: Rupali J | E1: MT Delegate: | F1: Souvik Das | W1: Actual green | X1: =IF(I15<>"",IF($F14="Higher the better",IF(I15>=I14,I15,NA()),IF(I15<=I14,I15,NA())),NA()) -> 0.91 | Y1: =IF(J15<>"",IF($F14="Higher the better",IF(J15>=J14,J15,NA()),IF(J15<=J14,J15,NA())),NA()) -> 0.96 | Z1: =IF(K15<>"",IF($F14="Higher the better",IF(K15>=K14,K15,NA()),IF(K15<=K14,K15,NA())),NA()) -> #N/A | AA1: =IF(L15<>"",IF($F14="Higher the better",IF(L15>=L14,L15,NA()),IF(L15<=L14,L15,NA())),NA()) -> #N/A | AB1: =IF(M15<>"",IF($F14="Higher the better",IF(M15>=M14,M15,NA()),IF(M15<=M14,M15,NA())),NA()) -> #N/A | AC1: =IF(N15<>"",IF($F14="Higher the better",IF(N15>=N14,N15,NA()),IF(N15<=N14,N15,NA())),NA()) -> 0.95 | AD1: =IF(O15<>"",IF($F14="Higher the better",IF(O15>=O14,O15,NA()),IF(O15<=O14,O15,NA())),NA()) -> 0.92 | AE1: =IF(P15<>"",IF($F14="Higher the better",IF(P15>=P14,P15,NA()),IF(P15<=P14,P15,NA())),NA()) -> #N/A | ... AI1: =IF(T15<>"",IF($F14="Higher the better",IF(T15>=T14,T15,NA()),IF(T15<=T14,T15,NA())),NA()) -> #N/A
W2: Actual red | X2: =IF(I15<>"",IF($F14="Higher the better",IF(I15<I14,I15,NA()),IF(I15>I14,I15,NA())),NA()) -> #N/A | Y2: =IF(J15<>"",IF($F14="Higher the better",IF(J15<J14,J15,NA()),IF(J15>J14,J15,NA())),NA()) -> #N/A | Z2: =IF(K15<>"",IF($F14="Higher the better",IF(K15<K14,K15,NA()),IF(K15>K14,K15,NA())),NA()) -> 0.66 | AA2: =IF(L15<>"",IF($F14="Higher the better",IF(L15<L14,L15,NA()),IF(L15>L14,L15,NA())),NA()) -> 0.73 | AB2: =IF(M15<>"",IF($F14="Higher the better",IF(M15<M14,M15,NA()),IF(M15>M14,M15,NA())),NA()) -> 0.71 | AC2: =IF(N15<>"",IF($F14="Higher the better",IF(N15<N14,N15,NA()),IF(N15>N14,N15,NA())),NA()) -> #N/A | AD2: =IF(O15<>"",IF($F14="Higher the better",IF(O15<O14,O15,NA()),IF(O15>O14,O15,NA())),NA()) -> #N/A | AE2: =IF(P15<>"",IF($F14="Higher the better",IF(P15<P14,P15,NA()),IF(P15>P14,P15,NA())),NA()) -> #N/A | ... AI2: =IF(T15<>"",IF($F14="Higher the better",IF(T15<T14,T15,NA()),IF(T15>T14,T15,NA())),NA()) -> #N/A
A3: ISC - DMB | W3: Actual green | X3: =IF(I17<>"",IF($F16="Higher the better",IF(I17>=I16,I17,NA()),IF(I17<=I16,I17,NA())),NA()) -> 113 | Y3: =IF(J17<>"",IF($F16="Higher the better",IF(J17>=J16,J17,NA()),IF(J17<=J16,J17,NA())),NA()) -> 119 | Z3: =IF(K17<>"",IF($F16="Higher the better",IF(K17>=K16,K17,NA()),IF(K17<=K16,K17,NA())),NA()) -> #N/A | AA3: =IF(L17<>"",IF($F16="Higher the better",IF(L17>=L16,L17,NA()),IF(L17<=L16,L17,NA())),NA()) -> #N/A | AB3: =IF(M17<>"",IF($F16="Higher the better",IF(M17>=M16,M17,NA()),IF(M17<=M16,M17,NA())),NA()) -> #N/A | AC3: =IF(N17<>"",IF($F16="Higher the better",IF(N17>=N16,N17,NA()),IF(N17<=N16,N17,NA())),NA()) -> #N/A | AD3: =IF(O17<>"",IF($F16="Higher the better",IF(O17>=O16,O17,NA()),IF(O17<=O16,O17,NA())),NA()) -> #N/A | AE3: =IF(P17<>"",IF($F16="Higher the better",IF(P17>=P16,P17,NA()),IF(P17<=P16,P17,NA())),NA()) -> #N/A | ... AI3: =IF(T17<>"",IF($F16="Higher the better",IF(T17>=T16,T17,NA()),IF(T17<=T16,T17,NA())),NA()) -> #N/A
A4: Mandatory Outcome KPI's (1-3) | N4: YTD | W4: Actual red | X4: =IF(I17<>"",IF($F16="Higher the better",IF(I17<I16,I17,NA()),IF(I17>I16,I17,NA())),NA()) -> #N/A | Y4: =IF(J17<>"",IF($F16="Higher the better",IF(J17<J16,J17,NA()),IF(J17>J16,J17,NA())),NA()) -> #N/A | Z4: =IF(K17<>"",IF($F16="Higher the better",IF(K17<K16,K17,NA()),IF(K17>K16,K17,NA())),NA()) -> 111 | AA4: =IF(L17<>"",IF($F16="Higher the better",IF(L17<L16,L17,NA()),IF(L17>L16,L17,NA())),NA()) -> 89 | AB4: =IF(M17<>"",IF($F16="Higher the better",IF(M17<M16,M17,NA()),IF(M17>M16,M17,NA())),NA()) -> 113 | AC4: =IF(N17<>"",IF($F16="Higher the better",IF(N17<N16,N17,NA()),IF(N17>N16,N17,NA())),NA()) -> 109 | AD4: =IF(O17<>"",IF($F16="Higher the better",IF(O17<O16,O17,NA()),IF(O17>O16,O17,NA())),NA()) -> 116 | AE4: =IF(P17<>"",IF($F16="Higher the better",IF(P17<P16,P17,NA()),IF(P17>P16,P17,NA())),NA()) -> #N/A | ... AI4: =IF(T17<>"",IF($F16="Higher the better",IF(T17<T16,T17,NA()),IF(T17>T16,T17,NA())),NA()) -> #N/A
A5: Mandatory KPI | B5: KPI Definition | C5: Operators | D5: Target AOP 2026 | E5: Units | F5: Metric nature | G5: Frequency | H5: Target/ Actual | I5: 46023 | J5: 46054 | K5: 46082 | L5: 46113 | M5: 46143 | N5: 46174 | O5: 46204 | P5: 46235 | Q5: 46266 | R5: 46296 | S5: 46327 | T5: 46357 | W5: Actual green | X5: =IF(I19<>"",IF($F18="Higher the better",IF(I19>=I18,I19,NA()),IF(I19<=I18,I19,NA())),NA()) -> 0.93 | Y5: =IF(J19<>"",IF($F18="Higher the better",IF(J19>=J18,J19,NA()),IF(J19<=J18,J19,NA())),NA()) -> 0.89 | Z5: =IF(K19<>"",IF($F18="Higher the better",IF(K19>=K18,K19,NA()),IF(K19<=K18,K19,NA())),NA()) -> #N/A | AA5: =IF(L19<>"",IF($F18="Higher the better",IF(L19>=L18,L19,NA()),IF(L19<=L18,L19,NA())),NA()) -> #N/A | AB5: =IF(M19<>"",IF($F18="Higher the better",IF(M19>=M18,M19,NA()),IF(M19<=M18,M19,NA())),NA()) -> 0.93 | AC5: =IF(N19<>"",IF($F18="Higher the better",IF(N19>=N18,N19,NA()),IF(N19<=N18,N19,NA())),NA()) -> 0.93 | AD5: =IF(O19<>"",IF($F18="Higher the better",IF(O19>=O18,O19,NA()),IF(O19<=O18,O19,NA())),NA()) -> 0.92 | AE5: =IF(P19<>"",IF($F18="Higher the better",IF(P19>=P18,P19,NA()),IF(P19<=P18,P19,NA())),NA()) -> 0.96 | ... AI5: =IF(T19<>"",IF($F18="Higher the better",IF(T19>=T18,T19,NA()),IF(T19<=T18,T19,NA())),NA()) -> #N/A
A6: Sales | B6: Revenue in M | C6: > | D6: 141/143 | E6: Mn | F6: Higher the better | G6: Monthly | H6: Target | I6: 8.6903065 | J6: 14.057193 | K6: 24.179072 | L6: 33.551326 | M6: 41.442864 | N6: 60.823993 | O6: 72.557892 | P6: 82.449741 | Q6: 97.417089 | R6: 109.99427 | S6: 123.7114 | T6: 144.52879 | W6: Actual red | X6: =IF(I19<>"",IF($F18="Higher the better",IF(I19<I18,I19,NA()),IF(I19>I18,I19,NA())),NA()) -> #N/A | Y6: =IF(J19<>"",IF($F18="Higher the better",IF(J19<J18,J19,NA()),IF(J19>J18,J19,NA())),NA()) -> #N/A | Z6: =IF(K19<>"",IF($F18="Higher the better",IF(K19<K18,K19,NA()),IF(K19>K18,K19,NA())),NA()) -> 0.88 | AA6: =IF(L19<>"",IF($F18="Higher the better",IF(L19<L18,L19,NA()),IF(L19>L18,L19,NA())),NA()) -> 0.84 | AB6: =IF(M19<>"",IF($F18="Higher the better",IF(M19<M18,M19,NA()),IF(M19>M18,M19,NA())),NA()) -> #N/A | AC6: =IF(N19<>"",IF($F18="Higher the better",IF(N19<N18,N19,NA()),IF(N19>N18,N19,NA())),NA()) -> #N/A | AD6: =IF(O19<>"",IF($F18="Higher the better",IF(O19<O18,O19,NA()),IF(O19>O18,O19,NA())),NA()) -> #N/A | AE6: =IF(P19<>"",IF($F18="Higher the better",IF(P19<P18,P19,NA()),IF(P19>P18,P19,NA())),NA()) -> #N/A | ... AI6: =IF(T19<>"",IF($F18="Higher the better",IF(T19<T18,T19,NA()),IF(T19>T18,T19,NA())),NA()) -> #N/A
H7: Actual | I7: 4.1 | J7: 9.8 | K7: 25.3 | L7: 31.44 | M7: 40.9 | N7: 55.18 | O7: 61.4 | W7: Actual green | X7: =IF(I21<>"",IF($F20="Higher the better",IF(I21>=I20,I21,NA()),IF(I21<=I20,I21,NA())),NA()) -> 0.8 | Y7: =IF(J21<>"",IF($F20="Higher the better",IF(J21>=J20,J21,NA()),IF(J21<=J20,J21,NA())),NA()) -> 0.9 | Z7: =IF(K21<>"",IF($F20="Higher the better",IF(K21>=K20,K21,NA()),IF(K21<=K20,K21,NA())),NA()) -> 1.02 | AA7: =IF(L21<>"",IF($F20="Higher the better",IF(L21>=L20,L21,NA()),IF(L21<=L20,L21,NA())),NA()) -> #N/A | AB7: =IF(M21<>"",IF($F20="Higher the better",IF(M21>=M20,M21,NA()),IF(M21<=M20,M21,NA())),NA()) -> #N/A | AC7: =IF(N21<>"",IF($F20="Higher the better",IF(N21>=N20,N21,NA()),IF(N21<=N20,N21,NA())),NA()) -> #N/A | AD7: =IF(O21<>"",IF($F20="Higher the better",IF(O21>=O20,O21,NA()),IF(O21<=O20,O21,NA())),NA()) -> #N/A | AE7: =IF(P21<>"",IF($F20="Higher the better",IF(P21>=P20,P21,NA()),IF(P21<=P20,P21,NA())),NA()) -> #N/A | ... AI7: =IF(T21<>"",IF($F20="Higher the better",IF(T21>=T20,T21,NA()),IF(T21<=T20,T21,NA())),NA()) -> #N/A
A8: OTIF | B8: CDD adherance | C8: > | D8: 0.85 | E8: % | F8: Higher the better | G8: Monthly | H8: Target | I8: 0.69 | J8: 0.69 | K8: 0.69 | L8: 0.72 | M8: 0.72 | N8: 0.72 | O8: 0.74 | P8: 0.74 | Q8: 0.74 | R8: 0.77 | S8: 0.77 | T8: 0.8 | W8: Actual red | X8: =IF(I21<>"",IF($F20="Higher the better",IF(I21<I20,I21,NA()),IF(I21>I20,I21,NA())),NA()) -> #N/A | Y8: =IF(J21<>"",IF($F20="Higher the better",IF(J21<J20,J21,NA()),IF(J21>J20,J21,NA())),NA()) -> #N/A | Z8: =IF(K21<>"",IF($F20="Higher the better",IF(K21<K20,K21,NA()),IF(K21>K20,K21,NA())),NA()) -> #N/A | AA8: =IF(L21<>"",IF($F20="Higher the better",IF(L21<L20,L21,NA()),IF(L21>L20,L21,NA())),NA()) -> 0.6 | AB8: =IF(M21<>"",IF($F20="Higher the better",IF(M21<M20,M21,NA()),IF(M21>M20,M21,NA())),NA()) -> 0.72 | AC8: =IF(N21<>"",IF($F20="Higher the better",IF(N21<N20,N21,NA()),IF(N21>N20,N21,NA())),NA()) -> 0.81 | AD8: =IF(O21<>"",IF($F20="Higher the better",IF(O21<O20,O21,NA()),IF(O21>O20,O21,NA())),NA()) -> 0.56 | AE8: =IF(P21<>"",IF($F20="Higher the better",IF(P21<P20,P21,NA()),IF(P21>P20,P21,NA())),NA()) -> 0.71 | ... AI8: =IF(T21<>"",IF($F20="Higher the better",IF(T21<T20,T21,NA()),IF(T21>T20,T21,NA())),NA()) -> #N/A
H9: Actual | I9: 0.83 | J9: 0.82 | K9: 0.81 | L9: 0.6 | M9: 0.87 | N9: 0.77 | O9: 0.7 | W9: Actual green | X9: =IF(I23<>"",IF($F22="Higher the better",IF(I23>=I22,I23,NA()),IF(I23<=I22,I23,NA())),NA()) -> #N/A | Y9: =IF(J23<>"",IF($F22="Higher the better",IF(J23>=J22,J23,NA()),IF(J23<=J22,J23,NA())),NA()) -> #N/A | Z9: =IF(K23<>"",IF($F22="Higher the better",IF(K23>=K22,K23,NA()),IF(K23<=K22,K23,NA())),NA()) -> #N/A | AA9: =IF(L23<>"",IF($F22="Higher the better",IF(L23>=L22,L23,NA()),IF(L23<=L22,L23,NA())),NA()) -> #N/A | AB9: =IF(M23<>"",IF($F22="Higher the better",IF(M23>=M22,M23,NA()),IF(M23<=M22,M23,NA())),NA()) -> #N/A | AC9: =IF(N23<>"",IF($F22="Higher the better",IF(N23>=N22,N23,NA()),IF(N23<=N22,N23,NA())),NA()) -> #N/A | AD9: =IF(O23<>"",IF($F22="Higher the better",IF(O23>=O22,O23,NA()),IF(O23<=O22,O23,NA())),NA()) -> #N/A | AE9: =IF(P23<>"",IF($F22="Higher the better",IF(P23>=P22,P23,NA()),IF(P23<=P22,P23,NA())),NA()) -> #N/A | ... AI9: =IF(T23<>"",IF($F22="Higher the better",IF(T23>=T22,T23,NA()),IF(T23<=T22,T23,NA())),NA()) -> #N/A
A10: Inventory | B10: (Business+Market+Service ) as % of sales | C10: < | D10: 22% / 49 M | E10: % | F10: Lower the better | G10: Monthly | H10: Target | I10: 0.283 | J10: 0.28 | K10: 0.29 | L10: 0.28678379 | M10: 0.26777766 | N10: 0.25862821 | O10: 0.24073532 | P10: 0.23371552 | Q10: 0.24603537 | R10: 0.23568022 | S10: 0.23414399 | T10: 0.21107105 | W10: Actual red | X10: =IF(I23<>"",IF($F22="Higher the better",IF(I23<I22,I23,NA()),IF(I23>I22,I23,NA())),NA()) -> 17.3 | Y10: =IF(J23<>"",IF($F22="Higher the better",IF(J23<J22,J23,NA()),IF(J23>J22,J23,NA())),NA()) -> 21.89 | Z10: =IF(K23<>"",IF($F22="Higher the better",IF(K23<K22,K23,NA()),IF(K23>K22,K23,NA())),NA()) -> 21.44 | AA10: =IF(L23<>"",IF($F22="Higher the better",IF(L23<L22,L23,NA()),IF(L23>L22,L23,NA())),NA()) -> 24.02 | AB10: =IF(M23<>"",IF($F22="Higher the better",IF(M23<M22,M23,NA()),IF(M23>M22,M23,NA())),NA()) -> 24.1 | AC10: =IF(N23<>"",IF($F22="Higher the better",IF(N23<N22,N23,NA()),IF(N23>N22,N23,NA())),NA()) -> 22.5 | AD10: =IF(O23<>"",IF($F22="Higher the better",IF(O23<O22,O23,NA()),IF(O23>O22,O23,NA())),NA()) -> 23 | AE10: =IF(P23<>"",IF($F22="Higher the better",IF(P23<P22,P23,NA()),IF(P23>P22,P23,NA())),NA()) -> #N/A | ... AI10: =IF(T23<>"",IF($F22="Higher the better",IF(T23<T22,T23,NA()),IF(T23>T22,T23,NA())),NA()) -> #N/A
H11: Actual | I11: 0.274 | J11: 0.29 | K11: 0.29 | L11: 0.3 | M11: 0.3 | N11: 0.29 | O11: 0.3 | W11: Actual green | X11: =IF(I25<>"",IF($F24="Higher the better",IF(I25>=I24,I25,NA()),IF(I25<=I24,I25,NA())),NA()) -> 7 | Y11: =IF(J25<>"",IF($F24="Higher the better",IF(J25>=J24,J25,NA()),IF(J25<=J24,J25,NA())),NA()) -> 8 | Z11: =IF(K25<>"",IF($F24="Higher the better",IF(K25>=K24,K25,NA()),IF(K25<=K24,K25,NA())),NA()) -> #N/A | AA11: =IF(L25<>"",IF($F24="Higher the better",IF(L25>=L24,L25,NA()),IF(L25<=L24,L25,NA())),NA()) -> #N/A | AB11: =IF(M25<>"",IF($F24="Higher the better",IF(M25>=M24,M25,NA()),IF(M25<=M24,M25,NA())),NA()) -> #N/A | AC11: =IF(N25<>"",IF($F24="Higher the better",IF(N25>=N24,N25,NA()),IF(N25<=N24,N25,NA())),NA()) -> 9 | AD11: =IF(O25<>"",IF($F24="Higher the better",IF(O25>=O24,O25,NA()),IF(O25<=O24,O25,NA())),NA()) -> 13 | AE11: =IF(P25<>"",IF($F24="Higher the better",IF(P25>=P24,P25,NA()),IF(P25<=P24,P25,NA())),NA()) -> #N/A | ... AI11: =IF(T25<>"",IF($F24="Higher the better",IF(T25>=T24,T25,NA()),IF(T25<=T24,T25,NA())),NA()) -> #N/A
A12: Critical Enabling/Leading KPI's (3-5) | W12: Actual red | X12: =IF(I25<>"",IF($F24="Higher the better",IF(I25<I24,I25,NA()),IF(I25>I24,I25,NA())),NA()) -> #N/A | Y12: =IF(J25<>"",IF($F24="Higher the better",IF(J25<J24,J25,NA()),IF(J25>J24,J25,NA())),NA()) -> #N/A | Z12: =IF(K25<>"",IF($F24="Higher the better",IF(K25<K24,K25,NA()),IF(K25>K24,K25,NA())),NA()) -> 28 | AA12: =IF(L25<>"",IF($F24="Higher the better",IF(L25<L24,L25,NA()),IF(L25>L24,L25,NA())),NA()) -> 16 | AB12: =IF(M25<>"",IF($F24="Higher the better",IF(M25<M24,M25,NA()),IF(M25>M24,M25,NA())),NA()) -> 20 | AC12: =IF(N25<>"",IF($F24="Higher the better",IF(N25<N24,N25,NA()),IF(N25>N24,N25,NA())),NA()) -> #N/A | AD12: =IF(O25<>"",IF($F24="Higher the better",IF(O25<O24,O25,NA()),IF(O25>O24,O25,NA())),NA()) -> #N/A | AE12: =IF(P25<>"",IF($F24="Higher the better",IF(P25<P24,P25,NA()),IF(P25>P24,P25,NA())),NA()) -> #N/A | ... AI12: =IF(T25<>"",IF($F24="Higher the better",IF(T25<T24,T25,NA()),IF(T25>T24,T25,NA())),NA()) -> #N/A
A13: KPI Name | B13: KPI Definition | C13: Operators | D13: Target AOP 2026 | E13: Units | F13: Metric nature | G13: Frequency | H13: Target/ Actual | I13: 46023 | J13: 46054 | K13: 46082 | L13: 46113 | M13: 46143 | N13: 46174 | O13: 46204 | P13: 46235 | Q13: 46266 | R13: 46296 | S13: 46327 | T13: 46357 | W13: Actual green | X13: =IF(#REF!<>"",IF(#REF!="Higher the better",IF(#REF!>=#REF!,#REF!,NA()),IF(#REF!<=#REF!,#REF!,NA())),NA()) -> #REF! | Y13: =IF(#REF!<>"",IF(#REF!="Higher the better",IF(#REF!>=#REF!,#REF!,NA()),IF(#REF!<=#REF!,#REF!,NA())),NA()) -> #REF! | Z13: =IF(#REF!<>"",IF(#REF!="Higher the better",IF(#REF!>=#REF!,#REF!,NA()),IF(#REF!<=#REF!,#REF!,NA())),NA()) -> #REF! | AA13: =IF(#REF!<>"",IF(#REF!="Higher the better",IF(#REF!>=#REF!,#REF!,NA()),IF(#REF!<=#REF!,#REF!,NA())),NA()) -> #REF! | AB13: =IF(#REF!<>"",IF(#REF!="Higher the better",IF(#REF!>=#REF!,#REF!,NA()),IF(#REF!<=#REF!,#REF!,NA())),NA()) -> #REF! | AC13: =IF(#REF!<>"",IF(#REF!="Higher the better",IF(#REF!>=#REF!,#REF!,NA()),IF(#REF!<=#REF!,#REF!,NA())),NA()) -> #REF! | AD13: =IF(#REF!<>"",IF(#REF!="Higher the better",IF(#REF!>=#REF!,#REF!,NA()),IF(#REF!<=#REF!,#REF!,NA())),NA()) -> #REF! | AE13: =IF(#REF!<>"",IF(#REF!="Higher the better",IF(#REF!>=#REF!,#REF!,NA()),IF(#REF!<=#REF!,#REF!,NA())),NA()) -> #REF! | ... AI13: =IF(#REF!<>"",IF(#REF!="Higher the better",IF(#REF!>=#REF!,#REF!,NA()),IF(#REF!<=#REF!,#REF!,NA())),NA()) -> #REF!
A14: Ontime supply | B14: FSD adherance | C14: > | D14: 0.9 | E14: % | F14: Higher the better | G14: Monthly | H14: Target | I14: 0.9 | J14: 0.9 | K14: 0.9 | L14: 0.9 | M14: 0.9 | N14: 0.9 | O14: 0.9 | P14: 0.9 | Q14: 0.9 | R14: 0.9 | S14: 0.9 | T14: 0.9 | W14: Actual red | X14: =IF(#REF!<>"",IF(#REF!="Higher the better",IF(#REF!<#REF!,#REF!,NA()),IF(#REF!>#REF!,#REF!,NA())),NA()) -> #REF! | Y14: =IF(#REF!<>"",IF(#REF!="Higher the better",IF(#REF!<#REF!,#REF!,NA()),IF(#REF!>#REF!,#REF!,NA())),NA()) -> #REF! | Z14: =IF(#REF!<>"",IF(#REF!="Higher the better",IF(#REF!<#REF!,#REF!,NA()),IF(#REF!>#REF!,#REF!,NA())),NA()) -> #REF! | AA14: =IF(#REF!<>"",IF(#REF!="Higher the better",IF(#REF!<#REF!,#REF!,NA()),IF(#REF!>#REF!,#REF!,NA())),NA()) -> #REF! | AB14: =IF(#REF!<>"",IF(#REF!="Higher the better",IF(#REF!<#REF!,#REF!,NA()),IF(#REF!>#REF!,#REF!,NA())),NA()) -> #REF! | AC14: =IF(#REF!<>"",IF(#REF!="Higher the better",IF(#REF!<#REF!,#REF!,NA()),IF(#REF!>#REF!,#REF!,NA())),NA()) -> #REF! | AD14: =IF(#REF!<>"",IF(#REF!="Higher the better",IF(#REF!<#REF!,#REF!,NA()),IF(#REF!>#REF!,#REF!,NA())),NA()) -> #REF! | AE14: =IF(#REF!<>"",IF(#REF!="Higher the better",IF(#REF!<#REF!,#REF!,NA()),IF(#REF!>#REF!,#REF!,NA())),NA()) -> #REF! | ... AI14: =IF(#REF!<>"",IF(#REF!="Higher the better",IF(#REF!<#REF!,#REF!,NA()),IF(#REF!>#REF!,#REF!,NA())),NA()) -> #REF!
H15: Actual | I15: 0.91 | J15: 0.96 | K15: 0.66 | L15: 0.73 | M15: 0.71 | N15: 0.95 | O15: 0.92 | W15: Actual green | X15: =IF(#REF!<>"",IF(#REF!="Higher the better",IF(#REF!>=#REF!,#REF!,NA()),IF(#REF!<=#REF!,#REF!,NA())),NA()) -> #REF! | Y15: =IF(#REF!<>"",IF(#REF!="Higher the better",IF(#REF!>=#REF!,#REF!,NA()),IF(#REF!<=#REF!,#REF!,NA())),NA()) -> #REF! | Z15: =IF(#REF!<>"",IF(#REF!="Higher the better",IF(#REF!>=#REF!,#REF!,NA()),IF(#REF!<=#REF!,#REF!,NA())),NA()) -> #REF! | AA15: =IF(#REF!<>"",IF(#REF!="Higher the better",IF(#REF!>=#REF!,#REF!,NA()),IF(#REF!<=#REF!,#REF!,NA())),NA()) -> #REF! | AB15: =IF(#REF!<>"",IF(#REF!="Higher the better",IF(#REF!>=#REF!,#REF!,NA()),IF(#REF!<=#REF!,#REF!,NA())),NA()) -> #REF! | AC15: =IF(#REF!<>"",IF(#REF!="Higher the better",IF(#REF!>=#REF!,#REF!,NA()),IF(#REF!<=#REF!,#REF!,NA())),NA()) -> #REF! | AD15: =IF(#REF!<>"",IF(#REF!="Higher the better",IF(#REF!>=#REF!,#REF!,NA()),IF(#REF!<=#REF!,#REF!,NA())),NA()) -> #REF! | AE15: =IF(#REF!<>"",IF(#REF!="Higher the better",IF(#REF!>=#REF!,#REF!,NA()),IF(#REF!<=#REF!,#REF!,NA())),NA()) -> #REF! | ... AI15: =IF(#REF!<>"",IF(#REF!="Higher the better",IF(#REF!>=#REF!,#REF!,NA()),IF(#REF!<=#REF!,#REF!,NA())),NA()) -> #REF!
A16: Production units | B16: Production number | C16: > | D16: 1332/1400 | E16: No. | F16: Higher the better | G16: Monthly | H16: Target | J16: 118 | K16: 124 | L16: 129 | M16: 132 | N16: 130 | O16: 125 | P16: 125 | Q16: 123 | R16: 123 | S16: 121 | T16: 79 | W16: Actual red | X16: =IF(#REF!<>"",IF(#REF!="Higher the better",IF(#REF!<#REF!,#REF!,NA()),IF(#REF!>#REF!,#REF!,NA())),NA()) -> #REF! | Y16: =IF(#REF!<>"",IF(#REF!="Higher the better",IF(#REF!<#REF!,#REF!,NA()),IF(#REF!>#REF!,#REF!,NA())),NA()) -> #REF! | Z16: =IF(#REF!<>"",IF(#REF!="Higher the better",IF(#REF!<#REF!,#REF!,NA()),IF(#REF!>#REF!,#REF!,NA())),NA()) -> #REF! | AA16: =IF(#REF!<>"",IF(#REF!="Higher the better",IF(#REF!<#REF!,#REF!,NA()),IF(#REF!>#REF!,#REF!,NA())),NA()) -> #REF! | AB16: =IF(#REF!<>"",IF(#REF!="Higher the better",IF(#REF!<#REF!,#REF!,NA()),IF(#REF!>#REF!,#REF!,NA())),NA()) -> #REF! | AC16: =IF(#REF!<>"",IF(#REF!="Higher the better",IF(#REF!<#REF!,#REF!,NA()),IF(#REF!>#REF!,#REF!,NA())),NA()) -> #REF! | AD16: =IF(#REF!<>"",IF(#REF!="Higher the better",IF(#REF!<#REF!,#REF!,NA()),IF(#REF!>#REF!,#REF!,NA())),NA()) -> #REF! | AE16: =IF(#REF!<>"",IF(#REF!="Higher the better",IF(#REF!<#REF!,#REF!,NA()),IF(#REF!>#REF!,#REF!,NA())),NA()) -> #REF! | ... AI16: =IF(#REF!<>"",IF(#REF!="Higher the better",IF(#REF!<#REF!,#REF!,NA()),IF(#REF!>#REF!,#REF!,NA())),NA()) -> #REF!
H17: Actual | I17: 113 | J17: 119 | K17: 111 | L17: 89 | M17: 113 | N17: 109 | O17: 116
A18: CTB (12 weeks) | B18: Clear to build material avaialbility | C18: > | D18: 0.9 | E18: % | F18: Higher the better | G18: Monthly | H18: Target | I18: 0.85 | J18: 0.87 | K18: 0.9 | L18: 0.9 | M18: 0.9 | N18: 0.9 | O18: 0.9 | P18: 0.9 | Q18: 0.92 | R18: 0.92 | S18: 0.92 | T18: 0.92
H19: Actual | I19: 0.93 | J19: 0.89 | K19: 0.88 | L19: 0.84 | M19: 0.93 | N19: 0.93 | O19: 0.92 | P19: 0.96
A20: OOH % | B20: OOH % for revnue in the Qtr | C20: > | D20: % | E20: % | F20: Higher the better | G20: Monthly | H20: Target | I20: 0.8 | J20: 0.9 | K20: 0.95 | L20: 0.8 | M20: 0.9 | N20: 0.95 | O20: 0.8 | P20: 0.95 | Q20: 1
H21: Actual | I21: 0.8 | J21: 0.9 | K21: 1.02 | L21: 0.6 | M21: 0.72 | N21: 0.81 | O21: 0.56 | P21: 0.71
A22: Market Inventory | B22: Market inventory | C22: < | D22: 10 % reduction | E22: Mn | F22: Lower the better | G22: Monthly | H22: Target | I22: 11.540479 | J22: 13.985593 | K22: 14.900208 | L22: 15.546561 | M22: 12.923735 | N22: 13.018238 | O22: 11.345502 | P22: 11.43287 | Q22: 14.88858 | R22: 13.436985 | S22: 15.144875 | T22: 9.5717963
H23: Actual | I23: 17.3 | J23: 21.89 | K23: 21.44 | L23: 24.02 | M23: 24.1 | N23: 22.5 | O23: 23
A24: CDD push out / month | B24: CDD move out during to execution | C24: <= | D24: 15 | E24: No. | F24: Lower the better | G24: Monthly | H24: Target | I24: 15 | J24: 15 | K24: 15 | L24: 15 | M24: 15 | N24: 15 | O24: 15 | P24: 15 | Q24: 15 | R24: 15 | S24: 15 | T24: 15
H25: Actual | I25: 7 | J25: 8 | K25: =0+0+14+11+3 -> 28 | L25: 16 | M25: 20 | N25: 9 | O25: 13
A26: Supplier Quality - Product Quality DMB
A27: Mandatory Outcome KPI's (1-3)
A28: Mandatory KPI | B28: KPI Definition | C28: Operators | D28: Target AOP 2026 | E28: Units | F28: Metric nature | G28: Frequency | H28: Target/ Actual | I28: 46023 | J28: 46054 | K28: 46082 | L28: 46113 | M28: 46143 | N28: 46174 | O28: 46204 | P28: 46235 | Q28: 46266 | R28: 46296 | S28: 46327 | T28: 46357
A29: SQN reduction | B29: Supplier Quality notification reduction | C29: >= | D29: 0.2 | E29: % | F29: Lower the better | G29: Monthly | H29: Target | I29: 15 | J29: 15 | K29: 15 | L29: 15 | M29: 15 | N29: 15 | O29: 15 | P29: 15 | Q29: 15 | R29: 15 | S29: 15 | T29: 15
H30: Actual | I30: 11 | J30: 11 | K30: 14 | L30: 11 | M30: 9 | N30: 9 | O30: 11
A31: SCAR Performance | B31: SCAR Clsoure % SCARs Closed < 180d | C31: >= | D31: 0.9 | E31: % | F31: Higher the better | G31: Monthly | H31: Target | I31: 0.9 | J31: 0.9 | K31: 0.9 | L31: 0.9 | M31: 0.9 | N31: 0.9 | O31: 0.9 | P31: 0.9 | Q31: 0.9 | R31: 0.9 | S31: 0.9 | T31: 0.9
H32: Actual | I32: 1 | J32: 1 | K32: 1 | L32: 1 | M32: 1 | N32: 1 | O32: 1
A33: SCAR Performance | B33: SCARs on time to plan (OTTP) | C33: >= | D33: 0.95 | E33: % | F33: Higher the better | G33: Monthly | H33: Target | I33: 0.95 | J33: 0.95 | K33: 0.95 | L33: 0.95 | M33: 0.95 | N33: 0.95 | O33: 0.95 | P33: 0.95 | Q33: 0.95 | R33: 0.95 | S33: 0.95 | T33: 0.95
H34: Actual | I34: 0.71 | J34: 0.74 | K34: 1 | L34: 1 | M34: 1 | N34: 1 | O34: 1
A35: SICRs execution | B35: Monthly execution of high priority SICRs without any line down situation | C35: >= | D35: 1 | E35: % | F35: Higher the better | G35: Monthly | H35: Target | I35: 1 | J35: 1 | K35: 1 | L35: 1 | M35: 1 | N35: 1 | O35: 1 | P35: 1 | Q35: 1 | R35: 1 | S35: 1 | T35: 1
H36: Actual | I36: 1 | J36: 1 | K36: 1 | L36: 1 | M36: 1 | N36: 1 | O36: 1
A37: DEFOA | B37: commercial Defect On Arrival at customer place | C37: < | D37: 0.03 | E37: No. | F37: Lower the better | G37: Monthly | H37: Target | I37: 0.03 | J37: 0.03 | K37: 0.03 | L37: 0.03 | M37: 0.03 | N37: 0.03 | O37: 0.03
H38: Actual | I38: 0.03 | J38: 0.04 | K38: 0.006 | L38: 0 | M38: 0.02 | N38: 0.013 | O38: 0.01
A39: Factory Yeild ( NPI) | B39: (Total Units dispatched-Number of defective products during manufacturing) *100/Total units dispatched | C39: >= | D39: 85 | E39: % | F39: Higher the better | G39: Monthly | H39: Target | I39: 0.85 | J39: 0.85 | K39: 0.85 | L39: 0.85 | M39: 0.85 | N39: 0.85 | O39: 0.85 | P39: 0.85 | Q39: 0.85 | R39: 0.85 | S39: 0.85 | T39: 0.85
H40: Actual | I40: 0.75 | J40: 0.8 | K40: 0.77 | L40: 0.84 | M40: 0.85 | N40: 0.9 | O40: 0.86
A42: Trends-
A59: If the KPI is reported Red, fill all the details as mentioned below for analysis & actions:
A60: Root Cause Analysis-
A61: Red KPI | B61: Top Causes
B62: Cause 1 | C62: Cause 2 | D62: Cause 3 | E62: Cause 4 | F62: Cause 5
A63: Production units | B63: Yoshiro FD17 covers for Zen 90
A64: % impact on KPI gap | B64: 1
A65: Red KPI | B65: Cause 1 | C65: Cause 2 | D65: Cause 3 | E65: Cause 4 | F65: Cause 5
A66: Inventory | B66: META-Hudut 41 systems + Morocco DEFOA | C66: UKI socking | D66: Intransit inventory (due to ME situation) | E66: NAM defoa | F66: Europe DEMO
A67: % impact on KPI gap | B67: =3.3/12 -> 0.275 | C67: =1.8/12 -> 0.15 | D67: =4/12 -> 0.33333333 | E67: =0.3/12 -> 0.025 | F67: =2.6/12 -> 0.21666667
A68: Red KPI | B68: Cause 1 | C68: Cause 2 | D68: Cause 3 | E68: Cause 4 | F68: Cause 5
A69: OOH% to revunue in Qtr. | B69: Europe | C69: Growth
A70: % impact on KPI gap | B70: 0.6 | C70: 0.4
A71: Red KPI | B71: Cause 1 | C71: Cause 2 | D71: 41852 | E71: Cause 4 | F71: Cause 5
A74: Red KPI | B74: Cause 1 | C74: Cause 2 | D74: Cause 3 | E74: Cause 4 | F74: Cause 5
A77: Red KPI | B77: Cause 1 | C77: Cause 2 | D77: Cause 3 | E77: Cause 4 | F77: Cause 5
A80: Paretos for RCA
A96: Action tracker | H96: Handshake Escalations/Support required
A97: Red KPI | B97: Root cause description | C97: Corrective action | D97: Owner | E97: Due Date | F97: Status | H97: KPI Name | I97: Key Dependency | J97: Function Name | K97: What action/s from Function is expected | L97: Success measure for Action Closure | M97: Handshaked (Yes or No) | N97: Open issue description | O97: Solutions to Open issues
A98: CDD push out | B98: Transit delay due to ME crises | C98: Daily monitoring and tracking /escalation | D98: Souvik | E98: Ongoing | F98: 4
A100: Market Inventory | B100: 41 Hudut systems are under rev | C100: rev conversion | D100: Ranga | E100: Sep | F100: 2
A102: Market Inventory | B102: Stocking systems in UKI | C102: Ensure Stock units conversion to revenue | D102: Silvia | E102: NOV | F102: 3
A104: Market Inventory | B104: NAR commerical and FSL stock revnue conversion | C104: revenue conversion | D104: Sarah | E104: Sept | F104: 3
A105: OOH% | B105: Convert Funnel to OIT 4 M | C105: OIT conversion | D105: Sarahand Mark | E105: Sept | F105: 4
A106: OOH% | B106: Hudut order 21 systems Q3 pull in | C106: pull in rev | D106: Ranga | E106: Aug | F106: 3
A108: OOH % | B108: Namibia oder and venuzuala tender orders awaitied | C108: Drive Q3 revenue convertible OIT | D108: Mahmut | E108: Aug | F108: 3
A110: OOH % | B110: EU B&B OIT for Q3 :1.5M | C110: Drive Q3 revenue convertible OIT | D110: Silvia | E110: Aug | F110: 2
A112: Action not assigned | B112: Action assigned | C112: Action started | D112: Action completed | E112: Resolution confirmed

Sheet 4.Procurement
A1: Month | B1: 46023 | C1: MT Owner: | D1: Anand P | E1: MT Delegate: | W1: Actual green | X1: =IF(I15<>"",IF($F14="Higher the better",IF(I15>=I14,I15,NA()),IF(I15<=I14,I15,NA())),NA()) -> 15 | Y1: =IF(J15<>"",IF($F14="Higher the better",IF(J15>=J14,J15,NA()),IF(J15<=J14,J15,NA())),NA()) -> #N/A | Z1: =IF(K15<>"",IF($F14="Higher the better",IF(K15>=K14,K15,NA()),IF(K15<=K14,K15,NA())),NA()) -> 15 | AA1: =IF(L15<>"",IF($F14="Higher the better",IF(L15>=L14,L15,NA()),IF(L15<=L14,L15,NA())),NA()) -> 22 | AB1: =IF(M15<>"",IF($F14="Higher the better",IF(M15>=M14,M15,NA()),IF(M15<=M14,M15,NA())),NA()) -> 1 | AC1: =IF(N15<>"",IF($F14="Higher the better",IF(N15>=N14,N15,NA()),IF(N15<=N14,N15,NA())),NA()) -> 10 | AD1: =IF(O15<>"",IF($F14="Higher the better",IF(O15>=O14,O15,NA()),IF(O15<=O14,O15,NA())),NA()) -> 1 | AE1: =IF(P15<>"",IF($F14="Higher the better",IF(P15>=P14,P15,NA()),IF(P15<=P14,P15,NA())),NA()) -> #N/A | ... AI1: =IF(T15<>"",IF($F14="Higher the better",IF(T15>=T14,T15,NA()),IF(T15<=T14,T15,NA())),NA()) -> #N/A
W2: Actual red | X2: =IF(I15<>"",IF($F14="Higher the better",IF(I15<I14,I15,NA()),IF(I15>I14,I15,NA())),NA()) -> #N/A | Y2: =IF(J15<>"",IF($F14="Higher the better",IF(J15<J14,J15,NA()),IF(J15>J14,J15,NA())),NA()) -> 9 | Z2: =IF(K15<>"",IF($F14="Higher the better",IF(K15<K14,K15,NA()),IF(K15>K14,K15,NA())),NA()) -> #N/A | AA2: =IF(L15<>"",IF($F14="Higher the better",IF(L15<L14,L15,NA()),IF(L15>L14,L15,NA())),NA()) -> #N/A | AB2: =IF(M15<>"",IF($F14="Higher the better",IF(M15<M14,M15,NA()),IF(M15>M14,M15,NA())),NA()) -> #N/A | AC2: =IF(N15<>"",IF($F14="Higher the better",IF(N15<N14,N15,NA()),IF(N15>N14,N15,NA())),NA()) -> #N/A | AD2: =IF(O15<>"",IF($F14="Higher the better",IF(O15<O14,O15,NA()),IF(O15>O14,O15,NA())),NA()) -> #N/A | AE2: =IF(P15<>"",IF($F14="Higher the better",IF(P15<P14,P15,NA()),IF(P15>P14,P15,NA())),NA()) -> #N/A | ... AI2: =IF(T15<>"",IF($F14="Higher the better",IF(T15<T14,T15,NA()),IF(T15>T14,T15,NA())),NA()) -> #N/A
A3: Procurement DMB | W3: Actual green | X3: =IF(I17<>"",IF($F16="Higher the better",IF(I17>=I16,I17,NA()),IF(I17<=I16,I17,NA())),NA()) -> 5 | Y3: =IF(J17<>"",IF($F16="Higher the better",IF(J17>=J16,J17,NA()),IF(J17<=J16,J17,NA())),NA()) -> #N/A | Z3: =IF(K17<>"",IF($F16="Higher the better",IF(K17>=K16,K17,NA()),IF(K17<=K16,K17,NA())),NA()) -> - | AA3: =IF(L17<>"",IF($F16="Higher the better",IF(L17>=L16,L17,NA()),IF(L17<=L16,L17,NA())),NA()) -> - | AB3: =IF(M17<>"",IF($F16="Higher the better",IF(M17>=M16,M17,NA()),IF(M17<=M16,M17,NA())),NA()) -> - | AC3: =IF(N17<>"",IF($F16="Higher the better",IF(N17>=N16,N17,NA()),IF(N17<=N16,N17,NA())),NA()) -> - | AD3: =IF(O17<>"",IF($F16="Higher the better",IF(O17>=O16,O17,NA()),IF(O17<=O16,O17,NA())),NA()) -> 0 | AE3: =IF(P17<>"",IF($F16="Higher the better",IF(P17>=P16,P17,NA()),IF(P17<=P16,P17,NA())),NA()) -> #N/A | ... AI3: =IF(T17<>"",IF($F16="Higher the better",IF(T17>=T16,T17,NA()),IF(T17<=T16,T17,NA())),NA()) -> #N/A
A4: Mandatory Outcome KPI's (1-3) | W4: Actual red | X4: =IF(I17<>"",IF($F16="Higher the better",IF(I17<I16,I17,NA()),IF(I17>I16,I17,NA())),NA()) -> #N/A | Y4: =IF(J17<>"",IF($F16="Higher the better",IF(J17<J16,J17,NA()),IF(J17>J16,J17,NA())),NA()) -> 7 | Z4: =IF(K17<>"",IF($F16="Higher the better",IF(K17<K16,K17,NA()),IF(K17>K16,K17,NA())),NA()) -> #N/A | AA4: =IF(L17<>"",IF($F16="Higher the better",IF(L17<L16,L17,NA()),IF(L17>L16,L17,NA())),NA()) -> #N/A | AB4: =IF(M17<>"",IF($F16="Higher the better",IF(M17<M16,M17,NA()),IF(M17>M16,M17,NA())),NA()) -> #N/A | AC4: =IF(N17<>"",IF($F16="Higher the better",IF(N17<N16,N17,NA()),IF(N17>N16,N17,NA())),NA()) -> #N/A | AD4: =IF(O17<>"",IF($F16="Higher the better",IF(O17<O16,O17,NA()),IF(O17>O16,O17,NA())),NA()) -> #N/A | AE4: =IF(P17<>"",IF($F16="Higher the better",IF(P17<P16,P17,NA()),IF(P17>P16,P17,NA())),NA()) -> #N/A | ... AI4: =IF(T17<>"",IF($F16="Higher the better",IF(T17<T16,T17,NA()),IF(T17>T16,T17,NA())),NA()) -> #N/A
A5: Mandatory KPI | B5: KPI Definition | C5: Operators | D5: Target AOP 2026 | E5: Units | F5: Metric nature | G5: Frequency | H5: Target/ Actual | I5: 46023 | J5: 46054 | K5: 46082 | L5: 46113 | M5: 46143 | N5: 46174 | O5: 46204 | P5: 46235 | Q5: 46266 | R5: 46296 | S5: 46327 | T5: 46357 | W5: Actual green | X5: =IF(I19<>"",IF($F18="Higher the better",IF(I19>=I18,I19,NA()),IF(I19<=I18,I19,NA())),NA()) -> 0.93 | Y5: =IF(J19<>"",IF($F18="Higher the better",IF(J19>=J18,J19,NA()),IF(J19<=J18,J19,NA())),NA()) -> 0.89 | Z5: =IF(K19<>"",IF($F18="Higher the better",IF(K19>=K18,K19,NA()),IF(K19<=K18,K19,NA())),NA()) -> 0.88 | AA5: =IF(L19<>"",IF($F18="Higher the better",IF(L19>=L18,L19,NA()),IF(L19<=L18,L19,NA())),NA()) -> 0.84 | AB5: =IF(M19<>"",IF($F18="Higher the better",IF(M19>=M18,M19,NA()),IF(M19<=M18,M19,NA())),NA()) -> 0.93 | AC5: =IF(N19<>"",IF($F18="Higher the better",IF(N19>=N18,N19,NA()),IF(N19<=N18,N19,NA())),NA()) -> 0.93 | AD5: =IF(O19<>"",IF($F18="Higher the better",IF(O19>=O18,O19,NA()),IF(O19<=O18,O19,NA())),NA()) -> 1 | AE5: =IF(P19<>"",IF($F18="Higher the better",IF(P19>=P18,P19,NA()),IF(P19<=P18,P19,NA())),NA()) -> #N/A | ... AI5: =IF(T19<>"",IF($F18="Higher the better",IF(T19>=T18,T19,NA()),IF(T19<=T18,T19,NA())),NA()) -> #N/A
A6: Productivity ( Nego) | B6: 1% of Spend | C6: <= | D6: 0.4 M € 0.7 M € Stretch | E6: % | F6: Higher the better | G6: Monthly | H6: Target | I6: 0.035 | J6: =I6+0.035 -> 0.07 | K6: =J6+0.035 -> 0.105 | L6: =K6+0.035 -> 0.14 | M6: =L6+0.035 -> 0.175 | N6: =M6+0.035 -> 0.21 | O6: 0.23 | P6: =O6+0.035 -> 0.265 | Q6: =P6+0.035 -> 0.3 | R6: =Q6+0.035 -> 0.335 | S6: =R6+0.035 -> 0.37 | T6: 0.4 | W6: Actual red | X6: =IF(I19<>"",IF($F18="Higher the better",IF(I19<I18,I19,NA()),IF(I19>I18,I19,NA())),NA()) -> #N/A | Y6: =IF(J19<>"",IF($F18="Higher the better",IF(J19<J18,J19,NA()),IF(J19>J18,J19,NA())),NA()) -> #N/A | Z6: =IF(K19<>"",IF($F18="Higher the better",IF(K19<K18,K19,NA()),IF(K19>K18,K19,NA())),NA()) -> #N/A | AA6: =IF(L19<>"",IF($F18="Higher the better",IF(L19<L18,L19,NA()),IF(L19>L18,L19,NA())),NA()) -> #N/A | AB6: =IF(M19<>"",IF($F18="Higher the better",IF(M19<M18,M19,NA()),IF(M19>M18,M19,NA())),NA()) -> #N/A | AC6: =IF(N19<>"",IF($F18="Higher the better",IF(N19<N18,N19,NA()),IF(N19>N18,N19,NA())),NA()) -> #N/A | AD6: =IF(O19<>"",IF($F18="Higher the better",IF(O19<O18,O19,NA()),IF(O19>O18,O19,NA())),NA()) -> #N/A | AE6: =IF(P19<>"",IF($F18="Higher the better",IF(P19<P18,P19,NA()),IF(P19>P18,P19,NA())),NA()) -> #N/A | ... AI6: =IF(T19<>"",IF($F18="Higher the better",IF(T19<T18,T19,NA()),IF(T19>T18,T19,NA())),NA()) -> #N/A
H7: Actual | I7: =20673/1000000 -> 0.020673 | J7: =(38099/1000000)+I7 -> 0.058772 | K7: =J7+(46887/1000000) -> 0.105659 | L7: =K7+(46763/1000000) -> 0.152422 | M7: 0.19 | N7: 0.21 | O7: 0.23 | W7: Actual green | X7: =IF(I21<>"",IF($F20="Higher the better",IF(I21>=I20,I21,NA()),IF(I21<=I20,I21,NA())),NA()) -> #N/A | Y7: =IF(J21<>"",IF($F20="Higher the better",IF(J21>=J20,J21,NA()),IF(J21<=J20,J21,NA())),NA()) -> #N/A | Z7: =IF(K21<>"",IF($F20="Higher the better",IF(K21>=K20,K21,NA()),IF(K21<=K20,K21,NA())),NA()) -> #N/A | AA7: =IF(L21<>"",IF($F20="Higher the better",IF(L21>=L20,L21,NA()),IF(L21<=L20,L21,NA())),NA()) -> #N/A | AB7: =IF(M21<>"",IF($F20="Higher the better",IF(M21>=M20,M21,NA()),IF(M21<=M20,M21,NA())),NA()) -> #N/A | AC7: =IF(N21<>"",IF($F20="Higher the better",IF(N21>=N20,N21,NA()),IF(N21<=N20,N21,NA())),NA()) -> #N/A | AD7: =IF(O21<>"",IF($F20="Higher the better",IF(O21>=O20,O21,NA()),IF(O21<=O20,O21,NA())),NA()) -> #N/A | AE7: =IF(P21<>"",IF($F20="Higher the better",IF(P21>=P20,P21,NA()),IF(P21<=P20,P21,NA())),NA()) -> #N/A | ... AI7: =IF(T21<>"",IF($F20="Higher the better",IF(T21>=T20,T21,NA()),IF(T21<=T20,T21,NA())),NA()) -> #N/A
A8: Material Availability (escalation) | B8: Clear to build material avaialbility | C8: >= | D8: 0.9 | E8: % | F8: Higher the better | G8: Monthly | H8: Target | I8: 0.9 | J8: 0.9 | K8: 0.9 | L8: 0.9 | M8: 0.9 | N8: 0.9 | O8: 0.9 | P8: 0.9 | Q8: 0.9 | R8: 0.9 | S8: 0.9 | T8: 0.9 | W8: Actual red | X8: =IF(I21<>"",IF($F20="Higher the better",IF(I21<I20,I21,NA()),IF(I21>I20,I21,NA())),NA()) -> #N/A | Y8: =IF(J21<>"",IF($F20="Higher the better",IF(J21<J20,J21,NA()),IF(J21>J20,J21,NA())),NA()) -> #N/A | Z8: =IF(K21<>"",IF($F20="Higher the better",IF(K21<K20,K21,NA()),IF(K21>K20,K21,NA())),NA()) -> #N/A | AA8: =IF(L21<>"",IF($F20="Higher the better",IF(L21<L20,L21,NA()),IF(L21>L20,L21,NA())),NA()) -> #N/A | AB8: =IF(M21<>"",IF($F20="Higher the better",IF(M21<M20,M21,NA()),IF(M21>M20,M21,NA())),NA()) -> #N/A | AC8: =IF(N21<>"",IF($F20="Higher the better",IF(N21<N20,N21,NA()),IF(N21>N20,N21,NA())),NA()) -> #N/A | AD8: =IF(O21<>"",IF($F20="Higher the better",IF(O21<O20,O21,NA()),IF(O21>O20,O21,NA())),NA()) -> #N/A | AE8: =IF(P21<>"",IF($F20="Higher the better",IF(P21<P20,P21,NA()),IF(P21>P20,P21,NA())),NA()) -> #N/A | ... AI8: =IF(T21<>"",IF($F20="Higher the better",IF(T21<T20,T21,NA()),IF(T21>T20,T21,NA())),NA()) -> #N/A
H9: Actual | I9: 1 | J9: 1 | K9: 1 | L9: 0.88 | M9: 0.93 | N9: =6/7 -> 0.85714286 | O9: 1
A10: NPI / MLD | B10: NPI gate readiness | C10: = | D10: 1 | E10: % | F10: Higher the better | G10: Monthly | H10: Target | I10: 0 | J10: 0 | K10: 0 | L10: 1 | M10: 0 | N10: 0 | O10: 1 | P10: 1 | Q10: 0 | R10: 0 | S10: 0 | T10: 0
H11: Actual | I11: - | J11: - | K11: - | L11: - | M11: - | N11: - | O11: 1
A12: Critical Enabling/Leading KPI's (3-5)
A13: KPI Name | B13: KPI Definition | C13: Operators | D13: Target AOP 2026 | E13: Units | F13: Metric nature | G13: Frequency | H13: Target/ Actual | I13: 46023 | J13: 46054 | K13: 46082 | L13: 46113 | M13: 46143 | N13: 46174 | O13: 46204 | P13: 46235 | Q13: 46266 | R13: 46296 | S13: 46327 | T13: 46357
A14: RFQ closure to meet NPI / MLD deliverables | B14: No of RFQ closed on time | C14: <= | D14: 1 | E14: % | F14: Higher the better | G14: Monthly | H14: Target | I14: 15 | J14: 10 | K14: 15 | L14: 22 | M14: 1 | N14: 10 | O14: 1 | P14: 0 | Q14: 0 | R14: 0 | S14: 0 | T14: 0
H15: Actual | I15: 15 | J15: 9 | K15: 15 | L15: 22 | M15: 1 | N15: 10 | O15: 1
A16: Supplier selection to meet NPI / MLD deliverables | B16: supplier selection per 12 NC for NPI | C16: <= | D16: 1 | E16: % | F16: Higher the better | G16: Monthly | H16: Target | I16: 5 | J16: 8 | K16: 0 | L16: 0 | M16: 0 | N16: 0 | O16: 0 | P16: 0 | Q16: 0 | R16: 0 | S16: 0 | T16: 0
H17: Actual | I17: 5 | J17: 7 | K17: - | L17: - | M17: - | N17: - | O17: 0
A18: CTB (12 weeks) | B18: Clear to build material avaialbility | C18: <= | D18: 0.8 | E18: % | F18: Higher the better | G18: Monthly | H18: Target | I18: 0.8 | J18: 0.8 | K18: 0.8 | L18: 0.8 | M18: 0.8 | N18: 0.8 | O18: 0.8 | P18: 0.8 | Q18: 0.8 | R18: 0.8 | S18: 0.8 | T18: 0.8
H19: Actual | I19: 0.93 | J19: 0.89 | K19: 0.88 | L19: 0.84 | M19: 0.93 | N19: 0.93 | O19: 1
